Workbook

Sheet HOME
B1: =Settings!$B$4 -> Gulf Star Manpower Services LLC
B2: ="Manpower Management System | Payroll month: "&TEXT(Settings!$B$8,"mmmm yyyy") -> Manpower Management System | Payroll month: October 2026
B4: Client Billing (AED) | F4: Gross Profit (AED) | J4: Net Salary to Pay - WPS (AED)
B5: =Dashboard!$B$4 -> 324858.76 | F5: =Dashboard!$B$7 -> 136300.32 | J5: =Dashboard!$B$15 -> 87430.82
B6: =IF(Dashboard!$B$18+Dashboard!$B$19=0,"All visas / Emirates IDs OK","WARNING: "&Dashboard!$B$18&" documents EXPIRED, "&Dashboard!$B$19&" expiring soon - open Workers") -> WARNING: 6 documents EXPIRED, 12 expiring soon - open Workers
B8: 1. ENTER DATA
B9: Timesheet | F9: Deductions | J9: Workers
B11: Client hours each month | F11: Advances, fines | J11: Add / edit workers
B13: 2. MASTER DATA
B14: Clients | F14: Suppliers | J14: Client Rates
B16: Customers | F16: Manpower agencies | J16: Selling rate / hr
B18: Supplier Rates | F18: Settings | J18: Help
B20: Cost rate / hr | F20: Month, OT, VAT | J20: How it works
B22: 3. REPORTS & PRINT
B23: Dashboard | F23: Payroll | J23: Payslip
B25: Profit & KPIs | F25: Salary sheet | J25: Print payslip
B27: Client Invoice | F27: Supplier Payment | J27: WPS File
B29: Tax invoice | F29: Amount payable | J29: Bank salary file
B31: Click any tile to open. Every sheet has a « HOME link at the top right to come back.

Sheet README
A1: Manpower Management System - Excel Demo | C1: « HOME
A2: Own workers + supplier workers -> clients -> timesheet -> payroll, supplier payment, client invoice
A4: HOW THE FLOW WORKS
A5: 1. Settings | B5: Choose the payroll month and company rules (OT rate, VAT, working days).
A6: 2. Clients / Suppliers | B6: Master list of customers and manpower suppliers (one row each).
A7: 3. ClientRates | B7: What you CHARGE each client per hour, per trade (normal + OT).
A8: 4. SupplierRates | B8: What each supplier CHARGES YOU per hour, per trade (normal + OT).
A9: 5. Workers | B9: Every worker: Source = Own or Supplier. Own workers have salary, IBAN, labour card.
A10: 6. Timesheet | B10: Monthly hours received from the client. ONLY enter columns A-H; the rest is calculated.
A11: 7. Deductions | B11: Salary advances, fines, accommodation etc. for own workers.
A13: AUTOMATIC OUTPUT SHEETS
A14: Dashboard | B14: Month KPIs: billing, supplier cost, own payroll, profit, profit per client, document alerts.
A15: Payroll | B15: Own workers' salary for the month (fixed, hourly, OT, deductions, net pay).
A16: Payslip | B16: Pick a Worker ID in cell C4 -> printable payslip.
A17: ClientInvoice | B17: Pick a Client ID in cell C4 -> tax invoice with trade-wise hours and 5% VAT.
A18: SupplierStatement | B18: How much to pay each supplier this month, incl. VAT and due date.
A19: WPS_SIF | B19: Salary rows in WPS SIF layout (EDR + SCR). Confirm exact format with your bank/exchange.
A21: COLOUR LEGEND
A22: Blue text / yellow cell | B22: Input - type here.
A23: Black text | B23: Formula - do not overwrite.
A24: Dark blue header | B24: Input column. Light blue header = calculated column.
A25: Red row | B25: Visa / Emirates ID expired or expiring within the alert days (Settings).
A27: MONTHLY ROUTINE
A28: Step 1 | B28: Settings!B8 -> set the month (1st day of month).
A29: Step 2 | B29: Paste/enter client timesheets in Timesheet (Month, Client, Site, Worker ID, Days, Hours, OT).
A30: Step 3 | B30: Enter advances / fines in Deductions.
A31: Step 4 | B31: Check Dashboard -> print Payslips, ClientInvoice, SupplierStatement, export WPS_SIF.
A33: ASSUMPTIONS (change in Settings)
A34: Monthly salary | B34: Absent days = Standard working days - Days worked; deduction = (Basic+Allowances)/30 x absent days.
A35: Overtime | B35: UAE practice: OT hourly = Basic/30/8 x 1.25 (multiplier editable). Hourly workers: rate x 1.25.
A36: Own worker cost per hour | B36: Used for profit per client = (Basic+Allowances)/(Std days x hours per day).
A37: Sample data | B37: All names, companies, IDs and rates are fictional examples.

Sheet Dashboard
A1: Dashboard | D1: « HOME
A2: ="Month: "&TEXT(Settings!$B$8,"mmmm yyyy") -> Month: October 2026 | D2: Profit by Client (this month)
A3: (change month in Settings!B8) | D3: Client ID | E3: Client Name | F3: Lines | G3: Billing (AED) | H3: Supplier Cost | I3: Own Cost Est. | J3: Profit (AED) | K3: Margin %
A4: Client Billing (excl. VAT) | B4: =SUMIFS(Timesheet!$O$5:$O$3004,Timesheet!$A$5:$A$3004,">="&Settings!$B$8,Timesheet!$A$5:$A$3004,"<="&Settings!$B$9) -> 324858.76 | D4: =IF(Clients!A5="","",Clients!A5) -> C001 | E4: =IF($D4="","",Clients!B5) -> Al Waha Contracting LLC | F4: =IF($D4="","",COUNTIFS(Timesheet!$B$5:$B$3004,$D4,Timesheet!$A$5:$A$3004,">="&Settings!$B$8,Timesheet!$A$5:$A$3004,"<="&Settings!$B$9)) -> 23 | G4: =IF($D4="","",SUMIFS(Timesheet!$O$5:$O$3004,Timesheet!$B$5:$B$3004,$D4,Timesheet!$A$5:$A$3004,">="&Settings!$B$8,Timesheet!$A$5:$A$3004,"<="&Settings!$B$9)) -> 97921 | H4: =IF($D4="","",SUMIFS(Timesheet!$R$5:$R$3004,Timesheet!$B$5:$B$3004,$D4,Timesheet!$A$5:$A$3004,">="&Settings!$B$8,Timesheet!$A$5:$A$3004,"<="&Settings!$B$9)) -> 31153.9 | I4: =IF($D4="","",SUMIFS(Timesheet!$S$5:$S$3004,Timesheet!$B$5:$B$3004,$D4,Timesheet!$A$5:$A$3004,">="&Settings!$B$8,Timesheet!$A$5:$A$3004,"<="&Settings!$B$9)) -> 26384.087 | J4: =IF($D4="","",G4-H4-I4) -> 40383.013 | K4: =IF(OR($D4="",N(G4)=0),"",J4/G4) -> 0.41240401
A5: Supplier Cost (excl. VAT) | B5: =SUMIFS(Timesheet!$R$5:$R$3004,Timesheet!$A$5:$A$3004,">="&Settings!$B$8,Timesheet!$A$5:$A$3004,"<="&Settings!$B$9) -> 99352.62 | D5: =IF(Clients!A6="","",Clients!A6) -> C002 | E5: =IF($D5="","",Clients!B6) -> Blue Creek Facilities Mgmt | F5: =IF($D5="","",COUNTIFS(Timesheet!$B$5:$B$3004,$D5,Timesheet!$A$5:$A$3004,">="&Settings!$B$8,Timesheet!$A$5:$A$3004,"<="&Settings!$B$9)) -> 19 | G5: =IF($D5="","",SUMIFS(Timesheet!$O$5:$O$3004,Timesheet!$B$5:$B$3004,$D5,Timesheet!$A$5:$A$3004,">="&Settings!$B$8,Timesheet!$A$5:$A$3004,"<="&Settings!$B$9)) -> 95547.14 | H5: =IF($D5="","",SUMIFS(Timesheet!$R$5:$R$3004,Timesheet!$B$5:$B$3004,$D5,Timesheet!$A$5:$A$3004,">="&Settings!$B$8,Timesheet!$A$5:$A$3004,"<="&Settings!$B$9)) -> 24791.58 | I5: =IF($D5="","",SUMIFS(Timesheet!$S$5:$S$3004,Timesheet!$B$5:$B$3004,$D5,Timesheet!$A$5:$A$3004,">="&Settings!$B$8,Timesheet!$A$5:$A$3004,"<="&Settings!$B$9)) -> 26544.837 | J5: =IF($D5="","",G5-H5-I5) -> 44210.723 | K5: =IF(OR($D5="",N(G5)=0),"",J5/G5) -> 0.46271111
A6: Own Workers Payroll (Gross) | B6: =Payroll!$N$3 -> 89205.82 | D6: =IF(Clients!A7="","",Clients!A7) -> C003 | E6: =IF($D6="","",Clients!B7) -> Sandline Construction Co. | F6: =IF($D6="","",COUNTIFS(Timesheet!$B$5:$B$3004,$D6,Timesheet!$A$5:$A$3004,">="&Settings!$B$8,Timesheet!$A$5:$A$3004,"<="&Settings!$B$9)) -> 19 | G6: =IF($D6="","",SUMIFS(Timesheet!$O$5:$O$3004,Timesheet!$B$5:$B$3004,$D6,Timesheet!$A$5:$A$3004,">="&Settings!$B$8,Timesheet!$A$5:$A$3004,"<="&Settings!$B$9)) -> 73433.96 | H6: =IF($D6="","",SUMIFS(Timesheet!$R$5:$R$3004,Timesheet!$B$5:$B$3004,$D6,Timesheet!$A$5:$A$3004,">="&Settings!$B$8,Timesheet!$A$5:$A$3004,"<="&Settings!$B$9)) -> 23265.76 | I6: =IF($D6="","",SUMIFS(Timesheet!$S$5:$S$3004,Timesheet!$B$5:$B$3004,$D6,Timesheet!$A$5:$A$3004,">="&Settings!$B$8,Timesheet!$A$5:$A$3004,"<="&Settings!$B$9)) -> 23818.75 | J6: =IF($D6="","",G6-H6-I6) -> 26349.45 | K6: =IF(OR($D6="",N(G6)=0),"",J6/G6) -> 0.35881832
A7: GROSS PROFIT | B7: =B4-B5-B6 -> 136300.32 | D7: =IF(Clients!A8="","",Clients!A8) -> C004 | E7: =IF($D7="","",Clients!B8) -> Marina Hospitality Group | F7: =IF($D7="","",COUNTIFS(Timesheet!$B$5:$B$3004,$D7,Timesheet!$A$5:$A$3004,">="&Settings!$B$8,Timesheet!$A$5:$A$3004,"<="&Settings!$B$9)) -> 13 | G7: =IF($D7="","",SUMIFS(Timesheet!$O$5:$O$3004,Timesheet!$B$5:$B$3004,$D7,Timesheet!$A$5:$A$3004,">="&Settings!$B$8,Timesheet!$A$5:$A$3004,"<="&Settings!$B$9)) -> 57956.66 | H7: =IF($D7="","",SUMIFS(Timesheet!$R$5:$R$3004,Timesheet!$B$5:$B$3004,$D7,Timesheet!$A$5:$A$3004,">="&Settings!$B$8,Timesheet!$A$5:$A$3004,"<="&Settings!$B$9)) -> 20141.38 | I7: =IF($D7="","",SUMIFS(Timesheet!$S$5:$S$3004,Timesheet!$B$5:$B$3004,$D7,Timesheet!$A$5:$A$3004,">="&Settings!$B$8,Timesheet!$A$5:$A$3004,"<="&Settings!$B$9)) -> 14190.154 | J7: =IF($D7="","",G7-H7-I7) -> 23625.126 | K7: =IF(OR($D7="",N(G7)=0),"",J7/G7) -> 0.40763436
A8: Gross Margin % | B8: =IF(B4=0,0,B7/B4) -> 0.41956794 | D8: =IF(Clients!A9="","",Clients!A9) | E8: =IF($D8="","",Clients!B9) | F8: =IF($D8="","",COUNTIFS(Timesheet!$B$5:$B$3004,$D8,Timesheet!$A$5:$A$3004,">="&Settings!$B$8,Timesheet!$A$5:$A$3004,"<="&Settings!$B$9)) | G8: =IF($D8="","",SUMIFS(Timesheet!$O$5:$O$3004,Timesheet!$B$5:$B$3004,$D8,Timesheet!$A$5:$A$3004,">="&Settings!$B$8,Timesheet!$A$5:$A$3004,"<="&Settings!$B$9)) | H8: =IF($D8="","",SUMIFS(Timesheet!$R$5:$R$3004,Timesheet!$B$5:$B$3004,$D8,Timesheet!$A$5:$A$3004,">="&Settings!$B$8,Timesheet!$A$5:$A$3004,"<="&Settings!$B$9)) | I8: =IF($D8="","",SUMIFS(Timesheet!$S$5:$S$3004,Timesheet!$B$5:$B$3004,$D8,Timesheet!$A$5:$A$3004,">="&Settings!$B$8,Timesheet!$A$5:$A$3004,"<="&Settings!$B$9)) | J8: =IF($D8="","",G8-H8-I8) | K8: =IF(OR($D8="",N(G8)=0),"",J8/G8)
A9: VAT Output (on billing) | B9: =ROUND(B4*Settings!$B$14,2) -> 16242.94 | D9: =IF(Clients!A10="","",Clients!A10) | E9: =IF($D9="","",Clients!B10) | F9: =IF($D9="","",COUNTIFS(Timesheet!$B$5:$B$3004,$D9,Timesheet!$A$5:$A$3004,">="&Settings!$B$8,Timesheet!$A$5:$A$3004,"<="&Settings!$B$9)) | G9: =IF($D9="","",SUMIFS(Timesheet!$O$5:$O$3004,Timesheet!$B$5:$B$3004,$D9,Timesheet!$A$5:$A$3004,">="&Settings!$B$8,Timesheet!$A$5:$A$3004,"<="&Settings!$B$9)) | H9: =IF($D9="","",SUMIFS(Timesheet!$R$5:$R$3004,Timesheet!$B$5:$B$3004,$D9,Timesheet!$A$5:$A$3004,">="&Settings!$B$8,Timesheet!$A$5:$A$3004,"<="&Settings!$B$9)) | I9: =IF($D9="","",SUMIFS(Timesheet!$S$5:$S$3004,Timesheet!$B$5:$B$3004,$D9,Timesheet!$A$5:$A$3004,">="&Settings!$B$8,Timesheet!$A$5:$A$3004,"<="&Settings!$B$9)) | J9: =IF($D9="","",G9-H9-I9) | K9: =IF(OR($D9="",N(G9)=0),"",J9/G9)
D10: =IF(Clients!A11="","",Clients!A11) | E10: =IF($D10="","",Clients!B11) | F10: =IF($D10="","",COUNTIFS(Timesheet!$B$5:$B$3004,$D10,Timesheet!$A$5:$A$3004,">="&Settings!$B$8,Timesheet!$A$5:$A$3004,"<="&Settings!$B$9)) | G10: =IF($D10="","",SUMIFS(Timesheet!$O$5:$O$3004,Timesheet!$B$5:$B$3004,$D10,Timesheet!$A$5:$A$3004,">="&Settings!$B$8,Timesheet!$A$5:$A$3004,"<="&Settings!$B$9)) | H10: =IF($D10="","",SUMIFS(Timesheet!$R$5:$R$3004,Timesheet!$B$5:$B$3004,$D10,Timesheet!$A$5:$A$3004,">="&Settings!$B$8,Timesheet!$A$5:$A$3004,"<="&Settings!$B$9)) | I10: =IF($D10="","",SUMIFS(Timesheet!$S$5:$S$3004,Timesheet!$B$5:$B$3004,$D10,Timesheet!$A$5:$A$3004,">="&Settings!$B$8,Timesheet!$A$5:$A$3004,"<="&Settings!$B$9)) | J10: =IF($D10="","",G10-H10-I10) | K10: =IF(OR($D10="",N(G10)=0),"",J10/G10)
A11: Total Billable Hours | B11: =SUMIFS(Timesheet!$F$5:$F$3004,Timesheet!$A$5:$A$3004,">="&Settings!$B$8,Timesheet!$A$5:$A$3004,"<="&Settings!$B$9)+SUMIFS(Timesheet!$G$5:$G$3004,Timesheet!$A$5:$A$3004,">="&Settings!$B$8,Timesheet!$A$5:$A$3004,"<="&Settings!$B$9) -> 14600 | D11: =IF(Clients!A12="","",Clients!A12) | E11: =IF($D11="","",Clients!B12) | F11: =IF($D11="","",COUNTIFS(Timesheet!$B$5:$B$3004,$D11,Timesheet!$A$5:$A$3004,">="&Settings!$B$8,Timesheet!$A$5:$A$3004,"<="&Settings!$B$9)) | G11: =IF($D11="","",SUMIFS(Timesheet!$O$5:$O$3004,Timesheet!$B$5:$B$3004,$D11,Timesheet!$A$5:$A$3004,">="&Settings!$B$8,Timesheet!$A$5:$A$3004,"<="&Settings!$B$9)) | H11: =IF($D11="","",SUMIFS(Timesheet!$R$5:$R$3004,Timesheet!$B$5:$B$3004,$D11,Timesheet!$A$5:$A$3004,">="&Settings!$B$8,Timesheet!$A$5:$A$3004,"<="&Settings!$B$9)) | I11: =IF($D11="","",SUMIFS(Timesheet!$S$5:$S$3004,Timesheet!$B$5:$B$3004,$D11,Timesheet!$A$5:$A$3004,">="&Settings!$B$8,Timesheet!$A$5:$A$3004,"<="&Settings!$B$9)) | J11: =IF($D11="","",G11-H11-I11) | K11: =IF(OR($D11="",N(G11)=0),"",J11/G11)
A12: Timesheet Lines (this month) | B12: =COUNTIFS(Timesheet!$A$5:$A$3004,">="&Settings!$B$8,Timesheet!$A$5:$A$3004,"<="&Settings!$B$9) -> 74 | D12: =IF(Clients!A13="","",Clients!A13) | E12: =IF($D12="","",Clients!B13) | F12: =IF($D12="","",COUNTIFS(Timesheet!$B$5:$B$3004,$D12,Timesheet!$A$5:$A$3004,">="&Settings!$B$8,Timesheet!$A$5:$A$3004,"<="&Settings!$B$9)) | G12: =IF($D12="","",SUMIFS(Timesheet!$O$5:$O$3004,Timesheet!$B$5:$B$3004,$D12,Timesheet!$A$5:$A$3004,">="&Settings!$B$8,Timesheet!$A$5:$A$3004,"<="&Settings!$B$9)) | H12: =IF($D12="","",SUMIFS(Timesheet!$R$5:$R$3004,Timesheet!$B$5:$B$3004,$D12,Timesheet!$A$5:$A$3004,">="&Settings!$B$8,Timesheet!$A$5:$A$3004,"<="&Settings!$B$9)) | I12: =IF($D12="","",SUMIFS(Timesheet!$S$5:$S$3004,Timesheet!$B$5:$B$3004,$D12,Timesheet!$A$5:$A$3004,">="&Settings!$B$8,Timesheet!$A$5:$A$3004,"<="&Settings!$B$9)) | J12: =IF($D12="","",G12-H12-I12) | K12: =IF(OR($D12="",N(G12)=0),"",J12/G12)
A13: Active Own Workers | B13: =COUNTIFS(Workers!$C$5:$C$2004,"Own",Workers!$Q$5:$Q$2004,"Active") -> 40 | D13: =IF(Clients!A14="","",Clients!A14) | E13: =IF($D13="","",Clients!B14) | F13: =IF($D13="","",COUNTIFS(Timesheet!$B$5:$B$3004,$D13,Timesheet!$A$5:$A$3004,">="&Settings!$B$8,Timesheet!$A$5:$A$3004,"<="&Settings!$B$9)) | G13: =IF($D13="","",SUMIFS(Timesheet!$O$5:$O$3004,Timesheet!$B$5:$B$3004,$D13,Timesheet!$A$5:$A$3004,">="&Settings!$B$8,Timesheet!$A$5:$A$3004,"<="&Settings!$B$9)) | H13: =IF($D13="","",SUMIFS(Timesheet!$R$5:$R$3004,Timesheet!$B$5:$B$3004,$D13,Timesheet!$A$5:$A$3004,">="&Settings!$B$8,Timesheet!$A$5:$A$3004,"<="&Settings!$B$9)) | I13: =IF($D13="","",SUMIFS(Timesheet!$S$5:$S$3004,Timesheet!$B$5:$B$3004,$D13,Timesheet!$A$5:$A$3004,">="&Settings!$B$8,Timesheet!$A$5:$A$3004,"<="&Settings!$B$9)) | J13: =IF($D13="","",G13-H13-I13) | K13: =IF(OR($D13="",N(G13)=0),"",J13/G13)
A14: Active Supplier Workers | B14: =COUNTIFS(Workers!$C$5:$C$2004,"Supplier",Workers!$Q$5:$Q$2004,"Active") -> 30 | D14: =IF(Clients!A15="","",Clients!A15) | E14: =IF($D14="","",Clients!B15) | F14: =IF($D14="","",COUNTIFS(Timesheet!$B$5:$B$3004,$D14,Timesheet!$A$5:$A$3004,">="&Settings!$B$8,Timesheet!$A$5:$A$3004,"<="&Settings!$B$9)) | G14: =IF($D14="","",SUMIFS(Timesheet!$O$5:$O$3004,Timesheet!$B$5:$B$3004,$D14,Timesheet!$A$5:$A$3004,">="&Settings!$B$8,Timesheet!$A$5:$A$3004,"<="&Settings!$B$9)) | H14: =IF($D14="","",SUMIFS(Timesheet!$R$5:$R$3004,Timesheet!$B$5:$B$3004,$D14,Timesheet!$A$5:$A$3004,">="&Settings!$B$8,Timesheet!$A$5:$A$3004,"<="&Settings!$B$9)) | I14: =IF($D14="","",SUMIFS(Timesheet!$S$5:$S$3004,Timesheet!$B$5:$B$3004,$D14,Timesheet!$A$5:$A$3004,">="&Settings!$B$8,Timesheet!$A$5:$A$3004,"<="&Settings!$B$9)) | J14: =IF($D14="","",G14-H14-I14) | K14: =IF(OR($D14="",N(G14)=0),"",J14/G14)
A15: Net Salary to Pay (WPS) | B15: =Payroll!$R$3 -> 87430.82 | D15: =IF(Clients!A16="","",Clients!A16) | E15: =IF($D15="","",Clients!B16) | F15: =IF($D15="","",COUNTIFS(Timesheet!$B$5:$B$3004,$D15,Timesheet!$A$5:$A$3004,">="&Settings!$B$8,Timesheet!$A$5:$A$3004,"<="&Settings!$B$9)) | G15: =IF($D15="","",SUMIFS(Timesheet!$O$5:$O$3004,Timesheet!$B$5:$B$3004,$D15,Timesheet!$A$5:$A$3004,">="&Settings!$B$8,Timesheet!$A$5:$A$3004,"<="&Settings!$B$9)) | H15: =IF($D15="","",SUMIFS(Timesheet!$R$5:$R$3004,Timesheet!$B$5:$B$3004,$D15,Timesheet!$A$5:$A$3004,">="&Settings!$B$8,Timesheet!$A$5:$A$3004,"<="&Settings!$B$9)) | I15: =IF($D15="","",SUMIFS(Timesheet!$S$5:$S$3004,Timesheet!$B$5:$B$3004,$D15,Timesheet!$A$5:$A$3004,">="&Settings!$B$8,Timesheet!$A$5:$A$3004,"<="&Settings!$B$9)) | J15: =IF($D15="","",G15-H15-I15) | K15: =IF(OR($D15="",N(G15)=0),"",J15/G15)
A16: Payable to Suppliers (incl. VAT) | B16: =SupplierStatement!$I$3 -> 104320.25 | D16: =IF(Clients!A17="","",Clients!A17) | E16: =IF($D16="","",Clients!B17) | F16: =IF($D16="","",COUNTIFS(Timesheet!$B$5:$B$3004,$D16,Timesheet!$A$5:$A$3004,">="&Settings!$B$8,Timesheet!$A$5:$A$3004,"<="&Settings!$B$9)) | G16: =IF($D16="","",SUMIFS(Timesheet!$O$5:$O$3004,Timesheet!$B$5:$B$3004,$D16,Timesheet!$A$5:$A$3004,">="&Settings!$B$8,Timesheet!$A$5:$A$3004,"<="&Settings!$B$9)) | H16: =IF($D16="","",SUMIFS(Timesheet!$R$5:$R$3004,Timesheet!$B$5:$B$3004,$D16,Timesheet!$A$5:$A$3004,">="&Settings!$B$8,Timesheet!$A$5:$A$3004,"<="&Settings!$B$9)) | I16: =IF($D16="","",SUMIFS(Timesheet!$S$5:$S$3004,Timesheet!$B$5:$B$3004,$D16,Timesheet!$A$5:$A$3004,">="&Settings!$B$8,Timesheet!$A$5:$A$3004,"<="&Settings!$B$9)) | J16: =IF($D16="","",G16-H16-I16) | K16: =IF(OR($D16="",N(G16)=0),"",J16/G16)
D17: =IF(Clients!A18="","",Clients!A18) | E17: =IF($D17="","",Clients!B18) | F17: =IF($D17="","",COUNTIFS(Timesheet!$B$5:$B$3004,$D17,Timesheet!$A$5:$A$3004,">="&Settings!$B$8,Timesheet!$A$5:$A$3004,"<="&Settings!$B$9)) | G17: =IF($D17="","",SUMIFS(Timesheet!$O$5:$O$3004,Timesheet!$B$5:$B$3004,$D17,Timesheet!$A$5:$A$3004,">="&Settings!$B$8,Timesheet!$A$5:$A$3004,"<="&Settings!$B$9)) | H17: =IF($D17="","",SUMIFS(Timesheet!$R$5:$R$3004,Timesheet!$B$5:$B$3004,$D17,Timesheet!$A$5:$A$3004,">="&Settings!$B$8,Timesheet!$A$5:$A$3004,"<="&Settings!$B$9)) | I17: =IF($D17="","",SUMIFS(Timesheet!$S$5:$S$3004,Timesheet!$B$5:$B$3004,$D17,Timesheet!$A$5:$A$3004,">="&Settings!$B$8,Timesheet!$A$5:$A$3004,"<="&Settings!$B$9)) | J17: =IF($D17="","",G17-H17-I17) | K17: =IF(OR($D17="",N(G17)=0),"",J17/G17)
A18: Documents EXPIRED | B18: =COUNTIF(Workers!$T$5:$T$2004,"EXPIRED") -> 6 | D18: =IF(Clients!A19="","",Clients!A19) | E18: =IF($D18="","",Clients!B19) | F18: =IF($D18="","",COUNTIFS(Timesheet!$B$5:$B$3004,$D18,Timesheet!$A$5:$A$3004,">="&Settings!$B$8,Timesheet!$A$5:$A$3004,"<="&Settings!$B$9)) | G18: =IF($D18="","",SUMIFS(Timesheet!$O$5:$O$3004,Timesheet!$B$5:$B$3004,$D18,Timesheet!$A$5:$A$3004,">="&Settings!$B$8,Timesheet!$A$5:$A$3004,"<="&Settings!$B$9)) | H18: =IF($D18="","",SUMIFS(Timesheet!$R$5:$R$3004,Timesheet!$B$5:$B$3004,$D18,Timesheet!$A$5:$A$3004,">="&Settings!$B$8,Timesheet!$A$5:$A$3004,"<="&Settings!$B$9)) | I18: =IF($D18="","",SUMIFS(Timesheet!$S$5:$S$3004,Timesheet!$B$5:$B$3004,$D18,Timesheet!$A$5:$A$3004,">="&Settings!$B$8,Timesheet!$A$5:$A$3004,"<="&Settings!$B$9)) | J18: =IF($D18="","",G18-H18-I18) | K18: =IF(OR($D18="",N(G18)=0),"",J18/G18)
A19: Documents EXPIRING SOON | B19: =COUNTIF(Workers!$T$5:$T$2004,"EXPIRING SOON") -> 12 | D19: =IF(Clients!A20="","",Clients!A20) | E19: =IF($D19="","",Clients!B20) | F19: =IF($D19="","",COUNTIFS(Timesheet!$B$5:$B$3004,$D19,Timesheet!$A$5:$A$3004,">="&Settings!$B$8,Timesheet!$A$5:$A$3004,"<="&Settings!$B$9)) | G19: =IF($D19="","",SUMIFS(Timesheet!$O$5:$O$3004,Timesheet!$B$5:$B$3004,$D19,Timesheet!$A$5:$A$3004,">="&Settings!$B$8,Timesheet!$A$5:$A$3004,"<="&Settings!$B$9)) | H19: =IF($D19="","",SUMIFS(Timesheet!$R$5:$R$3004,Timesheet!$B$5:$B$3004,$D19,Timesheet!$A$5:$A$3004,">="&Settings!$B$8,Timesheet!$A$5:$A$3004,"<="&Settings!$B$9)) | I19: =IF($D19="","",SUMIFS(Timesheet!$S$5:$S$3004,Timesheet!$B$5:$B$3004,$D19,Timesheet!$A$5:$A$3004,">="&Settings!$B$8,Timesheet!$A$5:$A$3004,"<="&Settings!$B$9)) | J19: =IF($D19="","",G19-H19-I19) | K19: =IF(OR($D19="",N(G19)=0),"",J19/G19)
D20: =IF(Clients!A21="","",Clients!A21) | E20: =IF($D20="","",Clients!B21) | F20: =IF($D20="","",COUNTIFS(Timesheet!$B$5:$B$3004,$D20,Timesheet!$A$5:$A$3004,">="&Settings!$B$8,Timesheet!$A$5:$A$3004,"<="&Settings!$B$9)) | G20: =IF($D20="","",SUMIFS(Timesheet!$O$5:$O$3004,Timesheet!$B$5:$B$3004,$D20,Timesheet!$A$5:$A$3004,">="&Settings!$B$8,Timesheet!$A$5:$A$3004,"<="&Settings!$B$9)) | H20: =IF($D20="","",SUMIFS(Timesheet!$R$5:$R$3004,Timesheet!$B$5:$B$3004,$D20,Timesheet!$A$5:$A$3004,">="&Settings!$B$8,Timesheet!$A$5:$A$3004,"<="&Settings!$B$9)) | I20: =IF($D20="","",SUMIFS(Timesheet!$S$5:$S$3004,Timesheet!$B$5:$B$3004,$D20,Timesheet!$A$5:$A$3004,">="&Settings!$B$8,Timesheet!$A$5:$A$3004,"<="&Settings!$B$9)) | J20: =IF($D20="","",G20-H20-I20) | K20: =IF(OR($D20="",N(G20)=0),"",J20/G20)
D21: =IF(Clients!A22="","",Clients!A22) | E21: =IF($D21="","",Clients!B22) | F21: =IF($D21="","",COUNTIFS(Timesheet!$B$5:$B$3004,$D21,Timesheet!$A$5:$A$3004,">="&Settings!$B$8,Timesheet!$A$5:$A$3004,"<="&Settings!$B$9)) | G21: =IF($D21="","",SUMIFS(Timesheet!$O$5:$O$3004,Timesheet!$B$5:$B$3004,$D21,Timesheet!$A$5:$A$3004,">="&Settings!$B$8,Timesheet!$A$5:$A$3004,"<="&Settings!$B$9)) | H21: =IF($D21="","",SUMIFS(Timesheet!$R$5:$R$3004,Timesheet!$B$5:$B$3004,$D21,Timesheet!$A$5:$A$3004,">="&Settings!$B$8,Timesheet!$A$5:$A$3004,"<="&Settings!$B$9)) | I21: =IF($D21="","",SUMIFS(Timesheet!$S$5:$S$3004,Timesheet!$B$5:$B$3004,$D21,Timesheet!$A$5:$A$3004,">="&Settings!$B$8,Timesheet!$A$5:$A$3004,"<="&Settings!$B$9)) | J21: =IF($D21="","",G21-H21-I21) | K21: =IF(OR($D21="",N(G21)=0),"",J21/G21)
A22: Note: 'Own Cost Est.' per client uses each own worker's cost/hour (Workers col V); Gross Profit at left uses actual payroll. | D22: =IF(Clients!A23="","",Clients!A23) | E22: =IF($D22="","",Clients!B23) | F22: =IF($D22="","",COUNTIFS(Timesheet!$B$5:$B$3004,$D22,Timesheet!$A$5:$A$3004,">="&Settings!$B$8,Timesheet!$A$5:$A$3004,"<="&Settings!$B$9)) | G22: =IF($D22="","",SUMIFS(Timesheet!$O$5:$O$3004,Timesheet!$B$5:$B$3004,$D22,Timesheet!$A$5:$A$3004,">="&Settings!$B$8,Timesheet!$A$5:$A$3004,"<="&Settings!$B$9)) | H22: =IF($D22="","",SUMIFS(Timesheet!$R$5:$R$3004,Timesheet!$B$5:$B$3004,$D22,Timesheet!$A$5:$A$3004,">="&Settings!$B$8,Timesheet!$A$5:$A$3004,"<="&Settings!$B$9)) | I22: =IF($D22="","",SUMIFS(Timesheet!$S$5:$S$3004,Timesheet!$B$5:$B$3004,$D22,Timesheet!$A$5:$A$3004,">="&Settings!$B$8,Timesheet!$A$5:$A$3004,"<="&Settings!$B$9)) | J22: =IF($D22="","",G22-H22-I22) | K22: =IF(OR($D22="",N(G22)=0),"",J22/G22)
D23: =IF(Clients!A24="","",Clients!A24) | E23: =IF($D23="","",Clients!B24) | F23: =IF($D23="","",COUNTIFS(Timesheet!$B$5:$B$3004,$D23,Timesheet!$A$5:$A$3004,">="&Settings!$B$8,Timesheet!$A$5:$A$3004,"<="&Settings!$B$9)) | G23: =IF($D23="","",SUMIFS(Timesheet!$O$5:$O$3004,Timesheet!$B$5:$B$3004,$D23,Timesheet!$A$5:$A$3004,">="&Settings!$B$8,Timesheet!$A$5:$A$3004,"<="&Settings!$B$9)) | H23: =IF($D23="","",SUMIFS(Timesheet!$R$5:$R$3004,Timesheet!$B$5:$B$3004,$D23,Timesheet!$A$5:$A$3004,">="&Settings!$B$8,Timesheet!$A$5:$A$3004,"<="&Settings!$B$9)) | I23: =IF($D23="","",SUMIFS(Timesheet!$S$5:$S$3004,Timesheet!$B$5:$B$3004,$D23,Timesheet!$A$5:$A$3004,">="&Settings!$B$8,Timesheet!$A$5:$A$3004,"<="&Settings!$B$9)) | J23: =IF($D23="","",G23-H23-I23) | K23: =IF(OR($D23="",N(G23)=0),"",J23/G23)
D24: =IF(Clients!A25="","",Clients!A25) | E24: =IF($D24="","",Clients!B25) | F24: =IF($D24="","",COUNTIFS(Timesheet!$B$5:$B$3004,$D24,Timesheet!$A$5:$A$3004,">="&Settings!$B$8,Timesheet!$A$5:$A$3004,"<="&Settings!$B$9)) | G24: =IF($D24="","",SUMIFS(Timesheet!$O$5:$O$3004,Timesheet!$B$5:$B$3004,$D24,Timesheet!$A$5:$A$3004,">="&Settings!$B$8,Timesheet!$A$5:$A$3004,"<="&Settings!$B$9)) | H24: =IF($D24="","",SUMIFS(Timesheet!$R$5:$R$3004,Timesheet!$B$5:$B$3004,$D24,Timesheet!$A$5:$A$3004,">="&Settings!$B$8,Timesheet!$A$5:$A$3004,"<="&Settings!$B$9)) | I24: =IF($D24="","",SUMIFS(Timesheet!$S$5:$S$3004,Timesheet!$B$5:$B$3004,$D24,Timesheet!$A$5:$A$3004,">="&Settings!$B$8,Timesheet!$A$5:$A$3004,"<="&Settings!$B$9)) | J24: =IF($D24="","",G24-H24-I24) | K24: =IF(OR($D24="",N(G24)=0),"",J24/G24)
D25: =IF(Clients!A26="","",Clients!A26) | E25: =IF($D25="","",Clients!B26) | F25: =IF($D25="","",COUNTIFS(Timesheet!$B$5:$B$3004,$D25,Timesheet!$A$5:$A$3004,">="&Settings!$B$8,Timesheet!$A$5:$A$3004,"<="&Settings!$B$9)) | G25: =IF($D25="","",SUMIFS(Timesheet!$O$5:$O$3004,Timesheet!$B$5:$B$3004,$D25,Timesheet!$A$5:$A$3004,">="&Settings!$B$8,Timesheet!$A$5:$A$3004,"<="&Settings!$B$9)) | H25: =IF($D25="","",SUMIFS(Timesheet!$R$5:$R$3004,Timesheet!$B$5:$B$3004,$D25,Timesheet!$A$5:$A$3004,">="&Settings!$B$8,Timesheet!$A$5:$A$3004,"<="&Settings!$B$9)) | I25: =IF($D25="","",SUMIFS(Timesheet!$S$5:$S$3004,Timesheet!$B$5:$B$3004,$D25,Timesheet!$A$5:$A$3004,">="&Settings!$B$8,Timesheet!$A$5:$A$3004,"<="&Settings!$B$9)) | J25: =IF($D25="","",G25-H25-I25) | K25: =IF(OR($D25="",N(G25)=0),"",J25/G25)
D26: =IF(Clients!A27="","",Clients!A27) | E26: =IF($D26="","",Clients!B27) | F26: =IF($D26="","",COUNTIFS(Timesheet!$B$5:$B$3004,$D26,Timesheet!$A$5:$A$3004,">="&Settings!$B$8,Timesheet!$A$5:$A$3004,"<="&Settings!$B$9)) | G26: =IF($D26="","",SUMIFS(Timesheet!$O$5:$O$3004,Timesheet!$B$5:$B$3004,$D26,Timesheet!$A$5:$A$3004,">="&Settings!$B$8,Timesheet!$A$5:$A$3004,"<="&Settings!$B$9)) | H26: =IF($D26="","",SUMIFS(Timesheet!$R$5:$R$3004,Timesheet!$B$5:$B$3004,$D26,Timesheet!$A$5:$A$3004,">="&Settings!$B$8,Timesheet!$A$5:$A$3004,"<="&Settings!$B$9)) | I26: =IF($D26="","",SUMIFS(Timesheet!$S$5:$S$3004,Timesheet!$B$5:$B$3004,$D26,Timesheet!$A$5:$A$3004,">="&Settings!$B$8,Timesheet!$A$5:$A$3004,"<="&Settings!$B$9)) | J26: =IF($D26="","",G26-H26-I26) | K26: =IF(OR($D26="",N(G26)=0),"",J26/G26)
D27: =IF(Clients!A28="","",Clients!A28) | E27: =IF($D27="","",Clients!B28) | F27: =IF($D27="","",COUNTIFS(Timesheet!$B$5:$B$3004,$D27,Timesheet!$A$5:$A$3004,">="&Settings!$B$8,Timesheet!$A$5:$A$3004,"<="&Settings!$B$9)) | G27: =IF($D27="","",SUMIFS(Timesheet!$O$5:$O$3004,Timesheet!$B$5:$B$3004,$D27,Timesheet!$A$5:$A$3004,">="&Settings!$B$8,Timesheet!$A$5:$A$3004,"<="&Settings!$B$9)) | H27: =IF($D27="","",SUMIFS(Timesheet!$R$5:$R$3004,Timesheet!$B$5:$B$3004,$D27,Timesheet!$A$5:$A$3004,">="&Settings!$B$8,Timesheet!$A$5:$A$3004,"<="&Settings!$B$9)) | I27: =IF($D27="","",SUMIFS(Timesheet!$S$5:$S$3004,Timesheet!$B$5:$B$3004,$D27,Timesheet!$A$5:$A$3004,">="&Settings!$B$8,Timesheet!$A$5:$A$3004,"<="&Settings!$B$9)) | J27: =IF($D27="","",G27-H27-I27) | K27: =IF(OR($D27="",N(G27)=0),"",J27/G27)
D28: =IF(Clients!A29="","",Clients!A29) | E28: =IF($D28="","",Clients!B29) | F28: =IF($D28="","",COUNTIFS(Timesheet!$B$5:$B$3004,$D28,Timesheet!$A$5:$A$3004,">="&Settings!$B$8,Timesheet!$A$5:$A$3004,"<="&Settings!$B$9)) | G28: =IF($D28="","",SUMIFS(Timesheet!$O$5:$O$3004,Timesheet!$B$5:$B$3004,$D28,Timesheet!$A$5:$A$3004,">="&Settings!$B$8,Timesheet!$A$5:$A$3004,"<="&Settings!$B$9)) | H28: =IF($D28="","",SUMIFS(Timesheet!$R$5:$R$3004,Timesheet!$B$5:$B$3004,$D28,Timesheet!$A$5:$A$3004,">="&Settings!$B$8,Timesheet!$A$5:$A$3004,"<="&Settings!$B$9)) | I28: =IF($D28="","",SUMIFS(Timesheet!$S$5:$S$3004,Timesheet!$B$5:$B$3004,$D28,Timesheet!$A$5:$A$3004,">="&Settings!$B$8,Timesheet!$A$5:$A$3004,"<="&Settings!$B$9)) | J28: =IF($D28="","",G28-H28-I28) | K28: =IF(OR($D28="",N(G28)=0),"",J28/G28)
D29: =IF(Clients!A30="","",Clients!A30) | E29: =IF($D29="","",Clients!B30) | F29: =IF($D29="","",COUNTIFS(Timesheet!$B$5:$B$3004,$D29,Timesheet!$A$5:$A$3004,">="&Settings!$B$8,Timesheet!$A$5:$A$3004,"<="&Settings!$B$9)) | G29: =IF($D29="","",SUMIFS(Timesheet!$O$5:$O$3004,Timesheet!$B$5:$B$3004,$D29,Timesheet!$A$5:$A$3004,">="&Settings!$B$8,Timesheet!$A$5:$A$3004,"<="&Settings!$B$9)) | H29: =IF($D29="","",SUMIFS(Timesheet!$R$5:$R$3004,Timesheet!$B$5:$B$3004,$D29,Timesheet!$A$5:$A$3004,">="&Settings!$B$8,Timesheet!$A$5:$A$3004,"<="&Settings!$B$9)) | I29: =IF($D29="","",SUMIFS(Timesheet!$S$5:$S$3004,Timesheet!$B$5:$B$3004,$D29,Timesheet!$A$5:$A$3004,">="&Settings!$B$8,Timesheet!$A$5:$A$3004,"<="&Settings!$B$9)) | J29: =IF($D29="","",G29-H29-I29) | K29: =IF(OR($D29="",N(G29)=0),"",J29/G29)
D30: =IF(Clients!A31="","",Clients!A31) | E30: =IF($D30="","",Clients!B31) | F30: =IF($D30="","",COUNTIFS(Timesheet!$B$5:$B$3004,$D30,Timesheet!$A$5:$A$3004,">="&Settings!$B$8,Timesheet!$A$5:$A$3004,"<="&Settings!$B$9)) | G30: =IF($D30="","",SUMIFS(Timesheet!$O$5:$O$3004,Timesheet!$B$5:$B$3004,$D30,Timesheet!$A$5:$A$3004,">="&Settings!$B$8,Timesheet!$A$5:$A$3004,"<="&Settings!$B$9)) | H30: =IF($D30="","",SUMIFS(Timesheet!$R$5:$R$3004,Timesheet!$B$5:$B$3004,$D30,Timesheet!$A$5:$A$3004,">="&Settings!$B$8,Timesheet!$A$5:$A$3004,"<="&Settings!$B$9)) | I30: =IF($D30="","",SUMIFS(Timesheet!$S$5:$S$3004,Timesheet!$B$5:$B$3004,$D30,Timesheet!$A$5:$A$3004,">="&Settings!$B$8,Timesheet!$A$5:$A$3004,"<="&Settings!$B$9)) | J30: =IF($D30="","",G30-H30-I30) | K30: =IF(OR($D30="",N(G30)=0),"",J30/G30)
D31: =IF(Clients!A32="","",Clients!A32) | E31: =IF($D31="","",Clients!B32) | F31: =IF($D31="","",COUNTIFS(Timesheet!$B$5:$B$3004,$D31,Timesheet!$A$5:$A$3004,">="&Settings!$B$8,Timesheet!$A$5:$A$3004,"<="&Settings!$B$9)) | G31: =IF($D31="","",SUMIFS(Timesheet!$O$5:$O$3004,Timesheet!$B$5:$B$3004,$D31,Timesheet!$A$5:$A$3004,">="&Settings!$B$8,Timesheet!$A$5:$A$3004,"<="&Settings!$B$9)) | H31: =IF($D31="","",SUMIFS(Timesheet!$R$5:$R$3004,Timesheet!$B$5:$B$3004,$D31,Timesheet!$A$5:$A$3004,">="&Settings!$B$8,Timesheet!$A$5:$A$3004,"<="&Settings!$B$9)) | I31: =IF($D31="","",SUMIFS(Timesheet!$S$5:$S$3004,Timesheet!$B$5:$B$3004,$D31,Timesheet!$A$5:$A$3004,">="&Settings!$B$8,Timesheet!$A$5:$A$3004,"<="&Settings!$B$9)) | J31: =IF($D31="","",G31-H31-I31) | K31: =IF(OR($D31="",N(G31)=0),"",J31/G31)
D32: =IF(Clients!A33="","",Clients!A33) | E32: =IF($D32="","",Clients!B33) | F32: =IF($D32="","",COUNTIFS(Timesheet!$B$5:$B$3004,$D32,Timesheet!$A$5:$A$3004,">="&Settings!$B$8,Timesheet!$A$5:$A$3004,"<="&Settings!$B$9)) | G32: =IF($D32="","",SUMIFS(Timesheet!$O$5:$O$3004,Timesheet!$B$5:$B$3004,$D32,Timesheet!$A$5:$A$3004,">="&Settings!$B$8,Timesheet!$A$5:$A$3004,"<="&Settings!$B$9)) | H32: =IF($D32="","",SUMIFS(Timesheet!$R$5:$R$3004,Timesheet!$B$5:$B$3004,$D32,Timesheet!$A$5:$A$3004,">="&Settings!$B$8,Timesheet!$A$5:$A$3004,"<="&Settings!$B$9)) | I32: =IF($D32="","",SUMIFS(Timesheet!$S$5:$S$3004,Timesheet!$B$5:$B$3004,$D32,Timesheet!$A$5:$A$3004,">="&Settings!$B$8,Timesheet!$A$5:$A$3004,"<="&Settings!$B$9)) | J32: =IF($D32="","",G32-H32-I32) | K32: =IF(OR($D32="",N(G32)=0),"",J32/G32)
D33: =IF(Clients!A34="","",Clients!A34) | E33: =IF($D33="","",Clients!B34) | F33: =IF($D33="","",COUNTIFS(Timesheet!$B$5:$B$3004,$D33,Timesheet!$A$5:$A$3004,">="&Settings!$B$8,Timesheet!$A$5:$A$3004,"<="&Settings!$B$9)) | G33: =IF($D33="","",SUMIFS(Timesheet!$O$5:$O$3004,Timesheet!$B$5:$B$3004,$D33,Timesheet!$A$5:$A$3004,">="&Settings!$B$8,Timesheet!$A$5:$A$3004,"<="&Settings!$B$9)) | H33: =IF($D33="","",SUMIFS(Timesheet!$R$5:$R$3004,Timesheet!$B$5:$B$3004,$D33,Timesheet!$A$5:$A$3004,">="&Settings!$B$8,Timesheet!$A$5:$A$3004,"<="&Settings!$B$9)) | I33: =IF($D33="","",SUMIFS(Timesheet!$S$5:$S$3004,Timesheet!$B$5:$B$3004,$D33,Timesheet!$A$5:$A$3004,">="&Settings!$B$8,Timesheet!$A$5:$A$3004,"<="&Settings!$B$9)) | J33: =IF($D33="","",G33-H33-I33) | K33: =IF(OR($D33="",N(G33)=0),"",J33/G33)

Sheet Settings
A1: Settings | D1: « HOME
A2: Yellow cells are inputs. Change the payroll month here every month.
A4: Company Name | B4: Gulf Star Manpower Services LLC | D4: Trades | F4: Source | H4: Pay Basis | J4: Deduction Types | L4: Status
A5: Company TRN (VAT) | B5: 100123456700003 | D5: Helper | F5: Own | H5: Monthly | J5: Advance | L5: Active
A6: Employer MOHRE ID (13 digits) | B6: 0000001234567 | D6: Mason | F6: Supplier | H6: Hourly | J6: Fine | L6: Inactive
A7: Employer Bank Routing Code | B7: 803320101 | D7: Carpenter | J7: Accommodation
A8: Payroll Month (1st day) | B8: 46296 | D8: Electrician | J8: Other
A9: Month End | B9: =EOMONTH(B8,0) -> 46326 | D9: Plumber
A10: Salary Day Divisor | B10: 30 | D10: Steel Fixer
A11: Standard Working Days / Month | B11: 26 | D11: Driver
A12: Normal Hours / Day | B12: 8 | D12: Cleaner
A13: OT Multiplier | B13: 1.25 | D13: Security Guard
A14: VAT Rate | B14: 0.05
A15: Document Expiry Alert (days) | B15: 30
A17: Note: OT multiplier 1.25 and divisor 30 follow common UAE practice - confirm with your HR / legal advisor.

Sheet Clients
A1: Clients (Customers) | C1: « HOME
A2: One row per client. Client ID must be unique.
A4: Client ID | B4: Client Name | C4: TRN | D4: Emirate | E4: Payment Terms (days) | F4: Contact Person | G4: Phone
A5: C001 | B5: Al Waha Contracting LLC | C5: 100555111200003 | D5: Dubai | E5: 30 | F5: Mr. Al | G5: +971 4 000 0000
A6: C002 | B6: Blue Creek Facilities Mgmt | C6: 100555222300003 | D6: Abu Dhabi | E6: 45 | F6: Mr. Blue | G6: +971 4 000 0001
A7: C003 | B7: Sandline Construction Co. | C7: 100555333400003 | D7: Sharjah | E7: 30 | F7: Mr. Sandline | G7: +971 4 000 0002
A8: C004 | B8: Marina Hospitality Group | C8: 100555444500003 | D8: Dubai | E8: 60 | F8: Mr. Marina | G8: +971 4 000 0003

Sheet Suppliers
A1: Suppliers (Manpower Agencies) | D1: « HOME
A2: Companies that supply workers to you.
A4: Supplier ID | B4: Supplier Name | C4: TRN | D4: Payment Terms (days) | E4: Contact Person | F4: Bank IBAN
A5: S001 | B5: Desert Falcon Manpower Supply | C5: 100777111200003 | D5: 30 | E5: Mr. Desert | F5: AE07 0331 2345 6789 0123 450
A6: S002 | B6: Emirates Link Labour Services | C6: 100777222300003 | D6: 45 | E6: Mr. Emirates | F6: AE07 0331 2345 6789 0123 451
A7: S003 | B7: Oasis Workforce Solutions | C7: 100777333400003 | D7: 30 | E7: Mr. Oasis | F7: AE07 0331 2345 6789 0123 452

Sheet ClientRates
A1: ClientRates | C1: « HOME
A2: Selling rate charged to each client, per trade.
A4: Key (auto) | B4: Client ID | C4: Trade | D4: Normal Rate / hr (AED) | E4: OT Rate / hr (AED)
A5: =IF(B5="","",B5&"|"&C5) -> C001|Helper | B5: C001 | C5: Helper | D5: 16 | E5: 20
A6: =IF(B6="","",B6&"|"&C6) -> C001|Mason | B6: C001 | C6: Mason | D6: 22 | E6: 27.5
A7: =IF(B7="","",B7&"|"&C7) -> C001|Carpenter | B7: C001 | C7: Carpenter | D7: 22 | E7: 27.5
A8: =IF(B8="","",B8&"|"&C8) -> C001|Electrician | B8: C001 | C8: Electrician | D8: 26 | E8: 32.5
A9: =IF(B9="","",B9&"|"&C9) -> C001|Plumber | B9: C001 | C9: Plumber | D9: 25 | E9: 31.25
A10: =IF(B10="","",B10&"|"&C10) -> C001|Steel Fixer | B10: C001 | C10: Steel Fixer | D10: 23 | E10: 28.75
A11: =IF(B11="","",B11&"|"&C11) -> C001|Driver | B11: C001 | C11: Driver | D11: 24 | E11: 30
A12: =IF(B12="","",B12&"|"&C12) -> C001|Cleaner | B12: C001 | C12: Cleaner | D12: 15 | E12: 18.75
A13: =IF(B13="","",B13&"|"&C13) -> C001|Security Guard | B13: C001 | C13: Security Guard | D13: 17 | E13: 21.25
A14: =IF(B14="","",B14&"|"&C14) -> C002|Helper | B14: C002 | C14: Helper | D14: 17.6 | E14: 22
A15: =IF(B15="","",B15&"|"&C15) -> C002|Mason | B15: C002 | C15: Mason | D15: 24.2 | E15: 30.25
A16: =IF(B16="","",B16&"|"&C16) -> C002|Carpenter | B16: C002 | C16: Carpenter | D16: 24.2 | E16: 30.25
... A40: =IF(B40="","",B40&"|"&C40) -> C004|Security Guard | B40: C004 | C40: Security Guard | D40: 17.85 | E40: 22.31
A41: =IF(B41="","",B41&"|"&C41)
A42: =IF(B42="","",B42&"|"&C42)
A43: =IF(B43="","",B43&"|"&C43)
A44: =IF(B44="","",B44&"|"&C44)
A45: =IF(B45="","",B45&"|"&C45)
A46: =IF(B46="","",B46&"|"&C46)
A47: =IF(B47="","",B47&"|"&C47)
A48: =IF(B48="","",B48&"|"&C48)
A49: =IF(B49="","",B49&"|"&C49)
A50: =IF(B50="","",B50&"|"&C50)
A51: =IF(B51="","",B51&"|"&C51)
A52: =IF(B52="","",B52&"|"&C52)
... A100: =IF(B100="","",B100&"|"&C100)

Sheet SupplierRates
A1: SupplierRates | C1: « HOME
A2: Cost rate charged by each supplier, per trade.
A4: Key (auto) | B4: Supplier ID | C4: Trade | D4: Normal Rate / hr (AED) | E4: OT Rate / hr (AED)
A5: =IF(B5="","",B5&"|"&C5) -> S001|Helper | B5: S001 | C5: Helper | D5: 11.52 | E5: 14.4
A6: =IF(B6="","",B6&"|"&C6) -> S001|Mason | B6: S001 | C6: Mason | D6: 15.84 | E6: 19.8
A7: =IF(B7="","",B7&"|"&C7) -> S001|Carpenter | B7: S001 | C7: Carpenter | D7: 15.84 | E7: 19.8
A8: =IF(B8="","",B8&"|"&C8) -> S001|Electrician | B8: S001 | C8: Electrician | D8: 18.72 | E8: 23.4
A9: =IF(B9="","",B9&"|"&C9) -> S001|Plumber | B9: S001 | C9: Plumber | D9: 18 | E9: 22.5
A10: =IF(B10="","",B10&"|"&C10) -> S001|Steel Fixer | B10: S001 | C10: Steel Fixer | D10: 16.56 | E10: 20.7
A11: =IF(B11="","",B11&"|"&C11) -> S001|Driver | B11: S001 | C11: Driver | D11: 17.28 | E11: 21.6
A12: =IF(B12="","",B12&"|"&C12) -> S001|Cleaner | B12: S001 | C12: Cleaner | D12: 10.8 | E12: 13.5
A13: =IF(B13="","",B13&"|"&C13) -> S001|Security Guard | B13: S001 | C13: Security Guard | D13: 12.24 | E13: 15.3
A14: =IF(B14="","",B14&"|"&C14) -> S002|Helper | B14: S002 | C14: Helper | D14: 12 | E14: 15
A15: =IF(B15="","",B15&"|"&C15) -> S002|Mason | B15: S002 | C15: Mason | D15: 16.5 | E15: 20.62
A16: =IF(B16="","",B16&"|"&C16) -> S002|Carpenter | B16: S002 | C16: Carpenter | D16: 16.5 | E16: 20.62
... A31: =IF(B31="","",B31&"|"&C31) -> S003|Security Guard | B31: S003 | C31: Security Guard | D31: 11.9 | E31: 14.88
A32: =IF(B32="","",B32&"|"&C32)
A33: =IF(B33="","",B33&"|"&C33)
A34: =IF(B34="","",B34&"|"&C34)
A35: =IF(B35="","",B35&"|"&C35)
A36: =IF(B36="","",B36&"|"&C36)
A37: =IF(B37="","",B37&"|"&C37)
A38: =IF(B38="","",B38&"|"&C38)
A39: =IF(B39="","",B39&"|"&C39)
A40: =IF(B40="","",B40&"|"&C40)
A41: =IF(B41="","",B41&"|"&C41)
A42: =IF(B42="","",B42&"|"&C42)
A43: =IF(B43="","",B43&"|"&C43)
... A91: =IF(B91="","",B91&"|"&C91)

Sheet Workers
A1: Workers Master | C1: « HOME
A2: Own + supplier workers. Salary / bank fields are needed only for Own workers. Columns R-V are automatic.
A4: Worker ID | B4: Name | C4: Source | D4: Supplier ID | E4: Trade | F4: Nationality | G4: Passport No | H4: Labour Card / Person ID | I4: Visa Expiry | J4: Emirates ID Expiry | K4: Pay Basis | L4: Basic Salary / Month | M4: Allowances / Month | N4: Hourly Rate | O4: Bank Routing Code | P4: IBAN | Q4: Status | R4: Days to Visa Expiry | S4: Days to EID Expiry | T4: Document Alert | U4: Own Seq (auto) | V4: Own Cost / hr
A5: W0001 | B5: Marlon Khan | C5: Own | E5: Steel Fixer | F5: Pakistan | G5: P9648511 | H5: 96921334349946 | I5: 46391 | J5: 46396 | K5: Monthly | L5: 1400 | M5: 400 | O5: 402320106 | P5: AE96 1884 8481 7428 7521 508 | Q5: Active | R5: =IF(I5="","",I5-TODAY()) -> 64 | S5: =IF(J5="","",J5-TODAY()) -> 69 | T5: =IF(A5="","",IF(OR(AND(R5<>"",R5<0),AND(S5<>"",S5<0)),"EXPIRED",IF(OR(AND(R5<>"",R5<=Settings!$B$15),AND(S5<>"",S5<=Settings!$B$15)),"EXPIRING SOON","OK"))) -> OK | U5: =IF(AND(C5="Own",Q5="Active"),COUNTIFS($C$5:C5,"Own",$Q$5:Q5,"Active"),"") -> 1 | V5: =IF(C5<>"Own","",IF(K5="Hourly",N5,(L5+M5)/(Settings!$B$11*Settings!$B$12))) -> 8.6538462
A6: W0002 | B6: Rohan Ali | C6: Own | E6: Helper | F6: Philippines | G6: P3537804 | H6: 24278776051635 | I6: 46339 | J6: 46339 | K6: Monthly | L6: 1200 | M6: 500 | O6: 600310101 | P6: AE88 1417 2152 4407 7164 252 | Q6: Active | R6: =IF(I6="","",I6-TODAY()) -> 12 | S6: =IF(J6="","",J6-TODAY()) -> 12 | T6: =IF(A6="","",IF(OR(AND(R6<>"",R6<0),AND(S6<>"",S6<0)),"EXPIRED",IF(OR(AND(R6<>"",R6<=Settings!$B$15),AND(S6<>"",S6<=Settings!$B$15)),"EXPIRING SOON","OK"))) -> EXPIRING SOON | U6: =IF(AND(C6="Own",Q6="Active"),COUNTIFS($C$5:C6,"Own",$Q$5:Q6,"Active"),"") -> 2 | V6: =IF(C6<>"Own","",IF(K6="Hourly",N6,(L6+M6)/(Settings!$B$11*Settings!$B$12))) -> 8.1730769
A7: W0003 | B7: Ronel Thapa | C7: Own | E7: Mason | F7: Nepal | G7: P5441883 | H7: 32723349357046 | I7: 46352 | J7: 46352 | K7: Monthly | L7: 1500 | M7: 500 | O7: 402320106 | P7: AE12 4362 9654 6926 3401 806 | Q7: Active | R7: =IF(I7="","",I7-TODAY()) -> 25 | S7: =IF(J7="","",J7-TODAY()) -> 25 | T7: =IF(A7="","",IF(OR(AND(R7<>"",R7<0),AND(S7<>"",S7<0)),"EXPIRED",IF(OR(AND(R7<>"",R7<=Settings!$B$15),AND(S7<>"",S7<=Settings!$B$15)),"EXPIRING SOON","OK"))) -> EXPIRING SOON | U7: =IF(AND(C7="Own",Q7="Active"),COUNTIFS($C$5:C7,"Own",$Q$5:Q7,"Active"),"") -> 3 | V7: =IF(C7<>"Own","",IF(K7="Hourly",N7,(L7+M7)/(Settings!$B$11*Settings!$B$12))) -> 9.6153846
A8: W0004 | B8: Tariq Varghese | C8: Own | E8: Helper | F8: Nepal | G8: P4742018 | H8: 41910762301181 | I8: 46615 | J8: 46655 | K8: Monthly | L8: 2000 | M8: 300 | O8: 803320101 | P8: AE76 9073 6825 1474 1457 909 | Q8: Active | R8: =IF(I8="","",I8-TODAY()) -> 288 | S8: =IF(J8="","",J8-TODAY()) -> 328 | T8: =IF(A8="","",IF(OR(AND(R8<>"",R8<0),AND(S8<>"",S8<0)),"EXPIRED",IF(OR(AND(R8<>"",R8<=Settings!$B$15),AND(S8<>"",S8<=Settings!$B$15)),"EXPIRING SOON","OK"))) -> OK | U8: =IF(AND(C8="Own",Q8="Active"),COUNTIFS($C$5:C8,"Own",$Q$5:Q8,"Active"),"") -> 4 | V8: =IF(C8<>"Own","",IF(K8="Hourly",N8,(L8+M8)/(Settings!$B$11*Settings!$B$12))) -> 11.057692
A9: W0005 | B9: Joseph Ahmed | C9: Own | E9: Helper | F9: Pakistan | G9: P9097578 | H9: 95890327812981 | I9: 46652 | J9: 46657 | K9: Monthly | L9: 1200 | M9: 400 | O9: 803320101 | P9: AE71 6636 2389 2964 7365 901 | Q9: Active | R9: =IF(I9="","",I9-TODAY()) -> 325 | S9: =IF(J9="","",J9-TODAY()) -> 330 | T9: =IF(A9="","",IF(OR(AND(R9<>"",R9<0),AND(S9<>"",S9<0)),"EXPIRED",IF(OR(AND(R9<>"",R9<=Settings!$B$15),AND(S9<>"",S9<=Settings!$B$15)),"EXPIRING SOON","OK"))) -> OK | U9: =IF(AND(C9="Own",Q9="Active"),COUNTIFS($C$5:C9,"Own",$Q$5:Q9,"Active"),"") -> 5 | V9: =IF(C9<>"Own","",IF(K9="Hourly",N9,(L9+M9)/(Settings!$B$11*Settings!$B$12))) -> 7.6923077
A10: W0006 | B10: Dinesh Shrestha | C10: Own | E10: Driver | F10: Pakistan | G10: P8807342 | H10: 96071772425721 | I10: 46352 | J10: 46352 | K10: Monthly | L10: 1200 | M10: 300 | O10: 402320106 | P10: AE70 6741 3554 9989 9983 234 | Q10: Active | R10: =IF(I10="","",I10-TODAY()) -> 25 | S10: =IF(J10="","",J10-TODAY()) -> 25 | T10: =IF(A10="","",IF(OR(AND(R10<>"",R10<0),AND(S10<>"",S10<0)),"EXPIRED",IF(OR(AND(R10<>"",R10<=Settings!$B$15),AND(S10<>"",S10<=Settings!$B$15)),"EXPIRING SOON","OK"))) -> EXPIRING SOON | U10: =IF(AND(C10="Own",Q10="Active"),COUNTIFS($C$5:C10,"Own",$Q$5:Q10,"Active"),"") -> 6 | V10: =IF(C10<>"Own","",IF(K10="Hourly",N10,(L10+M10)/(Settings!$B$11*Settings!$B$12))) -> 7.2115385
A11: W0007 | B11: Rahul Kumar | C11: Own | E11: Mason | F11: Nepal | G11: P5351419 | H11: 68972238951406 | I11: 46686 | J11: 46726 | K11: Monthly | L11: 2000 | M11: 400 | O11: 803320101 | P11: AE17 6796 8506 9466 7891 946 | Q11: Active | R11: =IF(I11="","",I11-TODAY()) -> 359 | S11: =IF(J11="","",J11-TODAY()) -> 399 | T11: =IF(A11="","",IF(OR(AND(R11<>"",R11<0),AND(S11<>"",S11<0)),"EXPIRED",IF(OR(AND(R11<>"",R11<=Settings!$B$15),AND(S11<>"",S11<=Settings!$B$15)),"EXPIRING SOON","OK"))) -> OK | U11: =IF(AND(C11="Own",Q11="Active"),COUNTIFS($C$5:C11,"Own",$Q$5:Q11,"Active"),"") -> 7 | V11: =IF(C11<>"Own","",IF(K11="Hourly",N11,(L11+M11)/(Settings!$B$11*Settings!$B$12))) -> 11.538462
A12: W0008 | B12: Mohan Nair | C12: Own | E12: Helper | F12: India | G12: P2036081 | H12: 84691707568212 | I12: 46406 | J12: 46446 | K12: Hourly | N12: 9 | O12: 402320106 | P12: AE71 2738 1930 5071 4134 383 | Q12: Active | R12: =IF(I12="","",I12-TODAY()) -> 79 | S12: =IF(J12="","",J12-TODAY()) -> 119 | T12: =IF(A12="","",IF(OR(AND(R12<>"",R12<0),AND(S12<>"",S12<0)),"EXPIRED",IF(OR(AND(R12<>"",R12<=Settings!$B$15),AND(S12<>"",S12<=Settings!$B$15)),"EXPIRING SOON","OK"))) -> OK | U12: =IF(AND(C12="Own",Q12="Active"),COUNTIFS($C$5:C12,"Own",$Q$5:Q12,"Active"),"") -> 8 | V12: =IF(C12<>"Own","",IF(K12="Hourly",N12,(L12+M12)/(Settings!$B$11*Settings!$B$12))) -> 9
A13: W0009 | B13: Anwar Shrestha | C13: Own | E13: Electrician | F13: Nepal | G13: P8589103 | H13: 85052441044367 | I13: 46487 | J13: 46527 | K13: Monthly | L13: 2500 | M13: 500 | O13: 600310101 | P13: AE74 5057 9572 5253 4319 960 | Q13: Active | R13: =IF(I13="","",I13-TODAY()) -> 160 | S13: =IF(J13="","",J13-TODAY()) -> 200 | T13: =IF(A13="","",IF(OR(AND(R13<>"",R13<0),AND(S13<>"",S13<0)),"EXPIRED",IF(OR(AND(R13<>"",R13<=Settings!$B$15),AND(S13<>"",S13<=Settings!$B$15)),"EXPIRING SOON","OK"))) -> OK | U13: =IF(AND(C13="Own",Q13="Active"),COUNTIFS($C$5:C13,"Own",$Q$5:Q13,"Active"),"") -> 9 | V13: =IF(C13<>"Own","",IF(K13="Hourly",N13,(L13+M13)/(Settings!$B$11*Settings!$B$12))) -> 14.423077
A14: W0010 | B14: Hari Nair | C14: Own | E14: Helper | F14: Nepal | G14: P3398789 | H14: 40904298604831 | I14: 46512 | J14: 46512 | K14: Monthly | L14: 2000 | M14: 500 | O14: 402320106 | P14: AE22 7525 8983 3667 4665 265 | Q14: Active | R14: =IF(I14="","",I14-TODAY()) -> 185 | S14: =IF(J14="","",J14-TODAY()) -> 185 | T14: =IF(A14="","",IF(OR(AND(R14<>"",R14<0),AND(S14<>"",S14<0)),"EXPIRED",IF(OR(AND(R14<>"",R14<=Settings!$B$15),AND(S14<>"",S14<=Settings!$B$15)),"EXPIRING SOON","OK"))) -> OK | U14: =IF(AND(C14="Own",Q14="Active"),COUNTIFS($C$5:C14,"Own",$Q$5:Q14,"Active"),"") -> 10 | V14: =IF(C14<>"Own","",IF(K14="Hourly",N14,(L14+M14)/(Settings!$B$11*Settings!$B$12))) -> 12.019231
A15: W0011 | B15: Dinesh Menon | C15: Own | E15: Driver | F15: India | G15: P7448231 | H15: 82822594276261 | I15: 46587 | J15: 46592 | K15: Monthly | L15: 1200 | M15: 300 | O15: 402320106 | P15: AE47 9392 2053 2848 4744 997 | Q15: Active | R15: =IF(I15="","",I15-TODAY()) -> 260 | S15: =IF(J15="","",J15-TODAY()) -> 265 | T15: =IF(A15="","",IF(OR(AND(R15<>"",R15<0),AND(S15<>"",S15<0)),"EXPIRED",IF(OR(AND(R15<>"",R15<=Settings!$B$15),AND(S15<>"",S15<=Settings!$B$15)),"EXPIRING SOON","OK"))) -> OK | U15: =IF(AND(C15="Own",Q15="Active"),COUNTIFS($C$5:C15,"Own",$Q$5:Q15,"Active"),"") -> 11 | V15: =IF(C15<>"Own","",IF(K15="Hourly",N15,(L15+M15)/(Settings!$B$11*Settings!$B$12))) -> 7.2115385
A16: W0012 | B16: Imran Ali | C16: Own | E16: Helper | F16: Nepal | G16: P2500926 | H16: 18097211916423 | I16: 46819 | J16: 46824 | K16: Monthly | L16: 2000 | M16: 300 | O16: 402320106 | P16: AE33 7968 2186 5406 1275 749 | Q16: Active | R16: =IF(I16="","",I16-TODAY()) -> 492 | S16: =IF(J16="","",J16-TODAY()) -> 497 | T16: =IF(A16="","",IF(OR(AND(R16<>"",R16<0),AND(S16<>"",S16<0)),"EXPIRED",IF(OR(AND(R16<>"",R16<=Settings!$B$15),AND(S16<>"",S16<=Settings!$B$15)),"EXPIRING SOON","OK"))) -> OK | U16: =IF(AND(C16="Own",Q16="Active"),COUNTIFS($C$5:C16,"Own",$Q$5:Q16,"Active"),"") -> 12 | V16: =IF(C16<>"Own","",IF(K16="Hourly",N16,(L16+M16)/(Settings!$B$11*Settings!$B$12))) -> 11.057692
A17: W0013 | B17: Suresh Shrestha | C17: Own | E17: Plumber | F17: Philippines | G17: P3168032 | H17: 84152795932475 | I17: 46814 | J17: 46819 | K17: Monthly | L17: 1800 | M17: 300 | O17: 402320106 | P17: AE40 2793 3645 5290 1825 285 | Q17: Active | R17: =IF(I17="","",I17-TODAY()) -> 487 | S17: =IF(J17="","",J17-TODAY()) -> 492 | T17: =IF(A17="","",IF(OR(AND(R17<>"",R17<0),AND(S17<>"",S17<0)),"EXPIRED",IF(OR(AND(R17<>"",R17<=Settings!$B$15),AND(S17<>"",S17<=Settings!$B$15)),"EXPIRING SOON","OK"))) -> OK | U17: =IF(AND(C17="Own",Q17="Active"),COUNTIFS($C$5:C17,"Own",$Q$5:Q17,"Active"),"") -> 13 | V17: =IF(C17<>"Own","",IF(K17="Hourly",N17,(L17+M17)/(Settings!$B$11*Settings!$B$12))) -> 10.096154
A18: W0014 | B18: Prakash Varghese | C18: Own | E18: Security Guard | F18: India | G18: P9483466 | H18: 82371012647049 | I18: 46317 | J18: 46317 | K18: Monthly | L18: 1200 | M18: 500 | O18: 600310101 | P18: AE41 8324 2741 8080 9110 659 | Q18: Active | R18: =IF(I18="","",I18-TODAY()) -> -10 | S18: =IF(J18="","",J18-TODAY()) -> -10 | T18: =IF(A18="","",IF(OR(AND(R18<>"",R18<0),AND(S18<>"",S18<0)),"EXPIRED",IF(OR(AND(R18<>"",R18<=Settings!$B$15),AND(S18<>"",S18<=Settings!$B$15)),"EXPIRING SOON","OK"))) -> EXPIRED | U18: =IF(AND(C18="Own",Q18="Active"),COUNTIFS($C$5:C18,"Own",$Q$5:Q18,"Active"),"") -> 14 | V18: =IF(C18<>"Own","",IF(K18="Hourly",N18,(L18+M18)/(Settings!$B$11*Settings!$B$12))) -> 8.1730769
A19: W0015 | B19: Rohan Gurung | C19: Own | E19: Plumber | F19: Nepal | G19: P8226629 | H19: 17796066780717 | I19: 46742 | J19: 46782 | K19: Monthly | L19: 2000 | M19: 500 | O19: 803320101 | P19: AE95 7240 9289 5619 4968 809 | Q19: Active | R19: =IF(I19="","",I19-TODAY()) -> 415 | S19: =IF(J19="","",J19-TODAY()) -> 455 | T19: =IF(A19="","",IF(OR(AND(R19<>"",R19<0),AND(S19<>"",S19<0)),"EXPIRED",IF(OR(AND(R19<>"",R19<=Settings!$B$15),AND(S19<>"",S19<=Settings!$B$15)),"EXPIRING SOON","OK"))) -> OK | U19: =IF(AND(C19="Own",Q19="Active"),COUNTIFS($C$5:C19,"Own",$Q$5:Q19,"Active"),"") -> 15 | V19: =IF(C19<>"Own","",IF(K19="Hourly",N19,(L19+M19)/(Settings!$B$11*Settings!$B$12))) -> 12.019231
A20: W0016 | B20: Sanjay Kumar | C20: Own | E20: Carpenter | F20: Pakistan | G20: P6982485 | H20: 10151109653521 | I20: 46317 | J20: 46322 | K20: Hourly | N20: 11 | O20: 600310101 | P20: AE58 2374 8776 5569 9237 771 | Q20: Active | R20: =IF(I20="","",I20-TODAY()) -> -10 | S20: =IF(J20="","",J20-TODAY()) -> -5 | T20: =IF(A20="","",IF(OR(AND(R20<>"",R20<0),AND(S20<>"",S20<0)),"EXPIRED",IF(OR(AND(R20<>"",R20<=Settings!$B$15),AND(S20<>"",S20<=Settings!$B$15)),"EXPIRING SOON","OK"))) -> EXPIRED | U20: =IF(AND(C20="Own",Q20="Active"),COUNTIFS($C$5:C20,"Own",$Q$5:Q20,"Active"),"") -> 16 | V20: =IF(C20<>"Own","",IF(K20="Hourly",N20,(L20+M20)/(Settings!$B$11*Settings!$B$12))) -> 11
A21: W0017 | B21: Prakash Khan | C21: Own | E21: Electrician | F21: Pakistan | G21: P2417384 | H21: 31851722182217 | I21: 46392 | J21: 46432 | K21: Monthly | L21: 1500 | M21: 300 | O21: 402320106 | P21: AE86 7381 6343 9096 3448 390 | Q21: Active | R21: =IF(I21="","",I21-TODAY()) -> 65 | S21: =IF(J21="","",J21-TODAY()) -> 105 | T21: =IF(A21="","",IF(OR(AND(R21<>"",R21<0),AND(S21<>"",S21<0)),"EXPIRED",IF(OR(AND(R21<>"",R21<=Settings!$B$15),AND(S21<>"",S21<=Settings!$B$15)),"EXPIRING SOON","OK"))) -> OK | U21: =IF(AND(C21="Own",Q21="Active"),COUNTIFS($C$5:C21,"Own",$Q$5:Q21,"Active"),"") -> 17 | V21: =IF(C21<>"Own","",IF(K21="Hourly",N21,(L21+M21)/(Settings!$B$11*Settings!$B$12))) -> 8.6538462
A22: W0018 | B22: Nabin Pillai | C22: Own | E22: Security Guard | F22: India | G22: P3232933 | H22: 60764954880477 | I22: 46339 | J22: 46339 | K22: Monthly | L22: 2500 | M22: 300 | O22: 803320101 | P22: AE58 8395 1831 1308 9707 797 | Q22: Active | R22: =IF(I22="","",I22-TODAY()) -> 12 | S22: =IF(J22="","",J22-TODAY()) -> 12 | T22: =IF(A22="","",IF(OR(AND(R22<>"",R22<0),AND(S22<>"",S22<0)),"EXPIRED",IF(OR(AND(R22<>"",R22<=Settings!$B$15),AND(S22<>"",S22<=Settings!$B$15)),"EXPIRING SOON","OK"))) -> EXPIRING SOON | U22: =IF(AND(C22="Own",Q22="Active"),COUNTIFS($C$5:C22,"Own",$Q$5:Q22,"Active"),"") -> 18 | V22: =IF(C22<>"Own","",IF(K22="Hourly",N22,(L22+M22)/(Settings!$B$11*Settings!$B$12))) -> 13.461538
A23: W0019 | B23: Faisal Ahmed | C23: Own | E23: Helper | F23: Pakistan | G23: P4442978 | H23: 79516022831268 | I23: 46645 | J23: 46650 | K23: Monthly | L23: 2000 | M23: 300 | O23: 600310101 | P23: AE19 8848 5707 1765 4248 179 | Q23: Active | R23: =IF(I23="","",I23-TODAY()) -> 318 | S23: =IF(J23="","",J23-TODAY()) -> 323 | T23: =IF(A23="","",IF(OR(AND(R23<>"",R23<0),AND(S23<>"",S23<0)),"EXPIRED",IF(OR(AND(R23<>"",R23<=Settings!$B$15),AND(S23<>"",S23<=Settings!$B$15)),"EXPIRING SOON","OK"))) -> OK | U23: =IF(AND(C23="Own",Q23="Active"),COUNTIFS($C$5:C23,"Own",$Q$5:Q23,"Active"),"") -> 19 | V23: =IF(C23<>"Own","",IF(K23="Hourly",N23,(L23+M23)/(Settings!$B$11*Settings!$B$12))) -> 11.057692
A24: W0020 | B24: Shafi Nair | C24: Own | E24: Cleaner | F24: Bangladesh | G24: P5879761 | H24: 82695366062236 | I24: 46449 | J24: 46449 | K24: Monthly | L24: 2500 | M24: 500 | O24: 600310101 | P24: AE69 8633 8640 2941 9996 304 | Q24: Active | R24: =IF(I24="","",I24-TODAY()) -> 122 | S24: =IF(J24="","",J24-TODAY()) -> 122 | T24: =IF(A24="","",IF(OR(AND(R24<>"",R24<0),AND(S24<>"",S24<0)),"EXPIRED",IF(OR(AND(R24<>"",R24<=Settings!$B$15),AND(S24<>"",S24<=Settings!$B$15)),"EXPIRING SOON","OK"))) -> OK | U24: =IF(AND(C24="Own",Q24="Active"),COUNTIFS($C$5:C24,"Own",$Q$5:Q24,"Active"),"") -> 20 | V24: =IF(C24<>"Own","",IF(K24="Hourly",N24,(L24+M24)/(Settings!$B$11*Settings!$B$12))) -> 14.423077
A25: W0021 | B25: Sanjay Ali | C25: Own | E25: Driver | F25: Pakistan | G25: P9792363 | H25: 28663177171983 | I25: 46847 | J25: 46847 | K25: Monthly | L25: 1500 | M25: 400 | O25: 402320106 | P25: AE90 9335 5580 2846 6983 336 | Q25: Active | R25: =IF(I25="","",I25-TODAY()) -> 520 | S25: =IF(J25="","",J25-TODAY()) -> 520 | T25: =IF(A25="","",IF(OR(AND(R25<>"",R25<0),AND(S25<>"",S25<0)),"EXPIRED",IF(OR(AND(R25<>"",R25<=Settings!$B$15),AND(S25<>"",S25<=Settings!$B$15)),"EXPIRING SOON","OK"))) -> OK | U25: =IF(AND(C25="Own",Q25="Active"),COUNTIFS($C$5:C25,"Own",$Q$5:Q25,"Active"),"") -> 21 | V25: =IF(C25<>"Own","",IF(K25="Hourly",N25,(L25+M25)/(Settings!$B$11*Settings!$B$12))) -> 9.1346154
A26: W0022 | B26: Jamal Varghese | C26: Own | E26: Cleaner | F26: India | G26: P6558700 | H26: 55672689704836 | I26: 46549 | J26: 46554 | K26: Monthly | L26: 1500 | M26: 400 | O26: 600310101 | P26: AE60 2966 4207 1192 5748 359 | Q26: Active | R26: =IF(I26="","",I26-TODAY()) -> 222 | S26: =IF(J26="","",J26-TODAY()) -> 227 | T26: =IF(A26="","",IF(OR(AND(R26<>"",R26<0),AND(S26<>"",S26<0)),"EXPIRED",IF(OR(AND(R26<>"",R26<=Settings!$B$15),AND(S26<>"",S26<=Settings!$B$15)),"EXPIRING SOON","OK"))) -> OK | U26: =IF(AND(C26="Own",Q26="Active"),COUNTIFS($C$5:C26,"Own",$Q$5:Q26,"Active"),"") -> 22 | V26: =IF(C26<>"Own","",IF(K26="Hourly",N26,(L26+M26)/(Settings!$B$11*Settings!$B$12))) -> 9.1346154
A27: W0023 | B27: Bikash Ali | C27: Own | E27: Electrician | F27: Pakistan | G27: P5458176 | H27: 81912511076662 | I27: 46436 | J27: 46436 | K27: Monthly | L27: 1400 | M27: 500 | O27: 600310101 | P27: AE34 7116 8008 1475 7554 996 | Q27: Active | R27: =IF(I27="","",I27-TODAY()) -> 109 | S27: =IF(J27="","",J27-TODAY()) -> 109 | T27: =IF(A27="","",IF(OR(AND(R27<>"",R27<0),AND(S27<>"",S27<0)),"EXPIRED",IF(OR(AND(R27<>"",R27<=Settings!$B$15),AND(S27<>"",S27<=Settings!$B$15)),"EXPIRING SOON","OK"))) -> OK | U27: =IF(AND(C27="Own",Q27="Active"),COUNTIFS($C$5:C27,"Own",$Q$5:Q27,"Active"),"") -> 23 | V27: =IF(C27<>"Own","",IF(K27="Hourly",N27,(L27+M27)/(Settings!$B$11*Settings!$B$12))) -> 9.1346154
A28: W0024 | B28: Tariq Gurung | C28: Own | E28: Electrician | F28: Bangladesh | G28: P6765705 | H28: 51907205997105 | I28: 46352 | J28: 46357 | K28: Hourly | N28: 11 | O28: 600310101 | P28: AE93 5262 7655 4910 5928 594 | Q28: Active | R28: =IF(I28="","",I28-TODAY()) -> 25 | S28: =IF(J28="","",J28-TODAY()) -> 30 | T28: =IF(A28="","",IF(OR(AND(R28<>"",R28<0),AND(S28<>"",S28<0)),"EXPIRED",IF(OR(AND(R28<>"",R28<=Settings!$B$15),AND(S28<>"",S28<=Settings!$B$15)),"EXPIRING SOON","OK"))) -> EXPIRING SOON | U28: =IF(AND(C28="Own",Q28="Active"),COUNTIFS($C$5:C28,"Own",$Q$5:Q28,"Active"),"") -> 24 | V28: =IF(C28<>"Own","",IF(K28="Hourly",N28,(L28+M28)/(Settings!$B$11*Settings!$B$12))) -> 11
A29: W0025 | B29: Tariq Santos | C29: Own | E29: Plumber | F29: Bangladesh | G29: P3342033 | H29: 37077826553945 | I29: 46612 | J29: 46617 | K29: Monthly | L29: 2000 | M29: 400 | O29: 803320101 | P29: AE21 3862 6602 2492 6231 344 | Q29: Active | R29: =IF(I29="","",I29-TODAY()) -> 285 | S29: =IF(J29="","",J29-TODAY()) -> 290 | T29: =IF(A29="","",IF(OR(AND(R29<>"",R29<0),AND(S29<>"",S29<0)),"EXPIRED",IF(OR(AND(R29<>"",R29<=Settings!$B$15),AND(S29<>"",S29<=Settings!$B$15)),"EXPIRING SOON","OK"))) -> OK | U29: =IF(AND(C29="Own",Q29="Active"),COUNTIFS($C$5:C29,"Own",$Q$5:Q29,"Active"),"") -> 25 | V29: =IF(C29<>"Own","",IF(K29="Hourly",N29,(L29+M29)/(Settings!$B$11*Settings!$B$12))) -> 11.538462
A30: W0026 | B30: Bikash Thapa | C30: Own | E30: Steel Fixer | F30: Philippines | G30: P7042234 | H30: 84481189948222 | I30: 46779 | J30: 46784 | K30: Monthly | L30: 2500 | M30: 400 | O30: 402320106 | P30: AE37 2517 5440 5070 7300 509 | Q30: Active | R30: =IF(I30="","",I30-TODAY()) -> 452 | S30: =IF(J30="","",J30-TODAY()) -> 457 | T30: =IF(A30="","",IF(OR(AND(R30<>"",R30<0),AND(S30<>"",S30<0)),"EXPIRED",IF(OR(AND(R30<>"",R30<=Settings!$B$15),AND(S30<>"",S30<=Settings!$B$15)),"EXPIRING SOON","OK"))) -> OK | U30: =IF(AND(C30="Own",Q30="Active"),COUNTIFS($C$5:C30,"Own",$Q$5:Q30,"Active"),"") -> 26 | V30: =IF(C30<>"Own","",IF(K30="Hourly",N30,(L30+M30)/(Settings!$B$11*Settings!$B$12))) -> 13.942308
A31: W0027 | B31: Ronel Ahmed | C31: Own | E31: Plumber | F31: Bangladesh | G31: P8532138 | H31: 41495463530590 | I31: 46787 | J31: 46827 | K31: Monthly | L31: 2000 | M31: 300 | O31: 803320101 | P31: AE29 9558 2784 8492 2392 664 | Q31: Active | R31: =IF(I31="","",I31-TODAY()) -> 460 | S31: =IF(J31="","",J31-TODAY()) -> 500 | T31: =IF(A31="","",IF(OR(AND(R31<>"",R31<0),AND(S31<>"",S31<0)),"EXPIRED",IF(OR(AND(R31<>"",R31<=Settings!$B$15),AND(S31<>"",S31<=Settings!$B$15)),"EXPIRING SOON","OK"))) -> OK | U31: =IF(AND(C31="Own",Q31="Active"),COUNTIFS($C$5:C31,"Own",$Q$5:Q31,"Active"),"") -> 27 | V31: =IF(C31<>"Own","",IF(K31="Hourly",N31,(L31+M31)/(Settings!$B$11*Settings!$B$12))) -> 11.057692
A32: W0028 | B32: Anwar Kumar | C32: Own | E32: Mason | F32: Philippines | G32: P4216221 | H32: 46715047245502 | I32: 46625 | J32: 46665 | K32: Monthly | L32: 2000 | M32: 400 | O32: 803320101 | P32: AE86 1018 1171 9806 5940 571 | Q32: Active | R32: =IF(I32="","",I32-TODAY()) -> 298 | S32: =IF(J32="","",J32-TODAY()) -> 338 | T32: =IF(A32="","",IF(OR(AND(R32<>"",R32<0),AND(S32<>"",S32<0)),"EXPIRED",IF(OR(AND(R32<>"",R32<=Settings!$B$15),AND(S32<>"",S32<=Settings!$B$15)),"EXPIRING SOON","OK"))) -> OK | U32: =IF(AND(C32="Own",Q32="Active"),COUNTIFS($C$5:C32,"Own",$Q$5:Q32,"Active"),"") -> 28 | V32: =IF(C32<>"Own","",IF(K32="Hourly",N32,(L32+M32)/(Settings!$B$11*Settings!$B$12))) -> 11.538462
A33: W0029 | B33: Joseph Hossain | C33: Own | E33: Carpenter | F33: Bangladesh | G33: P2360499 | H33: 42063035771278 | I33: 46947 | J33: 46987 | K33: Monthly | L33: 1500 | M33: 300 | O33: 402320106 | P33: AE64 7065 4715 9076 1558 812 | Q33: Active | R33: =IF(I33="","",I33-TODAY()) -> 620 | S33: =IF(J33="","",J33-TODAY()) -> 660 | T33: =IF(A33="","",IF(OR(AND(R33<>"",R33<0),AND(S33<>"",S33<0)),"EXPIRED",IF(OR(AND(R33<>"",R33<=Settings!$B$15),AND(S33<>"",S33<=Settings!$B$15)),"EXPIRING SOON","OK"))) -> OK | U33: =IF(AND(C33="Own",Q33="Active"),COUNTIFS($C$5:C33,"Own",$Q$5:Q33,"Active"),"") -> 29 | V33: =IF(C33<>"Own","",IF(K33="Hourly",N33,(L33+M33)/(Settings!$B$11*Settings!$B$12))) -> 8.6538462
A34: W0030 | B34: Asif Reyes | C34: Own | E34: Cleaner | F34: Pakistan | G34: P8803319 | H34: 47298447088097 | I34: 46894 | J34: 46894 | K34: Monthly | L34: 1800 | M34: 300 | O34: 600310101 | P34: AE23 9122 4068 4658 8947 527 | Q34: Active | R34: =IF(I34="","",I34-TODAY()) -> 567 | S34: =IF(J34="","",J34-TODAY()) -> 567 | T34: =IF(A34="","",IF(OR(AND(R34<>"",R34<0),AND(S34<>"",S34<0)),"EXPIRED",IF(OR(AND(R34<>"",R34<=Settings!$B$15),AND(S34<>"",S34<=Settings!$B$15)),"EXPIRING SOON","OK"))) -> OK | U34: =IF(AND(C34="Own",Q34="Active"),COUNTIFS($C$5:C34,"Own",$Q$5:Q34,"Active"),"") -> 30 | V34: =IF(C34<>"Own","",IF(K34="Hourly",N34,(L34+M34)/(Settings!$B$11*Settings!$B$12))) -> 10.096154
A35: W0031 | B35: Marlon Kumar | C35: Own | E35: Mason | F35: Nepal | G35: P2899274 | H35: 21171199327519 | I35: 46442 | J35: 46447 | K35: Monthly | L35: 2000 | M35: 500 | O35: 803320101 | P35: AE52 4124 4039 9598 8661 132 | Q35: Active | R35: =IF(I35="","",I35-TODAY()) -> 115 | S35: =IF(J35="","",J35-TODAY()) -> 120 | T35: =IF(A35="","",IF(OR(AND(R35<>"",R35<0),AND(S35<>"",S35<0)),"EXPIRED",IF(OR(AND(R35<>"",R35<=Settings!$B$15),AND(S35<>"",S35<=Settings!$B$15)),"EXPIRING SOON","OK"))) -> OK | U35: =IF(AND(C35="Own",Q35="Active"),COUNTIFS($C$5:C35,"Own",$Q$5:Q35,"Active"),"") -> 31 | V35: =IF(C35<>"Own","",IF(K35="Hourly",N35,(L35+M35)/(Settings!$B$11*Settings!$B$12))) -> 12.019231
A36: W0032 | B36: Sanjay Santos | C36: Own | E36: Steel Fixer | F36: Philippines | G36: P4479635 | H36: 60192620465646 | I36: 46817 | J36: 46817 | K36: Hourly | N36: 11 | O36: 600310101 | P36: AE65 2437 1807 8757 4206 481 | Q36: Active | R36: =IF(I36="","",I36-TODAY()) -> 490 | S36: =IF(J36="","",J36-TODAY()) -> 490 | T36: =IF(A36="","",IF(OR(AND(R36<>"",R36<0),AND(S36<>"",S36<0)),"EXPIRED",IF(OR(AND(R36<>"",R36<=Settings!$B$15),AND(S36<>"",S36<=Settings!$B$15)),"EXPIRING SOON","OK"))) -> OK | U36: =IF(AND(C36="Own",Q36="Active"),COUNTIFS($C$5:C36,"Own",$Q$5:Q36,"Active"),"") -> 32 | V36: =IF(C36<>"Own","",IF(K36="Hourly",N36,(L36+M36)/(Settings!$B$11*Settings!$B$12))) -> 11
A37: W0033 | B37: Tariq Varghese | C37: Own | E37: Steel Fixer | F37: India | G37: P2040252 | H37: 37433059994682 | I37: 46317 | J37: 46322 | K37: Monthly | L37: 2000 | M37: 400 | O37: 402320106 | P37: AE18 6555 6946 5461 6488 731 | Q37: Active | R37: =IF(I37="","",I37-TODAY()) -> -10 | S37: =IF(J37="","",J37-TODAY()) -> -5 | T37: =IF(A37="","",IF(OR(AND(R37<>"",R37<0),AND(S37<>"",S37<0)),"EXPIRED",IF(OR(AND(R37<>"",R37<=Settings!$B$15),AND(S37<>"",S37<=Settings!$B$15)),"EXPIRING SOON","OK"))) -> EXPIRED | U37: =IF(AND(C37="Own",Q37="Active"),COUNTIFS($C$5:C37,"Own",$Q$5:Q37,"Active"),"") -> 33 | V37: =IF(C37<>"Own","",IF(K37="Hourly",N37,(L37+M37)/(Settings!$B$11*Settings!$B$12))) -> 11.538462
A38: W0034 | B38: Anwar Thapa | C38: Own | E38: Cleaner | F38: Bangladesh | G38: P9279117 | H38: 35746166597902 | I38: 46873 | J38: 46878 | K38: Monthly | L38: 1200 | M38: 300 | O38: 803320101 | P38: AE48 3479 4868 6370 6235 571 | Q38: Active | R38: =IF(I38="","",I38-TODAY()) -> 546 | S38: =IF(J38="","",J38-TODAY()) -> 551 | T38: =IF(A38="","",IF(OR(AND(R38<>"",R38<0),AND(S38<>"",S38<0)),"EXPIRED",IF(OR(AND(R38<>"",R38<=Settings!$B$15),AND(S38<>"",S38<=Settings!$B$15)),"EXPIRING SOON","OK"))) -> OK | U38: =IF(AND(C38="Own",Q38="Active"),COUNTIFS($C$5:C38,"Own",$Q$5:Q38,"Active"),"") -> 34 | V38: =IF(C38<>"Own","",IF(K38="Hourly",N38,(L38+M38)/(Settings!$B$11*Settings!$B$12))) -> 7.2115385
A39: W0035 | B39: Bikash Shrestha | C39: Own | E39: Plumber | F39: Pakistan | G39: P8156393 | H39: 24808546763942 | I39: 46550 | J39: 46555 | K39: Monthly | L39: 1800 | M39: 500 | O39: 803320101 | P39: AE43 2377 4413 2579 7898 610 | Q39: Active | R39: =IF(I39="","",I39-TODAY()) -> 223 | S39: =IF(J39="","",J39-TODAY()) -> 228 | T39: =IF(A39="","",IF(OR(AND(R39<>"",R39<0),AND(S39<>"",S39<0)),"EXPIRED",IF(OR(AND(R39<>"",R39<=Settings!$B$15),AND(S39<>"",S39<=Settings!$B$15)),"EXPIRING SOON","OK"))) -> OK | U39: =IF(AND(C39="Own",Q39="Active"),COUNTIFS($C$5:C39,"Own",$Q$5:Q39,"Active"),"") -> 35 | V39: =IF(C39<>"Own","",IF(K39="Hourly",N39,(L39+M39)/(Settings!$B$11*Settings!$B$12))) -> 11.057692
A40: W0036 | B40: Dinesh Ahmed | C40: Own | E40: Mason | F40: Nepal | G40: P5262360 | H40: 46639241010357 | I40: 46627 | J40: 46632 | K40: Monthly | L40: 1200 | M40: 500 | O40: 803320101 | P40: AE66 5053 4043 5019 4858 257 | Q40: Active | R40: =IF(I40="","",I40-TODAY()) -> 300 | S40: =IF(J40="","",J40-TODAY()) -> 305 | T40: =IF(A40="","",IF(OR(AND(R40<>"",R40<0),AND(S40<>"",S40<0)),"EXPIRED",IF(OR(AND(R40<>"",R40<=Settings!$B$15),AND(S40<>"",S40<=Settings!$B$15)),"EXPIRING SOON","OK"))) -> OK | U40: =IF(AND(C40="Own",Q40="Active"),COUNTIFS($C$5:C40,"Own",$Q$5:Q40,"Active"),"") -> 36 | V40: =IF(C40<>"Own","",IF(K40="Hourly",N40,(L40+M40)/(Settings!$B$11*Settings!$B$12))) -> 8.1730769
A41: W0037 | B41: Sanjay Varghese | C41: Own | E41: Plumber | F41: India | G41: P8965197 | H41: 15679552551765 | I41: 46317 | J41: 46317 | K41: Monthly | L41: 2500 | M41: 500 | O41: 600310101 | P41: AE39 2953 1825 4105 4181 176 | Q41: Active | R41: =IF(I41="","",I41-TODAY()) -> -10 | S41: =IF(J41="","",J41-TODAY()) -> -10 | T41: =IF(A41="","",IF(OR(AND(R41<>"",R41<0),AND(S41<>"",S41<0)),"EXPIRED",IF(OR(AND(R41<>"",R41<=Settings!$B$15),AND(S41<>"",S41<=Settings!$B$15)),"EXPIRING SOON","OK"))) -> EXPIRED | U41: =IF(AND(C41="Own",Q41="Active"),COUNTIFS($C$5:C41,"Own",$Q$5:Q41,"Active"),"") -> 37 | V41: =IF(C41<>"Own","",IF(K41="Hourly",N41,(L41+M41)/(Settings!$B$11*Settings!$B$12))) -> 14.423077
A42: W0038 | B42: Bikash Gurung | C42: Own | E42: Cleaner | F42: India | G42: P4422156 | H42: 45880156248589 | I42: 47004 | J42: 47004 | K42: Monthly | L42: 1500 | M42: 500 | O42: 803320101 | P42: AE86 4333 1186 6361 7700 794 | Q42: Active | R42: =IF(I42="","",I42-TODAY()) -> 677 | S42: =IF(J42="","",J42-TODAY()) -> 677 | T42: =IF(A42="","",IF(OR(AND(R42<>"",R42<0),AND(S42<>"",S42<0)),"EXPIRED",IF(OR(AND(R42<>"",R42<=Settings!$B$15),AND(S42<>"",S42<=Settings!$B$15)),"EXPIRING SOON","OK"))) -> OK | U42: =IF(AND(C42="Own",Q42="Active"),COUNTIFS($C$5:C42,"Own",$Q$5:Q42,"Active"),"") -> 38 | V42: =IF(C42<>"Own","",IF(K42="Hourly",N42,(L42+M42)/(Settings!$B$11*Settings!$B$12))) -> 9.6153846
A43: W0039 | B43: Bikash Nair | C43: Own | E43: Driver | F43: Pakistan | G43: P9958985 | H43: 65981306776326 | I43: 46882 | J43: 46922 | K43: Monthly | L43: 2500 | M43: 400 | O43: 402320106 | P43: AE44 7713 5641 6039 7845 152 | Q43: Active | R43: =IF(I43="","",I43-TODAY()) -> 555 | S43: =IF(J43="","",J43-TODAY()) -> 595 | T43: =IF(A43="","",IF(OR(AND(R43<>"",R43<0),AND(S43<>"",S43<0)),"EXPIRED",IF(OR(AND(R43<>"",R43<=Settings!$B$15),AND(S43<>"",S43<=Settings!$B$15)),"EXPIRING SOON","OK"))) -> OK | U43: =IF(AND(C43="Own",Q43="Active"),COUNTIFS($C$5:C43,"Own",$Q$5:Q43,"Active"),"") -> 39 | V43: =IF(C43<>"Own","",IF(K43="Hourly",N43,(L43+M43)/(Settings!$B$11*Settings!$B$12))) -> 13.942308
A44: W0040 | B44: Sanjay Reyes | C44: Own | E44: Helper | F44: Bangladesh | G44: P2904873 | H44: 22738101488894 | I44: 46831 | J44: 46831 | K44: Hourly | N44: 10 | O44: 600310101 | P44: AE83 6975 8551 3663 3129 115 | Q44: Active | R44: =IF(I44="","",I44-TODAY()) -> 504 | S44: =IF(J44="","",J44-TODAY()) -> 504 | T44: =IF(A44="","",IF(OR(AND(R44<>"",R44<0),AND(S44<>"",S44<0)),"EXPIRED",IF(OR(AND(R44<>"",R44<=Settings!$B$15),AND(S44<>"",S44<=Settings!$B$15)),"EXPIRING SOON","OK"))) -> OK | U44: =IF(AND(C44="Own",Q44="Active"),COUNTIFS($C$5:C44,"Own",$Q$5:Q44,"Active"),"") -> 40 | V44: =IF(C44<>"Own","",IF(K44="Hourly",N44,(L44+M44)/(Settings!$B$11*Settings!$B$12))) -> 10
A45: SW0001 | B45: Anwar Gurung | C45: Supplier | D45: S001 | E45: Carpenter | F45: India | G45: P2825241 | I45: 46766 | J45: 46766 | Q45: Active | R45: =IF(I45="","",I45-TODAY()) -> 439 | S45: =IF(J45="","",J45-TODAY()) -> 439 | T45: =IF(A45="","",IF(OR(AND(R45<>"",R45<0),AND(S45<>"",S45<0)),"EXPIRED",IF(OR(AND(R45<>"",R45<=Settings!$B$15),AND(S45<>"",S45<=Settings!$B$15)),"EXPIRING SOON","OK"))) -> OK | U45: =IF(AND(C45="Own",Q45="Active"),COUNTIFS($C$5:C45,"Own",$Q$5:Q45,"Active"),"") | V45: =IF(C45<>"Own","",IF(K45="Hourly",N45,(L45+M45)/(Settings!$B$11*Settings!$B$12)))
A46: SW0002 | B46: Rohan Ahmed | C46: Supplier | D46: S002 | E46: Mason | F46: Philippines | G46: P7786124 | I46: 47009 | J46: 47009 | Q46: Active | R46: =IF(I46="","",I46-TODAY()) -> 682 | S46: =IF(J46="","",J46-TODAY()) -> 682 | T46: =IF(A46="","",IF(OR(AND(R46<>"",R46<0),AND(S46<>"",S46<0)),"EXPIRED",IF(OR(AND(R46<>"",R46<=Settings!$B$15),AND(S46<>"",S46<=Settings!$B$15)),"EXPIRING SOON","OK"))) -> OK | U46: =IF(AND(C46="Own",Q46="Active"),COUNTIFS($C$5:C46,"Own",$Q$5:Q46,"Active"),"") | V46: =IF(C46<>"Own","",IF(K46="Hourly",N46,(L46+M46)/(Settings!$B$11*Settings!$B$12)))
A47: SW0003 | B47: Shafi Rahman | C47: Supplier | D47: S003 | E47: Cleaner | F47: Pakistan | G47: P1689527 | I47: 46352 | J47: 46352 | Q47: Active | R47: =IF(I47="","",I47-TODAY()) -> 25 | S47: =IF(J47="","",J47-TODAY()) -> 25 | T47: =IF(A47="","",IF(OR(AND(R47<>"",R47<0),AND(S47<>"",S47<0)),"EXPIRED",IF(OR(AND(R47<>"",R47<=Settings!$B$15),AND(S47<>"",S47<=Settings!$B$15)),"EXPIRING SOON","OK"))) -> EXPIRING SOON | U47: =IF(AND(C47="Own",Q47="Active"),COUNTIFS($C$5:C47,"Own",$Q$5:Q47,"Active"),"") | V47: =IF(C47<>"Own","",IF(K47="Hourly",N47,(L47+M47)/(Settings!$B$11*Settings!$B$12)))
A48: SW0004 | B48: Tariq Rahman | C48: Supplier | D48: S001 | E48: Helper | F48: Nepal | G48: P8495882 | I48: 46786 | J48: 46791 | Q48: Active | R48: =IF(I48="","",I48-TODAY()) -> 459 | S48: =IF(J48="","",J48-TODAY()) -> 464 | T48: =IF(A48="","",IF(OR(AND(R48<>"",R48<0),AND(S48<>"",S48<0)),"EXPIRED",IF(OR(AND(R48<>"",R48<=Settings!$B$15),AND(S48<>"",S48<=Settings!$B$15)),"EXPIRING SOON","OK"))) -> OK | U48: =IF(AND(C48="Own",Q48="Active"),COUNTIFS($C$5:C48,"Own",$Q$5:Q48,"Active"),"") | V48: =IF(C48<>"Own","",IF(K48="Hourly",N48,(L48+M48)/(Settings!$B$11*Settings!$B$12)))
A49: SW0005 | B49: Mohan Ahmed | C49: Supplier | D49: S002 | E49: Electrician | F49: India | G49: P3155132 | I49: 47020 | J49: 47020 | Q49: Active | R49: =IF(I49="","",I49-TODAY()) -> 693 | S49: =IF(J49="","",J49-TODAY()) -> 693 | T49: =IF(A49="","",IF(OR(AND(R49<>"",R49<0),AND(S49<>"",S49<0)),"EXPIRED",IF(OR(AND(R49<>"",R49<=Settings!$B$15),AND(S49<>"",S49<=Settings!$B$15)),"EXPIRING SOON","OK"))) -> OK | U49: =IF(AND(C49="Own",Q49="Active"),COUNTIFS($C$5:C49,"Own",$Q$5:Q49,"Active"),"") | V49: =IF(C49<>"Own","",IF(K49="Hourly",N49,(L49+M49)/(Settings!$B$11*Settings!$B$12)))
A50: SW0006 | B50: Bikash Menon | C50: Supplier | D50: S003 | E50: Plumber | F50: Bangladesh | G50: P3284817 | I50: 46317 | J50: 46357 | Q50: Active | R50: =IF(I50="","",I50-TODAY()) -> -10 | S50: =IF(J50="","",J50-TODAY()) -> 30 | T50: =IF(A50="","",IF(OR(AND(R50<>"",R50<0),AND(S50<>"",S50<0)),"EXPIRED",IF(OR(AND(R50<>"",R50<=Settings!$B$15),AND(S50<>"",S50<=Settings!$B$15)),"EXPIRING SOON","OK"))) -> EXPIRED | U50: =IF(AND(C50="Own",Q50="Active"),COUNTIFS($C$5:C50,"Own",$Q$5:Q50,"Active"),"") | V50: =IF(C50<>"Own","",IF(K50="Hourly",N50,(L50+M50)/(Settings!$B$11*Settings!$B$12)))
A51: SW0007 | B51: Rahul Rahman | C51: Supplier | D51: S001 | E51: Carpenter | F51: Pakistan | G51: P6433116 | I51: 46454 | J51: 46459 | Q51: Active | R51: =IF(I51="","",I51-TODAY()) -> 127 | S51: =IF(J51="","",J51-TODAY()) -> 132 | T51: =IF(A51="","",IF(OR(AND(R51<>"",R51<0),AND(S51<>"",S51<0)),"EXPIRED",IF(OR(AND(R51<>"",R51<=Settings!$B$15),AND(S51<>"",S51<=Settings!$B$15)),"EXPIRING SOON","OK"))) -> OK | U51: =IF(AND(C51="Own",Q51="Active"),COUNTIFS($C$5:C51,"Own",$Q$5:Q51,"Active"),"") | V51: =IF(C51<>"Own","",IF(K51="Hourly",N51,(L51+M51)/(Settings!$B$11*Settings!$B$12)))
A52: SW0008 | B52: Shafi Thapa | C52: Supplier | D52: S002 | E52: Electrician | F52: Pakistan | G52: P4055070 | I52: 46647 | J52: 46647 | Q52: Active | R52: =IF(I52="","",I52-TODAY()) -> 320 | S52: =IF(J52="","",J52-TODAY()) -> 320 | T52: =IF(A52="","",IF(OR(AND(R52<>"",R52<0),AND(S52<>"",S52<0)),"EXPIRED",IF(OR(AND(R52<>"",R52<=Settings!$B$15),AND(S52<>"",S52<=Settings!$B$15)),"EXPIRING SOON","OK"))) -> OK | U52: =IF(AND(C52="Own",Q52="Active"),COUNTIFS($C$5:C52,"Own",$Q$5:Q52,"Active"),"") | V52: =IF(C52<>"Own","",IF(K52="Hourly",N52,(L52+M52)/(Settings!$B$11*Settings!$B$12)))
A53: SW0009 | B53: Rohan Nair | C53: Supplier | D53: S003 | E53: Driver | F53: India | G53: P5228388 | I53: 46930 | J53: 46970 | Q53: Active | R53: =IF(I53="","",I53-TODAY()) -> 603 | S53: =IF(J53="","",J53-TODAY()) -> 643 | T53: =IF(A53="","",IF(OR(AND(R53<>"",R53<0),AND(S53<>"",S53<0)),"EXPIRED",IF(OR(AND(R53<>"",R53<=Settings!$B$15),AND(S53<>"",S53<=Settings!$B$15)),"EXPIRING SOON","OK"))) -> OK | U53: =IF(AND(C53="Own",Q53="Active"),COUNTIFS($C$5:C53,"Own",$Q$5:Q53,"Active"),"") | V53: =IF(C53<>"Own","",IF(K53="Hourly",N53,(L53+M53)/(Settings!$B$11*Settings!$B$12)))
A54: SW0010 | B54: Tariq Santos | C54: Supplier | D54: S001 | E54: Driver | F54: India | G54: P5972488 | I54: 46352 | J54: 46392 | Q54: Active | R54: =IF(I54="","",I54-TODAY()) -> 25 | S54: =IF(J54="","",J54-TODAY()) -> 65 | T54: =IF(A54="","",IF(OR(AND(R54<>"",R54<0),AND(S54<>"",S54<0)),"EXPIRED",IF(OR(AND(R54<>"",R54<=Settings!$B$15),AND(S54<>"",S54<=Settings!$B$15)),"EXPIRING SOON","OK"))) -> EXPIRING SOON | U54: =IF(AND(C54="Own",Q54="Active"),COUNTIFS($C$5:C54,"Own",$Q$5:Q54,"Active"),"") | V54: =IF(C54<>"Own","",IF(K54="Hourly",N54,(L54+M54)/(Settings!$B$11*Settings!$B$12)))
A55: SW0011 | B55: Mohan Thapa | C55: Supplier | D55: S002 | E55: Cleaner | F55: India | G55: P3214983 | I55: 46613 | J55: 46618 | Q55: Active | R55: =IF(I55="","",I55-TODAY()) -> 286 | S55: =IF(J55="","",J55-TODAY()) -> 291 | T55: =IF(A55="","",IF(OR(AND(R55<>"",R55<0),AND(S55<>"",S55<0)),"EXPIRED",IF(OR(AND(R55<>"",R55<=Settings!$B$15),AND(S55<>"",S55<=Settings!$B$15)),"EXPIRING SOON","OK"))) -> OK | U55: =IF(AND(C55="Own",Q55="Active"),COUNTIFS($C$5:C55,"Own",$Q$5:Q55,"Active"),"") | V55: =IF(C55<>"Own","",IF(K55="Hourly",N55,(L55+M55)/(Settings!$B$11*Settings!$B$12)))
A56: SW0012 | B56: Jamal Khan | C56: Supplier | D56: S003 | E56: Mason | F56: Philippines | G56: P6052542 | I56: 47014 | J56: 47019 | Q56: Active | R56: =IF(I56="","",I56-TODAY()) -> 687 | S56: =IF(J56="","",J56-TODAY()) -> 692 | T56: =IF(A56="","",IF(OR(AND(R56<>"",R56<0),AND(S56<>"",S56<0)),"EXPIRED",IF(OR(AND(R56<>"",R56<=Settings!$B$15),AND(S56<>"",S56<=Settings!$B$15)),"EXPIRING SOON","OK"))) -> OK | U56: =IF(AND(C56="Own",Q56="Active"),COUNTIFS($C$5:C56,"Own",$Q$5:Q56,"Active"),"") | V56: =IF(C56<>"Own","",IF(K56="Hourly",N56,(L56+M56)/(Settings!$B$11*Settings!$B$12)))
... A74: SW0030 | B74: Anwar Kumar | C74: Supplier | D74: S003 | E74: Electrician | F74: Bangladesh | G74: P8065805 | I74: 46650 | J74: 46650 | Q74: Active | R74: =IF(I74="","",I74-TODAY()) -> 323 | S74: =IF(J74="","",J74-TODAY()) -> 323 | T74: =IF(A74="","",IF(OR(AND(R74<>"",R74<0),AND(S74<>"",S74<0)),"EXPIRED",IF(OR(AND(R74<>"",R74<=Settings!$B$15),AND(S74<>"",S74<=Settings!$B$15)),"EXPIRING SOON","OK"))) -> OK | U74: =IF(AND(C74="Own",Q74="Active"),COUNTIFS($C$5:C74,"Own",$Q$5:Q74,"Active"),"") | V74: =IF(C74<>"Own","",IF(K74="Hourly",N74,(L74+M74)/(Settings!$B$11*Settings!$B$12)))
R75: =IF(I75="","",I75-TODAY()) | S75: =IF(J75="","",J75-TODAY()) | T75: =IF(A75="","",IF(OR(AND(R75<>"",R75<0),AND(S75<>"",S75<0)),"EXPIRED",IF(OR(AND(R75<>"",R75<=Settings!$B$15),AND(S75<>"",S75<=Settings!$B$15)),"EXPIRING SOON","OK"))) | U75: =IF(AND(C75="Own",Q75="Active"),COUNTIFS($C$5:C75,"Own",$Q$5:Q75,"Active"),"") | V75: =IF(C75<>"Own","",IF(K75="Hourly",N75,(L75+M75)/(Settings!$B$11*Settings!$B$12)))
R76: =IF(I76="","",I76-TODAY()) | S76: =IF(J76="","",J76-TODAY()) | T76: =IF(A76="","",IF(OR(AND(R76<>"",R76<0),AND(S76<>"",S76<0)),"EXPIRED",IF(OR(AND(R76<>"",R76<=Settings!$B$15),AND(S76<>"",S76<=Settings!$B$15)),"EXPIRING SOON","OK"))) | U76: =IF(AND(C76="Own",Q76="Active"),COUNTIFS($C$5:C76,"Own",$Q$5:Q76,"Active"),"") | V76: =IF(C76<>"Own","",IF(K76="Hourly",N76,(L76+M76)/(Settings!$B$11*Settings!$B$12)))
R77: =IF(I77="","",I77-TODAY()) | S77: =IF(J77="","",J77-TODAY()) | T77: =IF(A77="","",IF(OR(AND(R77<>"",R77<0),AND(S77<>"",S77<0)),"EXPIRED",IF(OR(AND(R77<>"",R77<=Settings!$B$15),AND(S77<>"",S77<=Settings!$B$15)),"EXPIRING SOON","OK"))) | U77: =IF(AND(C77="Own",Q77="Active"),COUNTIFS($C$5:C77,"Own",$Q$5:Q77,"Active"),"") | V77: =IF(C77<>"Own","",IF(K77="Hourly",N77,(L77+M77)/(Settings!$B$11*Settings!$B$12)))
R78: =IF(I78="","",I78-TODAY()) | S78: =IF(J78="","",J78-TODAY()) | T78: =IF(A78="","",IF(OR(AND(R78<>"",R78<0),AND(S78<>"",S78<0)),"EXPIRED",IF(OR(AND(R78<>"",R78<=Settings!$B$15),AND(S78<>"",S78<=Settings!$B$15)),"EXPIRING SOON","OK"))) | U78: =IF(AND(C78="Own",Q78="Active"),COUNTIFS($C$5:C78,"Own",$Q$5:Q78,"Active"),"") | V78: =IF(C78<>"Own","",IF(K78="Hourly",N78,(L78+M78)/(Settings!$B$11*Settings!$B$12)))
R79: =IF(I79="","",I79-TODAY()) | S79: =IF(J79="","",J79-TODAY()) | T79: =IF(A79="","",IF(OR(AND(R79<>"",R79<0),AND(S79<>"",S79<0)),"EXPIRED",IF(OR(AND(R79<>"",R79<=Settings!$B$15),AND(S79<>"",S79<=Settings!$B$15)),"EXPIRING SOON","OK"))) | U79: =IF(AND(C79="Own",Q79="Active"),COUNTIFS($C$5:C79,"Own",$Q$5:Q79,"Active"),"") | V79: =IF(C79<>"Own","",IF(K79="Hourly",N79,(L79+M79)/(Settings!$B$11*Settings!$B$12)))
R80: =IF(I80="","",I80-TODAY()) | S80: =IF(J80="","",J80-TODAY()) | T80: =IF(A80="","",IF(OR(AND(R80<>"",R80<0),AND(S80<>"",S80<0)),"EXPIRED",IF(OR(AND(R80<>"",R80<=Settings!$B$15),AND(S80<>"",S80<=Settings!$B$15)),"EXPIRING SOON","OK"))) | U80: =IF(AND(C80="Own",Q80="Active"),COUNTIFS($C$5:C80,"Own",$Q$5:Q80,"Active"),"") | V80: =IF(C80<>"Own","",IF(K80="Hourly",N80,(L80+M80)/(Settings!$B$11*Settings!$B$12)))
R81: =IF(I81="","",I81-TODAY()) | S81: =IF(J81="","",J81-TODAY()) | T81: =IF(A81="","",IF(OR(AND(R81<>"",R81<0),AND(S81<>"",S81<0)),"EXPIRED",IF(OR(AND(R81<>"",R81<=Settings!$B$15),AND(S81<>"",S81<=Settings!$B$15)),"EXPIRING SOON","OK"))) | U81: =IF(AND(C81="Own",Q81="Active"),COUNTIFS($C$5:C81,"Own",$Q$5:Q81,"Active"),"") | V81: =IF(C81<>"Own","",IF(K81="Hourly",N81,(L81+M81)/(Settings!$B$11*Settings!$B$12)))
R82: =IF(I82="","",I82-TODAY()) | S82: =IF(J82="","",J82-TODAY()) | T82: =IF(A82="","",IF(OR(AND(R82<>"",R82<0),AND(S82<>"",S82<0)),"EXPIRED",IF(OR(AND(R82<>"",R82<=Settings!$B$15),AND(S82<>"",S82<=Settings!$B$15)),"EXPIRING SOON","OK"))) | U82: =IF(AND(C82="Own",Q82="Active"),COUNTIFS($C$5:C82,"Own",$Q$5:Q82,"Active"),"") | V82: =IF(C82<>"Own","",IF(K82="Hourly",N82,(L82+M82)/(Settings!$B$11*Settings!$B$12)))
R83: =IF(I83="","",I83-TODAY()) | S83: =IF(J83="","",J83-TODAY()) | T83: =IF(A83="","",IF(OR(AND(R83<>"",R83<0),AND(S83<>"",S83<0)),"EXPIRED",IF(OR(AND(R83<>"",R83<=Settings!$B$15),AND(S83<>"",S83<=Settings!$B$15)),"EXPIRING SOON","OK"))) | U83: =IF(AND(C83="Own",Q83="Active"),COUNTIFS($C$5:C83,"Own",$Q$5:Q83,"Active"),"") | V83: =IF(C83<>"Own","",IF(K83="Hourly",N83,(L83+M83)/(Settings!$B$11*Settings!$B$12)))
R84: =IF(I84="","",I84-TODAY()) | S84: =IF(J84="","",J84-TODAY()) | T84: =IF(A84="","",IF(OR(AND(R84<>"",R84<0),AND(S84<>"",S84<0)),"EXPIRED",IF(OR(AND(R84<>"",R84<=Settings!$B$15),AND(S84<>"",S84<=Settings!$B$15)),"EXPIRING SOON","OK"))) | U84: =IF(AND(C84="Own",Q84="Active"),COUNTIFS($C$5:C84,"Own",$Q$5:Q84,"Active"),"") | V84: =IF(C84<>"Own","",IF(K84="Hourly",N84,(L84+M84)/(Settings!$B$11*Settings!$B$12)))
R85: =IF(I85="","",I85-TODAY()) | S85: =IF(J85="","",J85-TODAY()) | T85: =IF(A85="","",IF(OR(AND(R85<>"",R85<0),AND(S85<>"",S85<0)),"EXPIRED",IF(OR(AND(R85<>"",R85<=Settings!$B$15),AND(S85<>"",S85<=Settings!$B$15)),"EXPIRING SOON","OK"))) | U85: =IF(AND(C85="Own",Q85="Active"),COUNTIFS($C$5:C85,"Own",$Q$5:Q85,"Active"),"") | V85: =IF(C85<>"Own","",IF(K85="Hourly",N85,(L85+M85)/(Settings!$B$11*Settings!$B$12)))
R86: =IF(I86="","",I86-TODAY()) | S86: =IF(J86="","",J86-TODAY()) | T86: =IF(A86="","",IF(OR(AND(R86<>"",R86<0),AND(S86<>"",S86<0)),"EXPIRED",IF(OR(AND(R86<>"",R86<=Settings!$B$15),AND(S86<>"",S86<=Settings!$B$15)),"EXPIRING SOON","OK"))) | U86: =IF(AND(C86="Own",Q86="Active"),COUNTIFS($C$5:C86,"Own",$Q$5:Q86,"Active"),"") | V86: =IF(C86<>"Own","",IF(K86="Hourly",N86,(L86+M86)/(Settings!$B$11*Settings!$B$12)))
... R2004: =IF(I2004="","",I2004-TODAY()) | S2004: =IF(J2004="","",J2004-TODAY()) | T2004: =IF(A2004="","",IF(OR(AND(R2004<>"",R2004<0),AND(S2004<>"",S2004<0)),"EXPIRED",IF(OR(AND(R2004<>"",R2004<=Settings!$B$15),AND(S2004<>"",S2004<=Settings!$B$15)),"EXPIRING SOON","OK"))) | U2004: =IF(AND(C2004="Own",Q2004="Active"),COUNTIFS($C$5:C2004,"Own",$Q$5:Q2004,"Active"),"") | V2004: =IF(C2004<>"Own","",IF(K2004="Hourly",N2004,(L2004+M2004)/(Settings!$B$11*Settings!$B$12)))

Sheet Timesheet
A1: Timesheet (from Client) | E1: « HOME
A2: One row per worker per client per month. Enter columns A-H only; columns I-T calculate automatically.
A4: Month (1st day) | B4: Client ID | C4: Site / Project | D4: Worker ID | E4: Days Worked | F4: Normal Hours | G4: OT Hours | H4: Client Timesheet Ref | I4: Worker Name | J4: Source | K4: Supplier ID | L4: Trade | M4: Bill Rate / hr | N4: Bill OT Rate / hr | O4: Billing Amount (AED) | P4: Supplier Rate / hr | Q4: Supplier OT Rate / hr | R4: Supplier Cost (AED) | S4: Own Worker Cost Est. (AED) | T4: Gross Profit (AED)
A5: 46296 | B5: C002 | C5: Yas Mall FM | D5: W0001 | E5: 26 | F5: 208 | G5: 26 | H5: TS-C002-2610 | I5: =IF($D5="","",IFERROR(INDEX(Workers!$B$5:$B$2004,MATCH($D5,Workers!$A$5:$A$2004,0)),"NOT FOUND")) -> Marlon Khan | J5: =IF($D5="","",IFERROR(INDEX(Workers!$C$5:$C$2004,MATCH($D5,Workers!$A$5:$A$2004,0)),"")) -> Own | K5: =IF($D5="","",IFERROR(IF(INDEX(Workers!$D$5:$D$2004,MATCH($D5,Workers!$A$5:$A$2004,0))=0,"",INDEX(Workers!$D$5:$D$2004,MATCH($D5,Workers!$A$5:$A$2004,0))),"")) | L5: =IF($D5="","",IFERROR(INDEX(Workers!$E$5:$E$2004,MATCH($D5,Workers!$A$5:$A$2004,0)),"")) -> Steel Fixer | M5: =IF($D5="","",IFERROR(INDEX(ClientRates!$D$5:$D$500,MATCH($B5&"|"&$L5,ClientRates!$A$5:$A$500,0)),0)) -> 25.3 | N5: =IF($D5="","",IFERROR(INDEX(ClientRates!$E$5:$E$500,MATCH($B5&"|"&$L5,ClientRates!$A$5:$A$500,0)),0)) -> 31.62 | O5: =IF($D5="","",F5*M5+G5*N5) -> 6084.52 | P5: =IF(OR($D5="",$J5<>"Supplier"),"",IFERROR(INDEX(SupplierRates!$D$5:$D$500,MATCH($K5&"|"&$L5,SupplierRates!$A$5:$A$500,0)),0)) | Q5: =IF(OR($D5="",$J5<>"Supplier"),"",IFERROR(INDEX(SupplierRates!$E$5:$E$500,MATCH($K5&"|"&$L5,SupplierRates!$A$5:$A$500,0)),0)) | R5: =IF(OR($D5="",$J5<>"Supplier"),0,F5*P5+G5*Q5) -> 0 | S5: =IF(OR($D5="",$J5<>"Own"),0,IFERROR((F5+G5*Settings!$B$13)*INDEX(Workers!$V$5:$V$2004,MATCH($D5,Workers!$A$5:$A$2004,0)),0)) -> 2081.25 | T5: =IF($D5="","",O5-R5-S5) -> 4003.27
A6: 46296 | B6: C001 | C6: Villa Project - Mirdif | D6: W0002 | E6: 25 | F6: 200 | G6: 26 | H6: TS-C001-2610 | I6: =IF($D6="","",IFERROR(INDEX(Workers!$B$5:$B$2004,MATCH($D6,Workers!$A$5:$A$2004,0)),"NOT FOUND")) -> Rohan Ali | J6: =IF($D6="","",IFERROR(INDEX(Workers!$C$5:$C$2004,MATCH($D6,Workers!$A$5:$A$2004,0)),"")) -> Own | K6: =IF($D6="","",IFERROR(IF(INDEX(Workers!$D$5:$D$2004,MATCH($D6,Workers!$A$5:$A$2004,0))=0,"",INDEX(Workers!$D$5:$D$2004,MATCH($D6,Workers!$A$5:$A$2004,0))),"")) | L6: =IF($D6="","",IFERROR(INDEX(Workers!$E$5:$E$2004,MATCH($D6,Workers!$A$5:$A$2004,0)),"")) -> Helper | M6: =IF($D6="","",IFERROR(INDEX(ClientRates!$D$5:$D$500,MATCH($B6&"|"&$L6,ClientRates!$A$5:$A$500,0)),0)) -> 16 | N6: =IF($D6="","",IFERROR(INDEX(ClientRates!$E$5:$E$500,MATCH($B6&"|"&$L6,ClientRates!$A$5:$A$500,0)),0)) -> 20 | O6: =IF($D6="","",F6*M6+G6*N6) -> 3720 | P6: =IF(OR($D6="",$J6<>"Supplier"),"",IFERROR(INDEX(SupplierRates!$D$5:$D$500,MATCH($K6&"|"&$L6,SupplierRates!$A$5:$A$500,0)),0)) | Q6: =IF(OR($D6="",$J6<>"Supplier"),"",IFERROR(INDEX(SupplierRates!$E$5:$E$500,MATCH($K6&"|"&$L6,SupplierRates!$A$5:$A$500,0)),0)) | R6: =IF(OR($D6="",$J6<>"Supplier"),0,F6*P6+G6*Q6) -> 0 | S6: =IF(OR($D6="",$J6<>"Own"),0,IFERROR((F6+G6*Settings!$B$13)*INDEX(Workers!$V$5:$V$2004,MATCH($D6,Workers!$A$5:$A$2004,0)),0)) -> 1900.2404 | T6: =IF($D6="","",O6-R6-S6) -> 1819.7596
A7: 46296 | B7: C001 | C7: Villa Project - Mirdif | D7: W0003 | E7: 25 | F7: 200 | G7: 26 | H7: TS-C001-2610 | I7: =IF($D7="","",IFERROR(INDEX(Workers!$B$5:$B$2004,MATCH($D7,Workers!$A$5:$A$2004,0)),"NOT FOUND")) -> Ronel Thapa | J7: =IF($D7="","",IFERROR(INDEX(Workers!$C$5:$C$2004,MATCH($D7,Workers!$A$5:$A$2004,0)),"")) -> Own | K7: =IF($D7="","",IFERROR(IF(INDEX(Workers!$D$5:$D$2004,MATCH($D7,Workers!$A$5:$A$2004,0))=0,"",INDEX(Workers!$D$5:$D$2004,MATCH($D7,Workers!$A$5:$A$2004,0))),"")) | L7: =IF($D7="","",IFERROR(INDEX(Workers!$E$5:$E$2004,MATCH($D7,Workers!$A$5:$A$2004,0)),"")) -> Mason | M7: =IF($D7="","",IFERROR(INDEX(ClientRates!$D$5:$D$500,MATCH($B7&"|"&$L7,ClientRates!$A$5:$A$500,0)),0)) -> 22 | N7: =IF($D7="","",IFERROR(INDEX(ClientRates!$E$5:$E$500,MATCH($B7&"|"&$L7,ClientRates!$A$5:$A$500,0)),0)) -> 27.5 | O7: =IF($D7="","",F7*M7+G7*N7) -> 5115 | P7: =IF(OR($D7="",$J7<>"Supplier"),"",IFERROR(INDEX(SupplierRates!$D$5:$D$500,MATCH($K7&"|"&$L7,SupplierRates!$A$5:$A$500,0)),0)) | Q7: =IF(OR($D7="",$J7<>"Supplier"),"",IFERROR(INDEX(SupplierRates!$E$5:$E$500,MATCH($K7&"|"&$L7,SupplierRates!$A$5:$A$500,0)),0)) | R7: =IF(OR($D7="",$J7<>"Supplier"),0,F7*P7+G7*Q7) -> 0 | S7: =IF(OR($D7="",$J7<>"Own"),0,IFERROR((F7+G7*Settings!$B$13)*INDEX(Workers!$V$5:$V$2004,MATCH($D7,Workers!$A$5:$A$2004,0)),0)) -> 2235.5769 | T7: =IF($D7="","",O7-R7-S7) -> 2879.4231
A8: 46296 | B8: C002 | C8: Khalifa City FM | D8: W0004 | E8: 24 | F8: 192 | G8: 16 | H8: TS-C002-2610 | I8: =IF($D8="","",IFERROR(INDEX(Workers!$B$5:$B$2004,MATCH($D8,Workers!$A$5:$A$2004,0)),"NOT FOUND")) -> Tariq Varghese | J8: =IF($D8="","",IFERROR(INDEX(Workers!$C$5:$C$2004,MATCH($D8,Workers!$A$5:$A$2004,0)),"")) -> Own | K8: =IF($D8="","",IFERROR(IF(INDEX(Workers!$D$5:$D$2004,MATCH($D8,Workers!$A$5:$A$2004,0))=0,"",INDEX(Workers!$D$5:$D$2004,MATCH($D8,Workers!$A$5:$A$2004,0))),"")) | L8: =IF($D8="","",IFERROR(INDEX(Workers!$E$5:$E$2004,MATCH($D8,Workers!$A$5:$A$2004,0)),"")) -> Helper | M8: =IF($D8="","",IFERROR(INDEX(ClientRates!$D$5:$D$500,MATCH($B8&"|"&$L8,ClientRates!$A$5:$A$500,0)),0)) -> 17.6 | N8: =IF($D8="","",IFERROR(INDEX(ClientRates!$E$5:$E$500,MATCH($B8&"|"&$L8,ClientRates!$A$5:$A$500,0)),0)) -> 22 | O8: =IF($D8="","",F8*M8+G8*N8) -> 3731.2 | P8: =IF(OR($D8="",$J8<>"Supplier"),"",IFERROR(INDEX(SupplierRates!$D$5:$D$500,MATCH($K8&"|"&$L8,SupplierRates!$A$5:$A$500,0)),0)) | Q8: =IF(OR($D8="",$J8<>"Supplier"),"",IFERROR(INDEX(SupplierRates!$E$5:$E$500,MATCH($K8&"|"&$L8,SupplierRates!$A$5:$A$500,0)),0)) | R8: =IF(OR($D8="",$J8<>"Supplier"),0,F8*P8+G8*Q8) -> 0 | S8: =IF(OR($D8="",$J8<>"Own"),0,IFERROR((F8+G8*Settings!$B$13)*INDEX(Workers!$V$5:$V$2004,MATCH($D8,Workers!$A$5:$A$2004,0)),0)) -> 2344.2308 | T8: =IF($D8="","",O8-R8-S8) -> 1386.9692
A9: 46296 | B9: C001 | C9: Tower A - JVC | D9: W0005 | E9: 26 | F9: 208 | G9: 26 | H9: TS-C001-2610 | I9: =IF($D9="","",IFERROR(INDEX(Workers!$B$5:$B$2004,MATCH($D9,Workers!$A$5:$A$2004,0)),"NOT FOUND")) -> Joseph Ahmed | J9: =IF($D9="","",IFERROR(INDEX(Workers!$C$5:$C$2004,MATCH($D9,Workers!$A$5:$A$2004,0)),"")) -> Own | K9: =IF($D9="","",IFERROR(IF(INDEX(Workers!$D$5:$D$2004,MATCH($D9,Workers!$A$5:$A$2004,0))=0,"",INDEX(Workers!$D$5:$D$2004,MATCH($D9,Workers!$A$5:$A$2004,0))),"")) | L9: =IF($D9="","",IFERROR(INDEX(Workers!$E$5:$E$2004,MATCH($D9,Workers!$A$5:$A$2004,0)),"")) -> Helper | M9: =IF($D9="","",IFERROR(INDEX(ClientRates!$D$5:$D$500,MATCH($B9&"|"&$L9,ClientRates!$A$5:$A$500,0)),0)) -> 16 | N9: =IF($D9="","",IFERROR(INDEX(ClientRates!$E$5:$E$500,MATCH($B9&"|"&$L9,ClientRates!$A$5:$A$500,0)),0)) -> 20 | O9: =IF($D9="","",F9*M9+G9*N9) -> 3848 | P9: =IF(OR($D9="",$J9<>"Supplier"),"",IFERROR(INDEX(SupplierRates!$D$5:$D$500,MATCH($K9&"|"&$L9,SupplierRates!$A$5:$A$500,0)),0)) | Q9: =IF(OR($D9="",$J9<>"Supplier"),"",IFERROR(INDEX(SupplierRates!$E$5:$E$500,MATCH($K9&"|"&$L9,SupplierRates!$A$5:$A$500,0)),0)) | R9: =IF(OR($D9="",$J9<>"Supplier"),0,F9*P9+G9*Q9) -> 0 | S9: =IF(OR($D9="",$J9<>"Own"),0,IFERROR((F9+G9*Settings!$B$13)*INDEX(Workers!$V$5:$V$2004,MATCH($D9,Workers!$A$5:$A$2004,0)),0)) -> 1850 | T9: =IF($D9="","",O9-R9-S9) -> 1998
A10: 46296 | B10: C003 | C10: Warehouse - Sajja | D10: W0006 | E10: 22 | F10: 176 | G10: 0 | H10: TS-C003-2610 | I10: =IF($D10="","",IFERROR(INDEX(Workers!$B$5:$B$2004,MATCH($D10,Workers!$A$5:$A$2004,0)),"NOT FOUND")) -> Dinesh Shrestha | J10: =IF($D10="","",IFERROR(INDEX(Workers!$C$5:$C$2004,MATCH($D10,Workers!$A$5:$A$2004,0)),"")) -> Own | K10: =IF($D10="","",IFERROR(IF(INDEX(Workers!$D$5:$D$2004,MATCH($D10,Workers!$A$5:$A$2004,0))=0,"",INDEX(Workers!$D$5:$D$2004,MATCH($D10,Workers!$A$5:$A$2004,0))),"")) | L10: =IF($D10="","",IFERROR(INDEX(Workers!$E$5:$E$2004,MATCH($D10,Workers!$A$5:$A$2004,0)),"")) -> Driver | M10: =IF($D10="","",IFERROR(INDEX(ClientRates!$D$5:$D$500,MATCH($B10&"|"&$L10,ClientRates!$A$5:$A$500,0)),0)) -> 22.8 | N10: =IF($D10="","",IFERROR(INDEX(ClientRates!$E$5:$E$500,MATCH($B10&"|"&$L10,ClientRates!$A$5:$A$500,0)),0)) -> 28.5 | O10: =IF($D10="","",F10*M10+G10*N10) -> 4012.8 | P10: =IF(OR($D10="",$J10<>"Supplier"),"",IFERROR(INDEX(SupplierRates!$D$5:$D$500,MATCH($K10&"|"&$L10,SupplierRates!$A$5:$A$500,0)),0)) | Q10: =IF(OR($D10="",$J10<>"Supplier"),"",IFERROR(INDEX(SupplierRates!$E$5:$E$500,MATCH($K10&"|"&$L10,SupplierRates!$A$5:$A$500,0)),0)) | R10: =IF(OR($D10="",$J10<>"Supplier"),0,F10*P10+G10*Q10) -> 0 | S10: =IF(OR($D10="",$J10<>"Own"),0,IFERROR((F10+G10*Settings!$B$13)*INDEX(Workers!$V$5:$V$2004,MATCH($D10,Workers!$A$5:$A$2004,0)),0)) -> 1269.2308 | T10: =IF($D10="","",O10-R10-S10) -> 2743.5692
A11: 46296 | B11: C001 | C11: Tower A - JVC | D11: W0007 | E11: 24 | F11: 192 | G11: 26 | H11: TS-C001-2610 | I11: =IF($D11="","",IFERROR(INDEX(Workers!$B$5:$B$2004,MATCH($D11,Workers!$A$5:$A$2004,0)),"NOT FOUND")) -> Rahul Kumar | J11: =IF($D11="","",IFERROR(INDEX(Workers!$C$5:$C$2004,MATCH($D11,Workers!$A$5:$A$2004,0)),"")) -> Own | K11: =IF($D11="","",IFERROR(IF(INDEX(Workers!$D$5:$D$2004,MATCH($D11,Workers!$A$5:$A$2004,0))=0,"",INDEX(Workers!$D$5:$D$2004,MATCH($D11,Workers!$A$5:$A$2004,0))),"")) | L11: =IF($D11="","",IFERROR(INDEX(Workers!$E$5:$E$2004,MATCH($D11,Workers!$A$5:$A$2004,0)),"")) -> Mason | M11: =IF($D11="","",IFERROR(INDEX(ClientRates!$D$5:$D$500,MATCH($B11&"|"&$L11,ClientRates!$A$5:$A$500,0)),0)) -> 22 | N11: =IF($D11="","",IFERROR(INDEX(ClientRates!$E$5:$E$500,MATCH($B11&"|"&$L11,ClientRates!$A$5:$A$500,0)),0)) -> 27.5 | O11: =IF($D11="","",F11*M11+G11*N11) -> 4939 | P11: =IF(OR($D11="",$J11<>"Supplier"),"",IFERROR(INDEX(SupplierRates!$D$5:$D$500,MATCH($K11&"|"&$L11,SupplierRates!$A$5:$A$500,0)),0)) | Q11: =IF(OR($D11="",$J11<>"Supplier"),"",IFERROR(INDEX(SupplierRates!$E$5:$E$500,MATCH($K11&"|"&$L11,SupplierRates!$A$5:$A$500,0)),0)) | R11: =IF(OR($D11="",$J11<>"Supplier"),0,F11*P11+G11*Q11) -> 0 | S11: =IF(OR($D11="",$J11<>"Own"),0,IFERROR((F11+G11*Settings!$B$13)*INDEX(Workers!$V$5:$V$2004,MATCH($D11,Workers!$A$5:$A$2004,0)),0)) -> 2590.3846 | T11: =IF($D11="","",O11-R11-S11) -> 2348.6154
A12: 46296 | B12: C002 | C12: Khalifa City FM | D12: W0008 | E12: 26 | F12: 208 | G12: 20 | H12: TS-C002-2610 | I12: =IF($D12="","",IFERROR(INDEX(Workers!$B$5:$B$2004,MATCH($D12,Workers!$A$5:$A$2004,0)),"NOT FOUND")) -> Mohan Nair | J12: =IF($D12="","",IFERROR(INDEX(Workers!$C$5:$C$2004,MATCH($D12,Workers!$A$5:$A$2004,0)),"")) -> Own | K12: =IF($D12="","",IFERROR(IF(INDEX(Workers!$D$5:$D$2004,MATCH($D12,Workers!$A$5:$A$2004,0))=0,"",INDEX(Workers!$D$5:$D$2004,MATCH($D12,Workers!$A$5:$A$2004,0))),"")) | L12: =IF($D12="","",IFERROR(INDEX(Workers!$E$5:$E$2004,MATCH($D12,Workers!$A$5:$A$2004,0)),"")) -> Helper | M12: =IF($D12="","",IFERROR(INDEX(ClientRates!$D$5:$D$500,MATCH($B12&"|"&$L12,ClientRates!$A$5:$A$500,0)),0)) -> 17.6 | N12: =IF($D12="","",IFERROR(INDEX(ClientRates!$E$5:$E$500,MATCH($B12&"|"&$L12,ClientRates!$A$5:$A$500,0)),0)) -> 22 | O12: =IF($D12="","",F12*M12+G12*N12) -> 4100.8 | P12: =IF(OR($D12="",$J12<>"Supplier"),"",IFERROR(INDEX(SupplierRates!$D$5:$D$500,MATCH($K12&"|"&$L12,SupplierRates!$A$5:$A$500,0)),0)) | Q12: =IF(OR($D12="",$J12<>"Supplier"),"",IFERROR(INDEX(SupplierRates!$E$5:$E$500,MATCH($K12&"|"&$L12,SupplierRates!$A$5:$A$500,0)),0)) | R12: =IF(OR($D12="",$J12<>"Supplier"),0,F12*P12+G12*Q12) -> 0 | S12: =IF(OR($D12="",$J12<>"Own"),0,IFERROR((F12+G12*Settings!$B$13)*INDEX(Workers!$V$5:$V$2004,MATCH($D12,Workers!$A$5:$A$2004,0)),0)) -> 2097 | T12: =IF($D12="","",O12-R12-S12) -> 2003.8
A13: 46296 | B13: C002 | C13: Khalifa City FM | D13: W0009 | E13: 25 | F13: 200 | G13: 20 | H13: TS-C002-2610 | I13: =IF($D13="","",IFERROR(INDEX(Workers!$B$5:$B$2004,MATCH($D13,Workers!$A$5:$A$2004,0)),"NOT FOUND")) -> Anwar Shrestha | J13: =IF($D13="","",IFERROR(INDEX(Workers!$C$5:$C$2004,MATCH($D13,Workers!$A$5:$A$2004,0)),"")) -> Own | K13: =IF($D13="","",IFERROR(IF(INDEX(Workers!$D$5:$D$2004,MATCH($D13,Workers!$A$5:$A$2004,0))=0,"",INDEX(Workers!$D$5:$D$2004,MATCH($D13,Workers!$A$5:$A$2004,0))),"")) | L13: =IF($D13="","",IFERROR(INDEX(Workers!$E$5:$E$2004,MATCH($D13,Workers!$A$5:$A$2004,0)),"")) -> Electrician | M13: =IF($D13="","",IFERROR(INDEX(ClientRates!$D$5:$D$500,MATCH($B13&"|"&$L13,ClientRates!$A$5:$A$500,0)),0)) -> 28.6 | N13: =IF($D13="","",IFERROR(INDEX(ClientRates!$E$5:$E$500,MATCH($B13&"|"&$L13,ClientRates!$A$5:$A$500,0)),0)) -> 35.75 | O13: =IF($D13="","",F13*M13+G13*N13) -> 6435 | P13: =IF(OR($D13="",$J13<>"Supplier"),"",IFERROR(INDEX(SupplierRates!$D$5:$D$500,MATCH($K13&"|"&$L13,SupplierRates!$A$5:$A$500,0)),0)) | Q13: =IF(OR($D13="",$J13<>"Supplier"),"",IFERROR(INDEX(SupplierRates!$E$5:$E$500,MATCH($K13&"|"&$L13,SupplierRates!$A$5:$A$500,0)),0)) | R13: =IF(OR($D13="",$J13<>"Supplier"),0,F13*P13+G13*Q13) -> 0 | S13: =IF(OR($D13="",$J13<>"Own"),0,IFERROR((F13+G13*Settings!$B$13)*INDEX(Workers!$V$5:$V$2004,MATCH($D13,Workers!$A$5:$A$2004,0)),0)) -> 3245.1923 | T13: =IF($D13="","",O13-R13-S13) -> 3189.8077
A14: 46296 | B14: C003 | C14: Warehouse - Sajja | D14: W0010 | E14: 25 | F14: 200 | G14: 0 | H14: TS-C003-2610 | I14: =IF($D14="","",IFERROR(INDEX(Workers!$B$5:$B$2004,MATCH($D14,Workers!$A$5:$A$2004,0)),"NOT FOUND")) -> Hari Nair | J14: =IF($D14="","",IFERROR(INDEX(Workers!$C$5:$C$2004,MATCH($D14,Workers!$A$5:$A$2004,0)),"")) -> Own | K14: =IF($D14="","",IFERROR(IF(INDEX(Workers!$D$5:$D$2004,MATCH($D14,Workers!$A$5:$A$2004,0))=0,"",INDEX(Workers!$D$5:$D$2004,MATCH($D14,Workers!$A$5:$A$2004,0))),"")) | L14: =IF($D14="","",IFERROR(INDEX(Workers!$E$5:$E$2004,MATCH($D14,Workers!$A$5:$A$2004,0)),"")) -> Helper | M14: =IF($D14="","",IFERROR(INDEX(ClientRates!$D$5:$D$500,MATCH($B14&"|"&$L14,ClientRates!$A$5:$A$500,0)),0)) -> 15.2 | N14: =IF($D14="","",IFERROR(INDEX(ClientRates!$E$5:$E$500,MATCH($B14&"|"&$L14,ClientRates!$A$5:$A$500,0)),0)) -> 19 | O14: =IF($D14="","",F14*M14+G14*N14) -> 3040 | P14: =IF(OR($D14="",$J14<>"Supplier"),"",IFERROR(INDEX(SupplierRates!$D$5:$D$500,MATCH($K14&"|"&$L14,SupplierRates!$A$5:$A$500,0)),0)) | Q14: =IF(OR($D14="",$J14<>"Supplier"),"",IFERROR(INDEX(SupplierRates!$E$5:$E$500,MATCH($K14&"|"&$L14,SupplierRates!$A$5:$A$500,0)),0)) | R14: =IF(OR($D14="",$J14<>"Supplier"),0,F14*P14+G14*Q14) -> 0 | S14: =IF(OR($D14="",$J14<>"Own"),0,IFERROR((F14+G14*Settings!$B$13)*INDEX(Workers!$V$5:$V$2004,MATCH($D14,Workers!$A$5:$A$2004,0)),0)) -> 2403.8462 | T14: =IF($D14="","",O14-R14-S14) -> 636.15385
A15: 46296 | B15: C002 | C15: Yas Mall FM | D15: W0011 | E15: 25 | F15: 200 | G15: 26 | H15: TS-C002-2610 | I15: =IF($D15="","",IFERROR(INDEX(Workers!$B$5:$B$2004,MATCH($D15,Workers!$A$5:$A$2004,0)),"NOT FOUND")) -> Dinesh Menon | J15: =IF($D15="","",IFERROR(INDEX(Workers!$C$5:$C$2004,MATCH($D15,Workers!$A$5:$A$2004,0)),"")) -> Own | K15: =IF($D15="","",IFERROR(IF(INDEX(Workers!$D$5:$D$2004,MATCH($D15,Workers!$A$5:$A$2004,0))=0,"",INDEX(Workers!$D$5:$D$2004,MATCH($D15,Workers!$A$5:$A$2004,0))),"")) | L15: =IF($D15="","",IFERROR(INDEX(Workers!$E$5:$E$2004,MATCH($D15,Workers!$A$5:$A$2004,0)),"")) -> Driver | M15: =IF($D15="","",IFERROR(INDEX(ClientRates!$D$5:$D$500,MATCH($B15&"|"&$L15,ClientRates!$A$5:$A$500,0)),0)) -> 26.4 | N15: =IF($D15="","",IFERROR(INDEX(ClientRates!$E$5:$E$500,MATCH($B15&"|"&$L15,ClientRates!$A$5:$A$500,0)),0)) -> 33 | O15: =IF($D15="","",F15*M15+G15*N15) -> 6138 | P15: =IF(OR($D15="",$J15<>"Supplier"),"",IFERROR(INDEX(SupplierRates!$D$5:$D$500,MATCH($K15&"|"&$L15,SupplierRates!$A$5:$A$500,0)),0)) | Q15: =IF(OR($D15="",$J15<>"Supplier"),"",IFERROR(INDEX(SupplierRates!$E$5:$E$500,MATCH($K15&"|"&$L15,SupplierRates!$A$5:$A$500,0)),0)) | R15: =IF(OR($D15="",$J15<>"Supplier"),0,F15*P15+G15*Q15) -> 0 | S15: =IF(OR($D15="",$J15<>"Own"),0,IFERROR((F15+G15*Settings!$B$13)*INDEX(Workers!$V$5:$V$2004,MATCH($D15,Workers!$A$5:$A$2004,0)),0)) -> 1676.6827 | T15: =IF($D15="","",O15-R15-S15) -> 4461.3173
A16: 46296 | B16: C003 | C16: Warehouse - Sajja | D16: W0012 | E16: 22 | F16: 176 | G16: 16 | H16: TS-C003-2610 | I16: =IF($D16="","",IFERROR(INDEX(Workers!$B$5:$B$2004,MATCH($D16,Workers!$A$5:$A$2004,0)),"NOT FOUND")) -> Imran Ali | J16: =IF($D16="","",IFERROR(INDEX(Workers!$C$5:$C$2004,MATCH($D16,Workers!$A$5:$A$2004,0)),"")) -> Own | K16: =IF($D16="","",IFERROR(IF(INDEX(Workers!$D$5:$D$2004,MATCH($D16,Workers!$A$5:$A$2004,0))=0,"",INDEX(Workers!$D$5:$D$2004,MATCH($D16,Workers!$A$5:$A$2004,0))),"")) | L16: =IF($D16="","",IFERROR(INDEX(Workers!$E$5:$E$2004,MATCH($D16,Workers!$A$5:$A$2004,0)),"")) -> Helper | M16: =IF($D16="","",IFERROR(INDEX(ClientRates!$D$5:$D$500,MATCH($B16&"|"&$L16,ClientRates!$A$5:$A$500,0)),0)) -> 15.2 | N16: =IF($D16="","",IFERROR(INDEX(ClientRates!$E$5:$E$500,MATCH($B16&"|"&$L16,ClientRates!$A$5:$A$500,0)),0)) -> 19 | O16: =IF($D16="","",F16*M16+G16*N16) -> 2979.2 | P16: =IF(OR($D16="",$J16<>"Supplier"),"",IFERROR(INDEX(SupplierRates!$D$5:$D$500,MATCH($K16&"|"&$L16,SupplierRates!$A$5:$A$500,0)),0)) | Q16: =IF(OR($D16="",$J16<>"Supplier"),"",IFERROR(INDEX(SupplierRates!$E$5:$E$500,MATCH($K16&"|"&$L16,SupplierRates!$A$5:$A$500,0)),0)) | R16: =IF(OR($D16="",$J16<>"Supplier"),0,F16*P16+G16*Q16) -> 0 | S16: =IF(OR($D16="",$J16<>"Own"),0,IFERROR((F16+G16*Settings!$B$13)*INDEX(Workers!$V$5:$V$2004,MATCH($D16,Workers!$A$5:$A$2004,0)),0)) -> 2167.3077 | T16: =IF($D16="","",O16-R16-S16) -> 811.89231
... A90: 46266 | B90: C001 | C90: Tower A - JVC | D90: W0012 | E90: 25 | F90: 200 | G90: 12 | H90: TS-C001-2609 | I90: =IF($D90="","",IFERROR(INDEX(Workers!$B$5:$B$2004,MATCH($D90,Workers!$A$5:$A$2004,0)),"NOT FOUND")) -> Imran Ali | J90: =IF($D90="","",IFERROR(INDEX(Workers!$C$5:$C$2004,MATCH($D90,Workers!$A$5:$A$2004,0)),"")) -> Own | K90: =IF($D90="","",IFERROR(IF(INDEX(Workers!$D$5:$D$2004,MATCH($D90,Workers!$A$5:$A$2004,0))=0,"",INDEX(Workers!$D$5:$D$2004,MATCH($D90,Workers!$A$5:$A$2004,0))),"")) | L90: =IF($D90="","",IFERROR(INDEX(Workers!$E$5:$E$2004,MATCH($D90,Workers!$A$5:$A$2004,0)),"")) -> Helper | M90: =IF($D90="","",IFERROR(INDEX(ClientRates!$D$5:$D$500,MATCH($B90&"|"&$L90,ClientRates!$A$5:$A$500,0)),0)) -> 16 | N90: =IF($D90="","",IFERROR(INDEX(ClientRates!$E$5:$E$500,MATCH($B90&"|"&$L90,ClientRates!$A$5:$A$500,0)),0)) -> 20 | O90: =IF($D90="","",F90*M90+G90*N90) -> 3440 | P90: =IF(OR($D90="",$J90<>"Supplier"),"",IFERROR(INDEX(SupplierRates!$D$5:$D$500,MATCH($K90&"|"&$L90,SupplierRates!$A$5:$A$500,0)),0)) | Q90: =IF(OR($D90="",$J90<>"Supplier"),"",IFERROR(INDEX(SupplierRates!$E$5:$E$500,MATCH($K90&"|"&$L90,SupplierRates!$A$5:$A$500,0)),0)) | R90: =IF(OR($D90="",$J90<>"Supplier"),0,F90*P90+G90*Q90) -> 0 | S90: =IF(OR($D90="",$J90<>"Own"),0,IFERROR((F90+G90*Settings!$B$13)*INDEX(Workers!$V$5:$V$2004,MATCH($D90,Workers!$A$5:$A$2004,0)),0)) -> 2377.4038 | T90: =IF($D90="","",O90-R90-S90) -> 1062.5962
I91: =IF($D91="","",IFERROR(INDEX(Workers!$B$5:$B$2004,MATCH($D91,Workers!$A$5:$A$2004,0)),"NOT FOUND")) | J91: =IF($D91="","",IFERROR(INDEX(Workers!$C$5:$C$2004,MATCH($D91,Workers!$A$5:$A$2004,0)),"")) | K91: =IF($D91="","",IFERROR(IF(INDEX(Workers!$D$5:$D$2004,MATCH($D91,Workers!$A$5:$A$2004,0))=0,"",INDEX(Workers!$D$5:$D$2004,MATCH($D91,Workers!$A$5:$A$2004,0))),"")) | L91: =IF($D91="","",IFERROR(INDEX(Workers!$E$5:$E$2004,MATCH($D91,Workers!$A$5:$A$2004,0)),"")) | M91: =IF($D91="","",IFERROR(INDEX(ClientRates!$D$5:$D$500,MATCH($B91&"|"&$L91,ClientRates!$A$5:$A$500,0)),0)) | N91: =IF($D91="","",IFERROR(INDEX(ClientRates!$E$5:$E$500,MATCH($B91&"|"&$L91,ClientRates!$A$5:$A$500,0)),0)) | O91: =IF($D91="","",F91*M91+G91*N91) | P91: =IF(OR($D91="",$J91<>"Supplier"),"",IFERROR(INDEX(SupplierRates!$D$5:$D$500,MATCH($K91&"|"&$L91,SupplierRates!$A$5:$A$500,0)),0)) | Q91: =IF(OR($D91="",$J91<>"Supplier"),"",IFERROR(INDEX(SupplierRates!$E$5:$E$500,MATCH($K91&"|"&$L91,SupplierRates!$A$5:$A$500,0)),0)) | R91: =IF(OR($D91="",$J91<>"Supplier"),0,F91*P91+G91*Q91) -> 0 | S91: =IF(OR($D91="",$J91<>"Own"),0,IFERROR((F91+G91*Settings!$B$13)*INDEX(Workers!$V$5:$V$2004,MATCH($D91,Workers!$A$5:$A$2004,0)),0)) -> 0 | T91: =IF($D91="","",O91-R91-S91)
I92: =IF($D92="","",IFERROR(INDEX(Workers!$B$5:$B$2004,MATCH($D92,Workers!$A$5:$A$2004,0)),"NOT FOUND")) | J92: =IF($D92="","",IFERROR(INDEX(Workers!$C$5:$C$2004,MATCH($D92,Workers!$A$5:$A$2004,0)),"")) | K92: =IF($D92="","",IFERROR(IF(INDEX(Workers!$D$5:$D$2004,MATCH($D92,Workers!$A$5:$A$2004,0))=0,"",INDEX(Workers!$D$5:$D$2004,MATCH($D92,Workers!$A$5:$A$2004,0))),"")) | L92: =IF($D92="","",IFERROR(INDEX(Workers!$E$5:$E$2004,MATCH($D92,Workers!$A$5:$A$2004,0)),"")) | M92: =IF($D92="","",IFERROR(INDEX(ClientRates!$D$5:$D$500,MATCH($B92&"|"&$L92,ClientRates!$A$5:$A$500,0)),0)) | N92: =IF($D92="","",IFERROR(INDEX(ClientRates!$E$5:$E$500,MATCH($B92&"|"&$L92,ClientRates!$A$5:$A$500,0)),0)) | O92: =IF($D92="","",F92*M92+G92*N92) | P92: =IF(OR($D92="",$J92<>"Supplier"),"",IFERROR(INDEX(SupplierRates!$D$5:$D$500,MATCH($K92&"|"&$L92,SupplierRates!$A$5:$A$500,0)),0)) | Q92: =IF(OR($D92="",$J92<>"Supplier"),"",IFERROR(INDEX(SupplierRates!$E$5:$E$500,MATCH($K92&"|"&$L92,SupplierRates!$A$5:$A$500,0)),0)) | R92: =IF(OR($D92="",$J92<>"Supplier"),0,F92*P92+G92*Q92) -> 0 | S92: =IF(OR($D92="",$J92<>"Own"),0,IFERROR((F92+G92*Settings!$B$13)*INDEX(Workers!$V$5:$V$2004,MATCH($D92,Workers!$A$5:$A$2004,0)),0)) -> 0 | T92: =IF($D92="","",O92-R92-S92)
I93: =IF($D93="","",IFERROR(INDEX(Workers!$B$5:$B$2004,MATCH($D93,Workers!$A$5:$A$2004,0)),"NOT FOUND")) | J93: =IF($D93="","",IFERROR(INDEX(Workers!$C$5:$C$2004,MATCH($D93,Workers!$A$5:$A$2004,0)),"")) | K93: =IF($D93="","",IFERROR(IF(INDEX(Workers!$D$5:$D$2004,MATCH($D93,Workers!$A$5:$A$2004,0))=0,"",INDEX(Workers!$D$5:$D$2004,MATCH($D93,Workers!$A$5:$A$2004,0))),"")) | L93: =IF($D93="","",IFERROR(INDEX(Workers!$E$5:$E$2004,MATCH($D93,Workers!$A$5:$A$2004,0)),"")) | M93: =IF($D93="","",IFERROR(INDEX(ClientRates!$D$5:$D$500,MATCH($B93&"|"&$L93,ClientRates!$A$5:$A$500,0)),0)) | N93: =IF($D93="","",IFERROR(INDEX(ClientRates!$E$5:$E$500,MATCH($B93&"|"&$L93,ClientRates!$A$5:$A$500,0)),0)) | O93: =IF($D93="","",F93*M93+G93*N93) | P93: =IF(OR($D93="",$J93<>"Supplier"),"",IFERROR(INDEX(SupplierRates!$D$5:$D$500,MATCH($K93&"|"&$L93,SupplierRates!$A$5:$A$500,0)),0)) | Q93: =IF(OR($D93="",$J93<>"Supplier"),"",IFERROR(INDEX(SupplierRates!$E$5:$E$500,MATCH($K93&"|"&$L93,SupplierRates!$A$5:$A$500,0)),0)) | R93: =IF(OR($D93="",$J93<>"Supplier"),0,F93*P93+G93*Q93) -> 0 | S93: =IF(OR($D93="",$J93<>"Own"),0,IFERROR((F93+G93*Settings!$B$13)*INDEX(Workers!$V$5:$V$2004,MATCH($D93,Workers!$A$5:$A$2004,0)),0)) -> 0 | T93: =IF($D93="","",O93-R93-S93)
I94: =IF($D94="","",IFERROR(INDEX(Workers!$B$5:$B$2004,MATCH($D94,Workers!$A$5:$A$2004,0)),"NOT FOUND")) | J94: =IF($D94="","",IFERROR(INDEX(Workers!$C$5:$C$2004,MATCH($D94,Workers!$A$5:$A$2004,0)),"")) | K94: =IF($D94="","",IFERROR(IF(INDEX(Workers!$D$5:$D$2004,MATCH($D94,Workers!$A$5:$A$2004,0))=0,"",INDEX(Workers!$D$5:$D$2004,MATCH($D94,Workers!$A$5:$A$2004,0))),"")) | L94: =IF($D94="","",IFERROR(INDEX(Workers!$E$5:$E$2004,MATCH($D94,Workers!$A$5:$A$2004,0)),"")) | M94: =IF($D94="","",IFERROR(INDEX(ClientRates!$D$5:$D$500,MATCH($B94&"|"&$L94,ClientRates!$A$5:$A$500,0)),0)) | N94: =IF($D94="","",IFERROR(INDEX(ClientRates!$E$5:$E$500,MATCH($B94&"|"&$L94,ClientRates!$A$5:$A$500,0)),0)) | O94: =IF($D94="","",F94*M94+G94*N94) | P94: =IF(OR($D94="",$J94<>"Supplier"),"",IFERROR(INDEX(SupplierRates!$D$5:$D$500,MATCH($K94&"|"&$L94,SupplierRates!$A$5:$A$500,0)),0)) | Q94: =IF(OR($D94="",$J94<>"Supplier"),"",IFERROR(INDEX(SupplierRates!$E$5:$E$500,MATCH($K94&"|"&$L94,SupplierRates!$A$5:$A$500,0)),0)) | R94: =IF(OR($D94="",$J94<>"Supplier"),0,F94*P94+G94*Q94) -> 0 | S94: =IF(OR($D94="",$J94<>"Own"),0,IFERROR((F94+G94*Settings!$B$13)*INDEX(Workers!$V$5:$V$2004,MATCH($D94,Workers!$A$5:$A$2004,0)),0)) -> 0 | T94: =IF($D94="","",O94-R94-S94)
I95: =IF($D95="","",IFERROR(INDEX(Workers!$B$5:$B$2004,MATCH($D95,Workers!$A$5:$A$2004,0)),"NOT FOUND")) | J95: =IF($D95="","",IFERROR(INDEX(Workers!$C$5:$C$2004,MATCH($D95,Workers!$A$5:$A$2004,0)),"")) | K95: =IF($D95="","",IFERROR(IF(INDEX(Workers!$D$5:$D$2004,MATCH($D95,Workers!$A$5:$A$2004,0))=0,"",INDEX(Workers!$D$5:$D$2004,MATCH($D95,Workers!$A$5:$A$2004,0))),"")) | L95: =IF($D95="","",IFERROR(INDEX(Workers!$E$5:$E$2004,MATCH($D95,Workers!$A$5:$A$2004,0)),"")) | M95: =IF($D95="","",IFERROR(INDEX(ClientRates!$D$5:$D$500,MATCH($B95&"|"&$L95,ClientRates!$A$5:$A$500,0)),0)) | N95: =IF($D95="","",IFERROR(INDEX(ClientRates!$E$5:$E$500,MATCH($B95&"|"&$L95,ClientRates!$A$5:$A$500,0)),0)) | O95: =IF($D95="","",F95*M95+G95*N95) | P95: =IF(OR($D95="",$J95<>"Supplier"),"",IFERROR(INDEX(SupplierRates!$D$5:$D$500,MATCH($K95&"|"&$L95,SupplierRates!$A$5:$A$500,0)),0)) | Q95: =IF(OR($D95="",$J95<>"Supplier"),"",IFERROR(INDEX(SupplierRates!$E$5:$E$500,MATCH($K95&"|"&$L95,SupplierRates!$A$5:$A$500,0)),0)) | R95: =IF(OR($D95="",$J95<>"Supplier"),0,F95*P95+G95*Q95) -> 0 | S95: =IF(OR($D95="",$J95<>"Own"),0,IFERROR((F95+G95*Settings!$B$13)*INDEX(Workers!$V$5:$V$2004,MATCH($D95,Workers!$A$5:$A$2004,0)),0)) -> 0 | T95: =IF($D95="","",O95-R95-S95)
I96: =IF($D96="","",IFERROR(INDEX(Workers!$B$5:$B$2004,MATCH($D96,Workers!$A$5:$A$2004,0)),"NOT FOUND")) | J96: =IF($D96="","",IFERROR(INDEX(Workers!$C$5:$C$2004,MATCH($D96,Workers!$A$5:$A$2004,0)),"")) | K96: =IF($D96="","",IFERROR(IF(INDEX(Workers!$D$5:$D$2004,MATCH($D96,Workers!$A$5:$A$2004,0))=0,"",INDEX(Workers!$D$5:$D$2004,MATCH($D96,Workers!$A$5:$A$2004,0))),"")) | L96: =IF($D96="","",IFERROR(INDEX(Workers!$E$5:$E$2004,MATCH($D96,Workers!$A$5:$A$2004,0)),"")) | M96: =IF($D96="","",IFERROR(INDEX(ClientRates!$D$5:$D$500,MATCH($B96&"|"&$L96,ClientRates!$A$5:$A$500,0)),0)) | N96: =IF($D96="","",IFERROR(INDEX(ClientRates!$E$5:$E$500,MATCH($B96&"|"&$L96,ClientRates!$A$5:$A$500,0)),0)) | O96: =IF($D96="","",F96*M96+G96*N96) | P96: =IF(OR($D96="",$J96<>"Supplier"),"",IFERROR(INDEX(SupplierRates!$D$5:$D$500,MATCH($K96&"|"&$L96,SupplierRates!$A$5:$A$500,0)),0)) | Q96: =IF(OR($D96="",$J96<>"Supplier"),"",IFERROR(INDEX(SupplierRates!$E$5:$E$500,MATCH($K96&"|"&$L96,SupplierRates!$A$5:$A$500,0)),0)) | R96: =IF(OR($D96="",$J96<>"Supplier"),0,F96*P96+G96*Q96) -> 0 | S96: =IF(OR($D96="",$J96<>"Own"),0,IFERROR((F96+G96*Settings!$B$13)*INDEX(Workers!$V$5:$V$2004,MATCH($D96,Workers!$A$5:$A$2004,0)),0)) -> 0 | T96: =IF($D96="","",O96-R96-S96)
I97: =IF($D97="","",IFERROR(INDEX(Workers!$B$5:$B$2004,MATCH($D97,Workers!$A$5:$A$2004,0)),"NOT FOUND")) | J97: =IF($D97="","",IFERROR(INDEX(Workers!$C$5:$C$2004,MATCH($D97,Workers!$A$5:$A$2004,0)),"")) | K97: =IF($D97="","",IFERROR(IF(INDEX(Workers!$D$5:$D$2004,MATCH($D97,Workers!$A$5:$A$2004,0))=0,"",INDEX(Workers!$D$5:$D$2004,MATCH($D97,Workers!$A$5:$A$2004,0))),"")) | L97: =IF($D97="","",IFERROR(INDEX(Workers!$E$5:$E$2004,MATCH($D97,Workers!$A$5:$A$2004,0)),"")) | M97: =IF($D97="","",IFERROR(INDEX(ClientRates!$D$5:$D$500,MATCH($B97&"|"&$L97,ClientRates!$A$5:$A$500,0)),0)) | N97: =IF($D97="","",IFERROR(INDEX(ClientRates!$E$5:$E$500,MATCH($B97&"|"&$L97,ClientRates!$A$5:$A$500,0)),0)) | O97: =IF($D97="","",F97*M97+G97*N97) | P97: =IF(OR($D97="",$J97<>"Supplier"),"",IFERROR(INDEX(SupplierRates!$D$5:$D$500,MATCH($K97&"|"&$L97,SupplierRates!$A$5:$A$500,0)),0)) | Q97: =IF(OR($D97="",$J97<>"Supplier"),"",IFERROR(INDEX(SupplierRates!$E$5:$E$500,MATCH($K97&"|"&$L97,SupplierRates!$A$5:$A$500,0)),0)) | R97: =IF(OR($D97="",$J97<>"Supplier"),0,F97*P97+G97*Q97) -> 0 | S97: =IF(OR($D97="",$J97<>"Own"),0,IFERROR((F97+G97*Settings!$B$13)*INDEX(Workers!$V$5:$V$2004,MATCH($D97,Workers!$A$5:$A$2004,0)),0)) -> 0 | T97: =IF($D97="","",O97-R97-S97)
I98: =IF($D98="","",IFERROR(INDEX(Workers!$B$5:$B$2004,MATCH($D98,Workers!$A$5:$A$2004,0)),"NOT FOUND")) | J98: =IF($D98="","",IFERROR(INDEX(Workers!$C$5:$C$2004,MATCH($D98,Workers!$A$5:$A$2004,0)),"")) | K98: =IF($D98="","",IFERROR(IF(INDEX(Workers!$D$5:$D$2004,MATCH($D98,Workers!$A$5:$A$2004,0))=0,"",INDEX(Workers!$D$5:$D$2004,MATCH($D98,Workers!$A$5:$A$2004,0))),"")) | L98: =IF($D98="","",IFERROR(INDEX(Workers!$E$5:$E$2004,MATCH($D98,Workers!$A$5:$A$2004,0)),"")) | M98: =IF($D98="","",IFERROR(INDEX(ClientRates!$D$5:$D$500,MATCH($B98&"|"&$L98,ClientRates!$A$5:$A$500,0)),0)) | N98: =IF($D98="","",IFERROR(INDEX(ClientRates!$E$5:$E$500,MATCH($B98&"|"&$L98,ClientRates!$A$5:$A$500,0)),0)) | O98: =IF($D98="","",F98*M98+G98*N98) | P98: =IF(OR($D98="",$J98<>"Supplier"),"",IFERROR(INDEX(SupplierRates!$D$5:$D$500,MATCH($K98&"|"&$L98,SupplierRates!$A$5:$A$500,0)),0)) | Q98: =IF(OR($D98="",$J98<>"Supplier"),"",IFERROR(INDEX(SupplierRates!$E$5:$E$500,MATCH($K98&"|"&$L98,SupplierRates!$A$5:$A$500,0)),0)) | R98: =IF(OR($D98="",$J98<>"Supplier"),0,F98*P98+G98*Q98) -> 0 | S98: =IF(OR($D98="",$J98<>"Own"),0,IFERROR((F98+G98*Settings!$B$13)*INDEX(Workers!$V$5:$V$2004,MATCH($D98,Workers!$A$5:$A$2004,0)),0)) -> 0 | T98: =IF($D98="","",O98-R98-S98)
I99: =IF($D99="","",IFERROR(INDEX(Workers!$B$5:$B$2004,MATCH($D99,Workers!$A$5:$A$2004,0)),"NOT FOUND")) | J99: =IF($D99="","",IFERROR(INDEX(Workers!$C$5:$C$2004,MATCH($D99,Workers!$A$5:$A$2004,0)),"")) | K99: =IF($D99="","",IFERROR(IF(INDEX(Workers!$D$5:$D$2004,MATCH($D99,Workers!$A$5:$A$2004,0))=0,"",INDEX(Workers!$D$5:$D$2004,MATCH($D99,Workers!$A$5:$A$2004,0))),"")) | L99: =IF($D99="","",IFERROR(INDEX(Workers!$E$5:$E$2004,MATCH($D99,Workers!$A$5:$A$2004,0)),"")) | M99: =IF($D99="","",IFERROR(INDEX(ClientRates!$D$5:$D$500,MATCH($B99&"|"&$L99,ClientRates!$A$5:$A$500,0)),0)) | N99: =IF($D99="","",IFERROR(INDEX(ClientRates!$E$5:$E$500,MATCH($B99&"|"&$L99,ClientRates!$A$5:$A$500,0)),0)) | O99: =IF($D99="","",F99*M99+G99*N99) | P99: =IF(OR($D99="",$J99<>"Supplier"),"",IFERROR(INDEX(SupplierRates!$D$5:$D$500,MATCH($K99&"|"&$L99,SupplierRates!$A$5:$A$500,0)),0)) | Q99: =IF(OR($D99="",$J99<>"Supplier"),"",IFERROR(INDEX(SupplierRates!$E$5:$E$500,MATCH($K99&"|"&$L99,SupplierRates!$A$5:$A$500,0)),0)) | R99: =IF(OR($D99="",$J99<>"Supplier"),0,F99*P99+G99*Q99) -> 0 | S99: =IF(OR($D99="",$J99<>"Own"),0,IFERROR((F99+G99*Settings!$B$13)*INDEX(Workers!$V$5:$V$2004,MATCH($D99,Workers!$A$5:$A$2004,0)),0)) -> 0 | T99: =IF($D99="","",O99-R99-S99)
I100: =IF($D100="","",IFERROR(INDEX(Workers!$B$5:$B$2004,MATCH($D100,Workers!$A$5:$A$2004,0)),"NOT FOUND")) | J100: =IF($D100="","",IFERROR(INDEX(Workers!$C$5:$C$2004,MATCH($D100,Workers!$A$5:$A$2004,0)),"")) | K100: =IF($D100="","",IFERROR(IF(INDEX(Workers!$D$5:$D$2004,MATCH($D100,Workers!$A$5:$A$2004,0))=0,"",INDEX(Workers!$D$5:$D$2004,MATCH($D100,Workers!$A$5:$A$2004,0))),"")) | L100: =IF($D100="","",IFERROR(INDEX(Workers!$E$5:$E$2004,MATCH($D100,Workers!$A$5:$A$2004,0)),"")) | M100: =IF($D100="","",IFERROR(INDEX(ClientRates!$D$5:$D$500,MATCH($B100&"|"&$L100,ClientRates!$A$5:$A$500,0)),0)) | N100: =IF($D100="","",IFERROR(INDEX(ClientRates!$E$5:$E$500,MATCH($B100&"|"&$L100,ClientRates!$A$5:$A$500,0)),0)) | O100: =IF($D100="","",F100*M100+G100*N100) | P100: =IF(OR($D100="",$J100<>"Supplier"),"",IFERROR(INDEX(SupplierRates!$D$5:$D$500,MATCH($K100&"|"&$L100,SupplierRates!$A$5:$A$500,0)),0)) | Q100: =IF(OR($D100="",$J100<>"Supplier"),"",IFERROR(INDEX(SupplierRates!$E$5:$E$500,MATCH($K100&"|"&$L100,SupplierRates!$A$5:$A$500,0)),0)) | R100: =IF(OR($D100="",$J100<>"Supplier"),0,F100*P100+G100*Q100) -> 0 | S100: =IF(OR($D100="",$J100<>"Own"),0,IFERROR((F100+G100*Settings!$B$13)*INDEX(Workers!$V$5:$V$2004,MATCH($D100,Workers!$A$5:$A$2004,0)),0)) -> 0 | T100: =IF($D100="","",O100-R100-S100)
I101: =IF($D101="","",IFERROR(INDEX(Workers!$B$5:$B$2004,MATCH($D101,Workers!$A$5:$A$2004,0)),"NOT FOUND")) | J101: =IF($D101="","",IFERROR(INDEX(Workers!$C$5:$C$2004,MATCH($D101,Workers!$A$5:$A$2004,0)),"")) | K101: =IF($D101="","",IFERROR(IF(INDEX(Workers!$D$5:$D$2004,MATCH($D101,Workers!$A$5:$A$2004,0))=0,"",INDEX(Workers!$D$5:$D$2004,MATCH($D101,Workers!$A$5:$A$2004,0))),"")) | L101: =IF($D101="","",IFERROR(INDEX(Workers!$E$5:$E$2004,MATCH($D101,Workers!$A$5:$A$2004,0)),"")) | M101: =IF($D101="","",IFERROR(INDEX(ClientRates!$D$5:$D$500,MATCH($B101&"|"&$L101,ClientRates!$A$5:$A$500,0)),0)) | N101: =IF($D101="","",IFERROR(INDEX(ClientRates!$E$5:$E$500,MATCH($B101&"|"&$L101,ClientRates!$A$5:$A$500,0)),0)) | O101: =IF($D101="","",F101*M101+G101*N101) | P101: =IF(OR($D101="",$J101<>"Supplier"),"",IFERROR(INDEX(SupplierRates!$D$5:$D$500,MATCH($K101&"|"&$L101,SupplierRates!$A$5:$A$500,0)),0)) | Q101: =IF(OR($D101="",$J101<>"Supplier"),"",IFERROR(INDEX(SupplierRates!$E$5:$E$500,MATCH($K101&"|"&$L101,SupplierRates!$A$5:$A$500,0)),0)) | R101: =IF(OR($D101="",$J101<>"Supplier"),0,F101*P101+G101*Q101) -> 0 | S101: =IF(OR($D101="",$J101<>"Own"),0,IFERROR((F101+G101*Settings!$B$13)*INDEX(Workers!$V$5:$V$2004,MATCH($D101,Workers!$A$5:$A$2004,0)),0)) -> 0 | T101: =IF($D101="","",O101-R101-S101)
I102: =IF($D102="","",IFERROR(INDEX(Workers!$B$5:$B$2004,MATCH($D102,Workers!$A$5:$A$2004,0)),"NOT FOUND")) | J102: =IF($D102="","",IFERROR(INDEX(Workers!$C$5:$C$2004,MATCH($D102,Workers!$A$5:$A$2004,0)),"")) | K102: =IF($D102="","",IFERROR(IF(INDEX(Workers!$D$5:$D$2004,MATCH($D102,Workers!$A$5:$A$2004,0))=0,"",INDEX(Workers!$D$5:$D$2004,MATCH($D102,Workers!$A$5:$A$2004,0))),"")) | L102: =IF($D102="","",IFERROR(INDEX(Workers!$E$5:$E$2004,MATCH($D102,Workers!$A$5:$A$2004,0)),"")) | M102: =IF($D102="","",IFERROR(INDEX(ClientRates!$D$5:$D$500,MATCH($B102&"|"&$L102,ClientRates!$A$5:$A$500,0)),0)) | N102: =IF($D102="","",IFERROR(INDEX(ClientRates!$E$5:$E$500,MATCH($B102&"|"&$L102,ClientRates!$A$5:$A$500,0)),0)) | O102: =IF($D102="","",F102*M102+G102*N102) | P102: =IF(OR($D102="",$J102<>"Supplier"),"",IFERROR(INDEX(SupplierRates!$D$5:$D$500,MATCH($K102&"|"&$L102,SupplierRates!$A$5:$A$500,0)),0)) | Q102: =IF(OR($D102="",$J102<>"Supplier"),"",IFERROR(INDEX(SupplierRates!$E$5:$E$500,MATCH($K102&"|"&$L102,SupplierRates!$A$5:$A$500,0)),0)) | R102: =IF(OR($D102="",$J102<>"Supplier"),0,F102*P102+G102*Q102) -> 0 | S102: =IF(OR($D102="",$J102<>"Own"),0,IFERROR((F102+G102*Settings!$B$13)*INDEX(Workers!$V$5:$V$2004,MATCH($D102,Workers!$A$5:$A$2004,0)),0)) -> 0 | T102: =IF($D102="","",O102-R102-S102)
... I3004: =IF($D3004="","",IFERROR(INDEX(Workers!$B$5:$B$2004,MATCH($D3004,Workers!$A$5:$A$2004,0)),"NOT FOUND")) | J3004: =IF($D3004="","",IFERROR(INDEX(Workers!$C$5:$C$2004,MATCH($D3004,Workers!$A$5:$A$2004,0)),"")) | K3004: =IF($D3004="","",IFERROR(IF(INDEX(Workers!$D$5:$D$2004,MATCH($D3004,Workers!$A$5:$A$2004,0))=0,"",INDEX(Workers!$D$5:$D$2004,MATCH($D3004,Workers!$A$5:$A$2004,0))),"")) | L3004: =IF($D3004="","",IFERROR(INDEX(Workers!$E$5:$E$2004,MATCH($D3004,Workers!$A$5:$A$2004,0)),"")) | M3004: =IF($D3004="","",IFERROR(INDEX(ClientRates!$D$5:$D$500,MATCH($B3004&"|"&$L3004,ClientRates!$A$5:$A$500,0)),0)) | N3004: =IF($D3004="","",IFERROR(INDEX(ClientRates!$E$5:$E$500,MATCH($B3004&"|"&$L3004,ClientRates!$A$5:$A$500,0)),0)) | O3004: =IF($D3004="","",F3004*M3004+G3004*N3004) | P3004: =IF(OR($D3004="",$J3004<>"Supplier"),"",IFERROR(INDEX(SupplierRates!$D$5:$D$500,MATCH($K3004&"|"&$L3004,SupplierRates!$A$5:$A$500,0)),0)) | Q3004: =IF(OR($D3004="",$J3004<>"Supplier"),"",IFERROR(INDEX(SupplierRates!$E$5:$E$500,MATCH($K3004&"|"&$L3004,SupplierRates!$A$5:$A$500,0)),0)) | R3004: =IF(OR($D3004="",$J3004<>"Supplier"),0,F3004*P3004+G3004*Q3004) -> 0 | S3004: =IF(OR($D3004="",$J3004<>"Own"),0,IFERROR((F3004+G3004*Settings!$B$13)*INDEX(Workers!$V$5:$V$2004,MATCH($D3004,Workers!$A$5:$A$2004,0)),0)) -> 0 | T3004: =IF($D3004="","",O3004-R3004-S3004)

Sheet Deductions
A1: Advances & Deductions (Own workers) | F1: « HOME
A2: Deduct in Month = the payroll month in which the amount is recovered.
A4: Date | B4: Worker ID | C4: Type | D4: Amount (AED) | E4: Deduct in Month (1st day) | F4: Notes
A5: 46298 | B5: W0002 | C5: Advance | D5: 300 | E5: 46296 | F5: Family emergency
A6: 46300 | B6: W0005 | C6: Advance | D6: 500 | E6: 46296
A7: 46304 | B7: W0011 | C7: Fine | D7: 100 | E7: 46296 | F7: Late arrival x3
A8: 46307 | B8: W0014 | C8: Accommodation | D8: 150 | E8: 46296 | F8: Private room
A9: 46310 | B9: W0020 | C9: Advance | D9: 400 | E9: 46296
A10: 46313 | B10: W0027 | C10: Other | D10: 75 | E10: 46296 | F10: Lost safety helmet
A11: 46316 | B11: W0033 | C11: Advance | D11: 250 | E11: 46296

Sheet Payroll
A1: Payroll - Own Workers | D1: « HOME
A2: Fully automatic. Lists every Active Own worker; values for the month in Settings!B8.
A3: TOTALS | B3: =COUNTIF(A5:A1204,"?*")&" workers" -> 40 workers | E3: =SUM(E5:E1204) -> 968 | F3: =SUM(F5:F1204) -> 7744 | G3: =SUM(G5:G1204) -> 736 | H3: =SUM(H5:H1204) -> 60 | I3: =SUM(I5:I1204) -> 62600 | J3: =SUM(J5:J1204) -> 14100 | K3: =SUM(K5:K1204) -> 72390.01 | L3: =SUM(L5:L1204) -> 9776 | ... R3: =SUM(R5:R1204) -> 87430.82
A4: Worker ID | B4: Name | C4: Trade | D4: Pay Basis | E4: Days Worked | F4: Normal Hours | G4: OT Hours | H4: Absent Days | I4: Basic Salary | J4: Allowances | K4: Fixed Earned | L4: Hourly Earnings | M4: OT Pay | N4: Gross Pay | O4: Advances | P4: Other Deductions | Q4: Total Deductions | R4: NET PAY (AED) | S4: Bank Routing | T4: IBAN | U4: Labour Card / Person ID
A5: =IFERROR(INDEX(Workers!$A$5:$A$2004,MATCH(ROW()-4,Workers!$U$5:$U$2004,0)),"") -> W0001 | B5: =IF($A5="","",INDEX(Workers!$B$5:$B$2004,MATCH($A5,Workers!$A$5:$A$2004,0))) -> Marlon Khan | C5: =IF($A5="","",INDEX(Workers!$E$5:$E$2004,MATCH($A5,Workers!$A$5:$A$2004,0))) -> Steel Fixer | D5: =IF($A5="","",INDEX(Workers!$K$5:$K$2004,MATCH($A5,Workers!$A$5:$A$2004,0))) -> Monthly | E5: =IF($A5="","",SUMIFS(Timesheet!$E$5:$E$3004,Timesheet!$D$5:$D$3004,$A5,Timesheet!$A$5:$A$3004,">="&Settings!$B$8,Timesheet!$A$5:$A$3004,"<="&Settings!$B$9)) -> 26 | F5: =IF($A5="","",SUMIFS(Timesheet!$F$5:$F$3004,Timesheet!$D$5:$D$3004,$A5,Timesheet!$A$5:$A$3004,">="&Settings!$B$8,Timesheet!$A$5:$A$3004,"<="&Settings!$B$9)) -> 208 | G5: =IF($A5="","",SUMIFS(Timesheet!$G$5:$G$3004,Timesheet!$D$5:$D$3004,$A5,Timesheet!$A$5:$A$3004,">="&Settings!$B$8,Timesheet!$A$5:$A$3004,"<="&Settings!$B$9)) -> 26 | H5: =IF($A5="","",IF(D5="Monthly",MAX(0,Settings!$B$11-E5),0)) -> 0 | I5: =IF($A5="","",N(INDEX(Workers!$L$5:$L$2004,MATCH($A5,Workers!$A$5:$A$2004,0)))) -> 1400 | J5: =IF($A5="","",N(INDEX(Workers!$M$5:$M$2004,MATCH($A5,Workers!$A$5:$A$2004,0)))) -> 400 | K5: =IF($A5="","",IF(D5="Monthly",ROUND(MAX(0,(I5+J5)-(I5+J5)/Settings!$B$10*H5),2),0)) -> 1800 | L5: =IF($A5="","",IF(D5="Hourly",ROUND(F5*N(INDEX(Workers!$N$5:$N$2004,MATCH($A5,Workers!$A$5:$A$2004,0))),2),0)) -> 0 | M5: =IF($A5="","",ROUND(G5*IF(D5="Hourly",N(INDEX(Workers!$N$5:$N$2004,MATCH($A5,Workers!$A$5:$A$2004,0))),I5/Settings!$B$10/Settings!$B$12)*Settings!$B$13,2)) -> 189.58 | N5: =IF($A5="","",K5+L5+M5) -> 1989.58 | O5: =IF($A5="","",SUMIFS(Deductions!$D$5:$D$2000,Deductions!$B$5:$B$2000,$A5,Deductions!$C$5:$C$2000,"Advance",Deductions!$E$5:$E$2000,">="&Settings!$B$8,Deductions!$E$5:$E$2000,"<="&Settings!$B$9)) -> 0 | P5: =IF($A5="","",SUMIFS(Deductions!$D$5:$D$2000,Deductions!$B$5:$B$2000,$A5,Deductions!$E$5:$E$2000,">="&Settings!$B$8,Deductions!$E$5:$E$2000,"<="&Settings!$B$9)-O5) -> 0 | Q5: =IF($A5="","",O5+P5) -> 0 | R5: =IF($A5="","",N5-Q5) -> 1989.58 | S5: =IF($A5="","",INDEX(Workers!$O$5:$O$2004,MATCH($A5,Workers!$A$5:$A$2004,0))&"") -> 402320106 | T5: =IF($A5="","",INDEX(Workers!$P$5:$P$2004,MATCH($A5,Workers!$A$5:$A$2004,0))&"") -> AE96 1884 8481 7428 7521 508 | U5: =IF($A5="","",INDEX(Workers!$H$5:$H$2004,MATCH($A5,Workers!$A$5:$A$2004,0))&"") -> 96921334349946
A6: =IFERROR(INDEX(Workers!$A$5:$A$2004,MATCH(ROW()-4,Workers!$U$5:$U$2004,0)),"") -> W0002 | B6: =IF($A6="","",INDEX(Workers!$B$5:$B$2004,MATCH($A6,Workers!$A$5:$A$2004,0))) -> Rohan Ali | C6: =IF($A6="","",INDEX(Workers!$E$5:$E$2004,MATCH($A6,Workers!$A$5:$A$2004,0))) -> Helper | D6: =IF($A6="","",INDEX(Workers!$K$5:$K$2004,MATCH($A6,Workers!$A$5:$A$2004,0))) -> Monthly | E6: =IF($A6="","",SUMIFS(Timesheet!$E$5:$E$3004,Timesheet!$D$5:$D$3004,$A6,Timesheet!$A$5:$A$3004,">="&Settings!$B$8,Timesheet!$A$5:$A$3004,"<="&Settings!$B$9)) -> 25 | F6: =IF($A6="","",SUMIFS(Timesheet!$F$5:$F$3004,Timesheet!$D$5:$D$3004,$A6,Timesheet!$A$5:$A$3004,">="&Settings!$B$8,Timesheet!$A$5:$A$3004,"<="&Settings!$B$9)) -> 200 | G6: =IF($A6="","",SUMIFS(Timesheet!$G$5:$G$3004,Timesheet!$D$5:$D$3004,$A6,Timesheet!$A$5:$A$3004,">="&Settings!$B$8,Timesheet!$A$5:$A$3004,"<="&Settings!$B$9)) -> 26 | H6: =IF($A6="","",IF(D6="Monthly",MAX(0,Settings!$B$11-E6),0)) -> 1 | I6: =IF($A6="","",N(INDEX(Workers!$L$5:$L$2004,MATCH($A6,Workers!$A$5:$A$2004,0)))) -> 1200 | J6: =IF($A6="","",N(INDEX(Workers!$M$5:$M$2004,MATCH($A6,Workers!$A$5:$A$2004,0)))) -> 500 | K6: =IF($A6="","",IF(D6="Monthly",ROUND(MAX(0,(I6+J6)-(I6+J6)/Settings!$B$10*H6),2),0)) -> 1643.33 | L6: =IF($A6="","",IF(D6="Hourly",ROUND(F6*N(INDEX(Workers!$N$5:$N$2004,MATCH($A6,Workers!$A$5:$A$2004,0))),2),0)) -> 0 | M6: =IF($A6="","",ROUND(G6*IF(D6="Hourly",N(INDEX(Workers!$N$5:$N$2004,MATCH($A6,Workers!$A$5:$A$2004,0))),I6/Settings!$B$10/Settings!$B$12)*Settings!$B$13,2)) -> 162.5 | N6: =IF($A6="","",K6+L6+M6) -> 1805.83 | O6: =IF($A6="","",SUMIFS(Deductions!$D$5:$D$2000,Deductions!$B$5:$B$2000,$A6,Deductions!$C$5:$C$2000,"Advance",Deductions!$E$5:$E$2000,">="&Settings!$B$8,Deductions!$E$5:$E$2000,"<="&Settings!$B$9)) -> 300 | P6: =IF($A6="","",SUMIFS(Deductions!$D$5:$D$2000,Deductions!$B$5:$B$2000,$A6,Deductions!$E$5:$E$2000,">="&Settings!$B$8,Deductions!$E$5:$E$2000,"<="&Settings!$B$9)-O6) -> 0 | Q6: =IF($A6="","",O6+P6) -> 300 | R6: =IF($A6="","",N6-Q6) -> 1505.83 | S6: =IF($A6="","",INDEX(Workers!$O$5:$O$2004,MATCH($A6,Workers!$A$5:$A$2004,0))&"") -> 600310101 | T6: =IF($A6="","",INDEX(Workers!$P$5:$P$2004,MATCH($A6,Workers!$A$5:$A$2004,0))&"") -> AE88 1417 2152 4407 7164 252 | U6: =IF($A6="","",INDEX(Workers!$H$5:$H$2004,MATCH($A6,Workers!$A$5:$A$2004,0))&"") -> 24278776051635
A7: =IFERROR(INDEX(Workers!$A$5:$A$2004,MATCH(ROW()-4,Workers!$U$5:$U$2004,0)),"") -> W0003 | B7: =IF($A7="","",INDEX(Workers!$B$5:$B$2004,MATCH($A7,Workers!$A$5:$A$2004,0))) -> Ronel Thapa | C7: =IF($A7="","",INDEX(Workers!$E$5:$E$2004,MATCH($A7,Workers!$A$5:$A$2004,0))) -> Mason | D7: =IF($A7="","",INDEX(Workers!$K$5:$K$2004,MATCH($A7,Workers!$A$5:$A$2004,0))) -> Monthly | E7: =IF($A7="","",SUMIFS(Timesheet!$E$5:$E$3004,Timesheet!$D$5:$D$3004,$A7,Timesheet!$A$5:$A$3004,">="&Settings!$B$8,Timesheet!$A$5:$A$3004,"<="&Settings!$B$9)) -> 25 | F7: =IF($A7="","",SUMIFS(Timesheet!$F$5:$F$3004,Timesheet!$D$5:$D$3004,$A7,Timesheet!$A$5:$A$3004,">="&Settings!$B$8,Timesheet!$A$5:$A$3004,"<="&Settings!$B$9)) -> 200 | G7: =IF($A7="","",SUMIFS(Timesheet!$G$5:$G$3004,Timesheet!$D$5:$D$3004,$A7,Timesheet!$A$5:$A$3004,">="&Settings!$B$8,Timesheet!$A$5:$A$3004,"<="&Settings!$B$9)) -> 26 | H7: =IF($A7="","",IF(D7="Monthly",MAX(0,Settings!$B$11-E7),0)) -> 1 | I7: =IF($A7="","",N(INDEX(Workers!$L$5:$L$2004,MATCH($A7,Workers!$A$5:$A$2004,0)))) -> 1500 | J7: =IF($A7="","",N(INDEX(Workers!$M$5:$M$2004,MATCH($A7,Workers!$A$5:$A$2004,0)))) -> 500 | K7: =IF($A7="","",IF(D7="Monthly",ROUND(MAX(0,(I7+J7)-(I7+J7)/Settings!$B$10*H7),2),0)) -> 1933.33 | L7: =IF($A7="","",IF(D7="Hourly",ROUND(F7*N(INDEX(Workers!$N$5:$N$2004,MATCH($A7,Workers!$A$5:$A$2004,0))),2),0)) -> 0 | M7: =IF($A7="","",ROUND(G7*IF(D7="Hourly",N(INDEX(Workers!$N$5:$N$2004,MATCH($A7,Workers!$A$5:$A$2004,0))),I7/Settings!$B$10/Settings!$B$12)*Settings!$B$13,2)) -> 203.13 | N7: =IF($A7="","",K7+L7+M7) -> 2136.46 | O7: =IF($A7="","",SUMIFS(Deductions!$D$5:$D$2000,Deductions!$B$5:$B$2000,$A7,Deductions!$C$5:$C$2000,"Advance",Deductions!$E$5:$E$2000,">="&Settings!$B$8,Deductions!$E$5:$E$2000,"<="&Settings!$B$9)) -> 0 | P7: =IF($A7="","",SUMIFS(Deductions!$D$5:$D$2000,Deductions!$B$5:$B$2000,$A7,Deductions!$E$5:$E$2000,">="&Settings!$B$8,Deductions!$E$5:$E$2000,"<="&Settings!$B$9)-O7) -> 0 | Q7: =IF($A7="","",O7+P7) -> 0 | R7: =IF($A7="","",N7-Q7) -> 2136.46 | S7: =IF($A7="","",INDEX(Workers!$O$5:$O$2004,MATCH($A7,Workers!$A$5:$A$2004,0))&"") -> 402320106 | T7: =IF($A7="","",INDEX(Workers!$P$5:$P$2004,MATCH($A7,Workers!$A$5:$A$2004,0))&"") -> AE12 4362 9654 6926 3401 806 | U7: =IF($A7="","",INDEX(Workers!$H$5:$H$2004,MATCH($A7,Workers!$A$5:$A$2004,0))&"") -> 32723349357046
A8: =IFERROR(INDEX(Workers!$A$5:$A$2004,MATCH(ROW()-4,Workers!$U$5:$U$2004,0)),"") -> W0004 | B8: =IF($A8="","",INDEX(Workers!$B$5:$B$2004,MATCH($A8,Workers!$A$5:$A$2004,0))) -> Tariq Varghese | C8: =IF($A8="","",INDEX(Workers!$E$5:$E$2004,MATCH($A8,Workers!$A$5:$A$2004,0))) -> Helper | D8: =IF($A8="","",INDEX(Workers!$K$5:$K$2004,MATCH($A8,Workers!$A$5:$A$2004,0))) -> Monthly | E8: =IF($A8="","",SUMIFS(Timesheet!$E$5:$E$3004,Timesheet!$D$5:$D$3004,$A8,Timesheet!$A$5:$A$3004,">="&Settings!$B$8,Timesheet!$A$5:$A$3004,"<="&Settings!$B$9)) -> 24 | F8: =IF($A8="","",SUMIFS(Timesheet!$F$5:$F$3004,Timesheet!$D$5:$D$3004,$A8,Timesheet!$A$5:$A$3004,">="&Settings!$B$8,Timesheet!$A$5:$A$3004,"<="&Settings!$B$9)) -> 192 | G8: =IF($A8="","",SUMIFS(Timesheet!$G$5:$G$3004,Timesheet!$D$5:$D$3004,$A8,Timesheet!$A$5:$A$3004,">="&Settings!$B$8,Timesheet!$A$5:$A$3004,"<="&Settings!$B$9)) -> 16 | H8: =IF($A8="","",IF(D8="Monthly",MAX(0,Settings!$B$11-E8),0)) -> 2 | I8: =IF($A8="","",N(INDEX(Workers!$L$5:$L$2004,MATCH($A8,Workers!$A$5:$A$2004,0)))) -> 2000 | J8: =IF($A8="","",N(INDEX(Workers!$M$5:$M$2004,MATCH($A8,Workers!$A$5:$A$2004,0)))) -> 300 | K8: =IF($A8="","",IF(D8="Monthly",ROUND(MAX(0,(I8+J8)-(I8+J8)/Settings!$B$10*H8),2),0)) -> 2146.67 | L8: =IF($A8="","",IF(D8="Hourly",ROUND(F8*N(INDEX(Workers!$N$5:$N$2004,MATCH($A8,Workers!$A$5:$A$2004,0))),2),0)) -> 0 | M8: =IF($A8="","",ROUND(G8*IF(D8="Hourly",N(INDEX(Workers!$N$5:$N$2004,MATCH($A8,Workers!$A$5:$A$2004,0))),I8/Settings!$B$10/Settings!$B$12)*Settings!$B$13,2)) -> 166.67 | N8: =IF($A8="","",K8+L8+M8) -> 2313.34 | O8: =IF($A8="","",SUMIFS(Deductions!$D$5:$D$2000,Deductions!$B$5:$B$2000,$A8,Deductions!$C$5:$C$2000,"Advance",Deductions!$E$5:$E$2000,">="&Settings!$B$8,Deductions!$E$5:$E$2000,"<="&Settings!$B$9)) -> 0 | P8: =IF($A8="","",SUMIFS(Deductions!$D$5:$D$2000,Deductions!$B$5:$B$2000,$A8,Deductions!$E$5:$E$2000,">="&Settings!$B$8,Deductions!$E$5:$E$2000,"<="&Settings!$B$9)-O8) -> 0 | Q8: =IF($A8="","",O8+P8) -> 0 | R8: =IF($A8="","",N8-Q8) -> 2313.34 | S8: =IF($A8="","",INDEX(Workers!$O$5:$O$2004,MATCH($A8,Workers!$A$5:$A$2004,0))&"") -> 803320101 | T8: =IF($A8="","",INDEX(Workers!$P$5:$P$2004,MATCH($A8,Workers!$A$5:$A$2004,0))&"") -> AE76 9073 6825 1474 1457 909 | U8: =IF($A8="","",INDEX(Workers!$H$5:$H$2004,MATCH($A8,Workers!$A$5:$A$2004,0))&"") -> 41910762301181
A9: =IFERROR(INDEX(Workers!$A$5:$A$2004,MATCH(ROW()-4,Workers!$U$5:$U$2004,0)),"") -> W0005 | B9: =IF($A9="","",INDEX(Workers!$B$5:$B$2004,MATCH($A9,Workers!$A$5:$A$2004,0))) -> Joseph Ahmed | C9: =IF($A9="","",INDEX(Workers!$E$5:$E$2004,MATCH($A9,Workers!$A$5:$A$2004,0))) -> Helper | D9: =IF($A9="","",INDEX(Workers!$K$5:$K$2004,MATCH($A9,Workers!$A$5:$A$2004,0))) -> Monthly | E9: =IF($A9="","",SUMIFS(Timesheet!$E$5:$E$3004,Timesheet!$D$5:$D$3004,$A9,Timesheet!$A$5:$A$3004,">="&Settings!$B$8,Timesheet!$A$5:$A$3004,"<="&Settings!$B$9)) -> 26 | F9: =IF($A9="","",SUMIFS(Timesheet!$F$5:$F$3004,Timesheet!$D$5:$D$3004,$A9,Timesheet!$A$5:$A$3004,">="&Settings!$B$8,Timesheet!$A$5:$A$3004,"<="&Settings!$B$9)) -> 208 | G9: =IF($A9="","",SUMIFS(Timesheet!$G$5:$G$3004,Timesheet!$D$5:$D$3004,$A9,Timesheet!$A$5:$A$3004,">="&Settings!$B$8,Timesheet!$A$5:$A$3004,"<="&Settings!$B$9)) -> 26 | H9: =IF($A9="","",IF(D9="Monthly",MAX(0,Settings!$B$11-E9),0)) -> 0 | I9: =IF($A9="","",N(INDEX(Workers!$L$5:$L$2004,MATCH($A9,Workers!$A$5:$A$2004,0)))) -> 1200 | J9: =IF($A9="","",N(INDEX(Workers!$M$5:$M$2004,MATCH($A9,Workers!$A$5:$A$2004,0)))) -> 400 | K9: =IF($A9="","",IF(D9="Monthly",ROUND(MAX(0,(I9+J9)-(I9+J9)/Settings!$B$10*H9),2),0)) -> 1600 | L9: =IF($A9="","",IF(D9="Hourly",ROUND(F9*N(INDEX(Workers!$N$5:$N$2004,MATCH($A9,Workers!$A$5:$A$2004,0))),2),0)) -> 0 | M9: =IF($A9="","",ROUND(G9*IF(D9="Hourly",N(INDEX(Workers!$N$5:$N$2004,MATCH($A9,Workers!$A$5:$A$2004,0))),I9/Settings!$B$10/Settings!$B$12)*Settings!$B$13,2)) -> 162.5 | N9: =IF($A9="","",K9+L9+M9) -> 1762.5 | O9: =IF($A9="","",SUMIFS(Deductions!$D$5:$D$2000,Deductions!$B$5:$B$2000,$A9,Deductions!$C$5:$C$2000,"Advance",Deductions!$E$5:$E$2000,">="&Settings!$B$8,Deductions!$E$5:$E$2000,"<="&Settings!$B$9)) -> 500 | P9: =IF($A9="","",SUMIFS(Deductions!$D$5:$D$2000,Deductions!$B$5:$B$2000,$A9,Deductions!$E$5:$E$2000,">="&Settings!$B$8,Deductions!$E$5:$E$2000,"<="&Settings!$B$9)-O9) -> 0 | Q9: =IF($A9="","",O9+P9) -> 500 | R9: =IF($A9="","",N9-Q9) -> 1262.5 | S9: =IF($A9="","",INDEX(Workers!$O$5:$O$2004,MATCH($A9,Workers!$A$5:$A$2004,0))&"") -> 803320101 | T9: =IF($A9="","",INDEX(Workers!$P$5:$P$2004,MATCH($A9,Workers!$A$5:$A$2004,0))&"") -> AE71 6636 2389 2964 7365 901 | U9: =IF($A9="","",INDEX(Workers!$H$5:$H$2004,MATCH($A9,Workers!$A$5:$A$2004,0))&"") -> 95890327812981
A10: =IFERROR(INDEX(Workers!$A$5:$A$2004,MATCH(ROW()-4,Workers!$U$5:$U$2004,0)),"") -> W0006 | B10: =IF($A10="","",INDEX(Workers!$B$5:$B$2004,MATCH($A10,Workers!$A$5:$A$2004,0))) -> Dinesh Shrestha | C10: =IF($A10="","",INDEX(Workers!$E$5:$E$2004,MATCH($A10,Workers!$A$5:$A$2004,0))) -> Driver | D10: =IF($A10="","",INDEX(Workers!$K$5:$K$2004,MATCH($A10,Workers!$A$5:$A$2004,0))) -> Monthly | E10: =IF($A10="","",SUMIFS(Timesheet!$E$5:$E$3004,Timesheet!$D$5:$D$3004,$A10,Timesheet!$A$5:$A$3004,">="&Settings!$B$8,Timesheet!$A$5:$A$3004,"<="&Settings!$B$9)) -> 22 | F10: =IF($A10="","",SUMIFS(Timesheet!$F$5:$F$3004,Timesheet!$D$5:$D$3004,$A10,Timesheet!$A$5:$A$3004,">="&Settings!$B$8,Timesheet!$A$5:$A$3004,"<="&Settings!$B$9)) -> 176 | G10: =IF($A10="","",SUMIFS(Timesheet!$G$5:$G$3004,Timesheet!$D$5:$D$3004,$A10,Timesheet!$A$5:$A$3004,">="&Settings!$B$8,Timesheet!$A$5:$A$3004,"<="&Settings!$B$9)) -> 0 | H10: =IF($A10="","",IF(D10="Monthly",MAX(0,Settings!$B$11-E10),0)) -> 4 | I10: =IF($A10="","",N(INDEX(Workers!$L$5:$L$2004,MATCH($A10,Workers!$A$5:$A$2004,0)))) -> 1200 | J10: =IF($A10="","",N(INDEX(Workers!$M$5:$M$2004,MATCH($A10,Workers!$A$5:$A$2004,0)))) -> 300 | K10: =IF($A10="","",IF(D10="Monthly",ROUND(MAX(0,(I10+J10)-(I10+J10)/Settings!$B$10*H10),2),0)) -> 1300 | L10: =IF($A10="","",IF(D10="Hourly",ROUND(F10*N(INDEX(Workers!$N$5:$N$2004,MATCH($A10,Workers!$A$5:$A$2004,0))),2),0)) -> 0 | M10: =IF($A10="","",ROUND(G10*IF(D10="Hourly",N(INDEX(Workers!$N$5:$N$2004,MATCH($A10,Workers!$A$5:$A$2004,0))),I10/Settings!$B$10/Settings!$B$12)*Settings!$B$13,2)) -> 0 | N10: =IF($A10="","",K10+L10+M10) -> 1300 | O10: =IF($A10="","",SUMIFS(Deductions!$D$5:$D$2000,Deductions!$B$5:$B$2000,$A10,Deductions!$C$5:$C$2000,"Advance",Deductions!$E$5:$E$2000,">="&Settings!$B$8,Deductions!$E$5:$E$2000,"<="&Settings!$B$9)) -> 0 | P10: =IF($A10="","",SUMIFS(Deductions!$D$5:$D$2000,Deductions!$B$5:$B$2000,$A10,Deductions!$E$5:$E$2000,">="&Settings!$B$8,Deductions!$E$5:$E$2000,"<="&Settings!$B$9)-O10) -> 0 | Q10: =IF($A10="","",O10+P10) -> 0 | R10: =IF($A10="","",N10-Q10) -> 1300 | S10: =IF($A10="","",INDEX(Workers!$O$5:$O$2004,MATCH($A10,Workers!$A$5:$A$2004,0))&"") -> 402320106 | T10: =IF($A10="","",INDEX(Workers!$P$5:$P$2004,MATCH($A10,Workers!$A$5:$A$2004,0))&"") -> AE70 6741 3554 9989 9983 234 | U10: =IF($A10="","",INDEX(Workers!$H$5:$H$2004,MATCH($A10,Workers!$A$5:$A$2004,0))&"") -> 96071772425721
A11: =IFERROR(INDEX(Workers!$A$5:$A$2004,MATCH(ROW()-4,Workers!$U$5:$U$2004,0)),"") -> W0007 | B11: =IF($A11="","",INDEX(Workers!$B$5:$B$2004,MATCH($A11,Workers!$A$5:$A$2004,0))) -> Rahul Kumar | C11: =IF($A11="","",INDEX(Workers!$E$5:$E$2004,MATCH($A11,Workers!$A$5:$A$2004,0))) -> Mason | D11: =IF($A11="","",INDEX(Workers!$K$5:$K$2004,MATCH($A11,Workers!$A$5:$A$2004,0))) -> Monthly | E11: =IF($A11="","",SUMIFS(Timesheet!$E$5:$E$3004,Timesheet!$D$5:$D$3004,$A11,Timesheet!$A$5:$A$3004,">="&Settings!$B$8,Timesheet!$A$5:$A$3004,"<="&Settings!$B$9)) -> 24 | F11: =IF($A11="","",SUMIFS(Timesheet!$F$5:$F$3004,Timesheet!$D$5:$D$3004,$A11,Timesheet!$A$5:$A$3004,">="&Settings!$B$8,Timesheet!$A$5:$A$3004,"<="&Settings!$B$9)) -> 192 | G11: =IF($A11="","",SUMIFS(Timesheet!$G$5:$G$3004,Timesheet!$D$5:$D$3004,$A11,Timesheet!$A$5:$A$3004,">="&Settings!$B$8,Timesheet!$A$5:$A$3004,"<="&Settings!$B$9)) -> 26 | H11: =IF($A11="","",IF(D11="Monthly",MAX(0,Settings!$B$11-E11),0)) -> 2 | I11: =IF($A11="","",N(INDEX(Workers!$L$5:$L$2004,MATCH($A11,Workers!$A$5:$A$2004,0)))) -> 2000 | J11: =IF($A11="","",N(INDEX(Workers!$M$5:$M$2004,MATCH($A11,Workers!$A$5:$A$2004,0)))) -> 400 | K11: =IF($A11="","",IF(D11="Monthly",ROUND(MAX(0,(I11+J11)-(I11+J11)/Settings!$B$10*H11),2),0)) -> 2240 | L11: =IF($A11="","",IF(D11="Hourly",ROUND(F11*N(INDEX(Workers!$N$5:$N$2004,MATCH($A11,Workers!$A$5:$A$2004,0))),2),0)) -> 0 | M11: =IF($A11="","",ROUND(G11*IF(D11="Hourly",N(INDEX(Workers!$N$5:$N$2004,MATCH($A11,Workers!$A$5:$A$2004,0))),I11/Settings!$B$10/Settings!$B$12)*Settings!$B$13,2)) -> 270.83 | N11: =IF($A11="","",K11+L11+M11) -> 2510.83 | O11: =IF($A11="","",SUMIFS(Deductions!$D$5:$D$2000,Deductions!$B$5:$B$2000,$A11,Deductions!$C$5:$C$2000,"Advance",Deductions!$E$5:$E$2000,">="&Settings!$B$8,Deductions!$E$5:$E$2000,"<="&Settings!$B$9)) -> 0 | P11: =IF($A11="","",SUMIFS(Deductions!$D$5:$D$2000,Deductions!$B$5:$B$2000,$A11,Deductions!$E$5:$E$2000,">="&Settings!$B$8,Deductions!$E$5:$E$2000,"<="&Settings!$B$9)-O11) -> 0 | Q11: =IF($A11="","",O11+P11) -> 0 | R11: =IF($A11="","",N11-Q11) -> 2510.83 | S11: =IF($A11="","",INDEX(Workers!$O$5:$O$2004,MATCH($A11,Workers!$A$5:$A$2004,0))&"") -> 803320101 | T11: =IF($A11="","",INDEX(Workers!$P$5:$P$2004,MATCH($A11,Workers!$A$5:$A$2004,0))&"") -> AE17 6796 8506 9466 7891 946 | U11: =IF($A11="","",INDEX(Workers!$H$5:$H$2004,MATCH($A11,Workers!$A$5:$A$2004,0))&"") -> 68972238951406
A12: =IFERROR(INDEX(Workers!$A$5:$A$2004,MATCH(ROW()-4,Workers!$U$5:$U$2004,0)),"") -> W0008 | B12: =IF($A12="","",INDEX(Workers!$B$5:$B$2004,MATCH($A12,Workers!$A$5:$A$2004,0))) -> Mohan Nair | C12: =IF($A12="","",INDEX(Workers!$E$5:$E$2004,MATCH($A12,Workers!$A$5:$A$2004,0))) -> Helper | D12: =IF($A12="","",INDEX(Workers!$K$5:$K$2004,MATCH($A12,Workers!$A$5:$A$2004,0))) -> Hourly | E12: =IF($A12="","",SUMIFS(Timesheet!$E$5:$E$3004,Timesheet!$D$5:$D$3004,$A12,Timesheet!$A$5:$A$3004,">="&Settings!$B$8,Timesheet!$A$5:$A$3004,"<="&Settings!$B$9)) -> 26 | F12: =IF($A12="","",SUMIFS(Timesheet!$F$5:$F$3004,Timesheet!$D$5:$D$3004,$A12,Timesheet!$A$5:$A$3004,">="&Settings!$B$8,Timesheet!$A$5:$A$3004,"<="&Settings!$B$9)) -> 208 | G12: =IF($A12="","",SUMIFS(Timesheet!$G$5:$G$3004,Timesheet!$D$5:$D$3004,$A12,Timesheet!$A$5:$A$3004,">="&Settings!$B$8,Timesheet!$A$5:$A$3004,"<="&Settings!$B$9)) -> 20 | H12: =IF($A12="","",IF(D12="Monthly",MAX(0,Settings!$B$11-E12),0)) -> 0 | I12: =IF($A12="","",N(INDEX(Workers!$L$5:$L$2004,MATCH($A12,Workers!$A$5:$A$2004,0)))) -> 0 | J12: =IF($A12="","",N(INDEX(Workers!$M$5:$M$2004,MATCH($A12,Workers!$A$5:$A$2004,0)))) -> 0 | K12: =IF($A12="","",IF(D12="Monthly",ROUND(MAX(0,(I12+J12)-(I12+J12)/Settings!$B$10*H12),2),0)) -> 0 | L12: =IF($A12="","",IF(D12="Hourly",ROUND(F12*N(INDEX(Workers!$N$5:$N$2004,MATCH($A12,Workers!$A$5:$A$2004,0))),2),0)) -> 1872 | M12: =IF($A12="","",ROUND(G12*IF(D12="Hourly",N(INDEX(Workers!$N$5:$N$2004,MATCH($A12,Workers!$A$5:$A$2004,0))),I12/Settings!$B$10/Settings!$B$12)*Settings!$B$13,2)) -> 225 | N12: =IF($A12="","",K12+L12+M12) -> 2097 | O12: =IF($A12="","",SUMIFS(Deductions!$D$5:$D$2000,Deductions!$B$5:$B$2000,$A12,Deductions!$C$5:$C$2000,"Advance",Deductions!$E$5:$E$2000,">="&Settings!$B$8,Deductions!$E$5:$E$2000,"<="&Settings!$B$9)) -> 0 | P12: =IF($A12="","",SUMIFS(Deductions!$D$5:$D$2000,Deductions!$B$5:$B$2000,$A12,Deductions!$E$5:$E$2000,">="&Settings!$B$8,Deductions!$E$5:$E$2000,"<="&Settings!$B$9)-O12) -> 0 | Q12: =IF($A12="","",O12+P12) -> 0 | R12: =IF($A12="","",N12-Q12) -> 2097 | S12: =IF($A12="","",INDEX(Workers!$O$5:$O$2004,MATCH($A12,Workers!$A$5:$A$2004,0))&"") -> 402320106 | T12: =IF($A12="","",INDEX(Workers!$P$5:$P$2004,MATCH($A12,Workers!$A$5:$A$2004,0))&"") -> AE71 2738 1930 5071 4134 383 | U12: =IF($A12="","",INDEX(Workers!$H$5:$H$2004,MATCH($A12,Workers!$A$5:$A$2004,0))&"") -> 84691707568212
A13: =IFERROR(INDEX(Workers!$A$5:$A$2004,MATCH(ROW()-4,Workers!$U$5:$U$2004,0)),"") -> W0009 | B13: =IF($A13="","",INDEX(Workers!$B$5:$B$2004,MATCH($A13,Workers!$A$5:$A$2004,0))) -> Anwar Shrestha | C13: =IF($A13="","",INDEX(Workers!$E$5:$E$2004,MATCH($A13,Workers!$A$5:$A$2004,0))) -> Electrician | D13: =IF($A13="","",INDEX(Workers!$K$5:$K$2004,MATCH($A13,Workers!$A$5:$A$2004,0))) -> Monthly | E13: =IF($A13="","",SUMIFS(Timesheet!$E$5:$E$3004,Timesheet!$D$5:$D$3004,$A13,Timesheet!$A$5:$A$3004,">="&Settings!$B$8,Timesheet!$A$5:$A$3004,"<="&Settings!$B$9)) -> 25 | F13: =IF($A13="","",SUMIFS(Timesheet!$F$5:$F$3004,Timesheet!$D$5:$D$3004,$A13,Timesheet!$A$5:$A$3004,">="&Settings!$B$8,Timesheet!$A$5:$A$3004,"<="&Settings!$B$9)) -> 200 | G13: =IF($A13="","",SUMIFS(Timesheet!$G$5:$G$3004,Timesheet!$D$5:$D$3004,$A13,Timesheet!$A$5:$A$3004,">="&Settings!$B$8,Timesheet!$A$5:$A$3004,"<="&Settings!$B$9)) -> 20 | H13: =IF($A13="","",IF(D13="Monthly",MAX(0,Settings!$B$11-E13),0)) -> 1 | I13: =IF($A13="","",N(INDEX(Workers!$L$5:$L$2004,MATCH($A13,Workers!$A$5:$A$2004,0)))) -> 2500 | J13: =IF($A13="","",N(INDEX(Workers!$M$5:$M$2004,MATCH($A13,Workers!$A$5:$A$2004,0)))) -> 500 | K13: =IF($A13="","",IF(D13="Monthly",ROUND(MAX(0,(I13+J13)-(I13+J13)/Settings!$B$10*H13),2),0)) -> 2900 | L13: =IF($A13="","",IF(D13="Hourly",ROUND(F13*N(INDEX(Workers!$N$5:$N$2004,MATCH($A13,Workers!$A$5:$A$2004,0))),2),0)) -> 0 | M13: =IF($A13="","",ROUND(G13*IF(D13="Hourly",N(INDEX(Workers!$N$5:$N$2004,MATCH($A13,Workers!$A$5:$A$2004,0))),I13/Settings!$B$10/Settings!$B$12)*Settings!$B$13,2)) -> 260.42 | N13: =IF($A13="","",K13+L13+M13) -> 3160.42 | O13: =IF($A13="","",SUMIFS(Deductions!$D$5:$D$2000,Deductions!$B$5:$B$2000,$A13,Deductions!$C$5:$C$2000,"Advance",Deductions!$E$5:$E$2000,">="&Settings!$B$8,Deductions!$E$5:$E$2000,"<="&Settings!$B$9)) -> 0 | P13: =IF($A13="","",SUMIFS(Deductions!$D$5:$D$2000,Deductions!$B$5:$B$2000,$A13,Deductions!$E$5:$E$2000,">="&Settings!$B$8,Deductions!$E$5:$E$2000,"<="&Settings!$B$9)-O13) -> 0 | Q13: =IF($A13="","",O13+P13) -> 0 | R13: =IF($A13="","",N13-Q13) -> 3160.42 | S13: =IF($A13="","",INDEX(Workers!$O$5:$O$2004,MATCH($A13,Workers!$A$5:$A$2004,0))&"") -> 600310101 | T13: =IF($A13="","",INDEX(Workers!$P$5:$P$2004,MATCH($A13,Workers!$A$5:$A$2004,0))&"") -> AE74 5057 9572 5253 4319 960 | U13: =IF($A13="","",INDEX(Workers!$H$5:$H$2004,MATCH($A13,Workers!$A$5:$A$2004,0))&"") -> 85052441044367
A14: =IFERROR(INDEX(Workers!$A$5:$A$2004,MATCH(ROW()-4,Workers!$U$5:$U$2004,0)),"") -> W0010 | B14: =IF($A14="","",INDEX(Workers!$B$5:$B$2004,MATCH($A14,Workers!$A$5:$A$2004,0))) -> Hari Nair | C14: =IF($A14="","",INDEX(Workers!$E$5:$E$2004,MATCH($A14,Workers!$A$5:$A$2004,0))) -> Helper | D14: =IF($A14="","",INDEX(Workers!$K$5:$K$2004,MATCH($A14,Workers!$A$5:$A$2004,0))) -> Monthly | E14: =IF($A14="","",SUMIFS(Timesheet!$E$5:$E$3004,Timesheet!$D$5:$D$3004,$A14,Timesheet!$A$5:$A$3004,">="&Settings!$B$8,Timesheet!$A$5:$A$3004,"<="&Settings!$B$9)) -> 25 | F14: =IF($A14="","",SUMIFS(Timesheet!$F$5:$F$3004,Timesheet!$D$5:$D$3004,$A14,Timesheet!$A$5:$A$3004,">="&Settings!$B$8,Timesheet!$A$5:$A$3004,"<="&Settings!$B$9)) -> 200 | G14: =IF($A14="","",SUMIFS(Timesheet!$G$5:$G$3004,Timesheet!$D$5:$D$3004,$A14,Timesheet!$A$5:$A$3004,">="&Settings!$B$8,Timesheet!$A$5:$A$3004,"<="&Settings!$B$9)) -> 0 | H14: =IF($A14="","",IF(D14="Monthly",MAX(0,Settings!$B$11-E14),0)) -> 1 | I14: =IF($A14="","",N(INDEX(Workers!$L$5:$L$2004,MATCH($A14,Workers!$A$5:$A$2004,0)))) -> 2000 | J14: =IF($A14="","",N(INDEX(Workers!$M$5:$M$2004,MATCH($A14,Workers!$A$5:$A$2004,0)))) -> 500 | K14: =IF($A14="","",IF(D14="Monthly",ROUND(MAX(0,(I14+J14)-(I14+J14)/Settings!$B$10*H14),2),0)) -> 2416.67 | L14: =IF($A14="","",IF(D14="Hourly",ROUND(F14*N(INDEX(Workers!$N$5:$N$2004,MATCH($A14,Workers!$A$5:$A$2004,0))),2),0)) -> 0 | M14: =IF($A14="","",ROUND(G14*IF(D14="Hourly",N(INDEX(Workers!$N$5:$N$2004,MATCH($A14,Workers!$A$5:$A$2004,0))),I14/Settings!$B$10/Settings!$B$12)*Settings!$B$13,2)) -> 0 | N14: =IF($A14="","",K14+L14+M14) -> 2416.67 | O14: =IF($A14="","",SUMIFS(Deductions!$D$5:$D$2000,Deductions!$B$5:$B$2000,$A14,Deductions!$C$5:$C$2000,"Advance",Deductions!$E$5:$E$2000,">="&Settings!$B$8,Deductions!$E$5:$E$2000,"<="&Settings!$B$9)) -> 0 | P14: =IF($A14="","",SUMIFS(Deductions!$D$5:$D$2000,Deductions!$B$5:$B$2000,$A14,Deductions!$E$5:$E$2000,">="&Settings!$B$8,Deductions!$E$5:$E$2000,"<="&Settings!$B$9)-O14) -> 0 | Q14: =IF($A14="","",O14+P14) -> 0 | R14: =IF($A14="","",N14-Q14) -> 2416.67 | S14: =IF($A14="","",INDEX(Workers!$O$5:$O$2004,MATCH($A14,Workers!$A$5:$A$2004,0))&"") -> 402320106 | T14: =IF($A14="","",INDEX(Workers!$P$5:$P$2004,MATCH($A14,Workers!$A$5:$A$2004,0))&"") -> AE22 7525 8983 3667 4665 265 | U14: =IF($A14="","",INDEX(Workers!$H$5:$H$2004,MATCH($A14,Workers!$A$5:$A$2004,0))&"") -> 40904298604831
A15: =IFERROR(INDEX(Workers!$A$5:$A$2004,MATCH(ROW()-4,Workers!$U$5:$U$2004,0)),"") -> W0011 | B15: =IF($A15="","",INDEX(Workers!$B$5:$B$2004,MATCH($A15,Workers!$A$5:$A$2004,0))) -> Dinesh Menon | C15: =IF($A15="","",INDEX(Workers!$E$5:$E$2004,MATCH($A15,Workers!$A$5:$A$2004,0))) -> Driver | D15: =IF($A15="","",INDEX(Workers!$K$5:$K$2004,MATCH($A15,Workers!$A$5:$A$2004,0))) -> Monthly | E15: =IF($A15="","",SUMIFS(Timesheet!$E$5:$E$3004,Timesheet!$D$5:$D$3004,$A15,Timesheet!$A$5:$A$3004,">="&Settings!$B$8,Timesheet!$A$5:$A$3004,"<="&Settings!$B$9)) -> 25 | F15: =IF($A15="","",SUMIFS(Timesheet!$F$5:$F$3004,Timesheet!$D$5:$D$3004,$A15,Timesheet!$A$5:$A$3004,">="&Settings!$B$8,Timesheet!$A$5:$A$3004,"<="&Settings!$B$9)) -> 200 | G15: =IF($A15="","",SUMIFS(Timesheet!$G$5:$G$3004,Timesheet!$D$5:$D$3004,$A15,Timesheet!$A$5:$A$3004,">="&Settings!$B$8,Timesheet!$A$5:$A$3004,"<="&Settings!$B$9)) -> 26 | H15: =IF($A15="","",IF(D15="Monthly",MAX(0,Settings!$B$11-E15),0)) -> 1 | I15: =IF($A15="","",N(INDEX(Workers!$L$5:$L$2004,MATCH($A15,Workers!$A$5:$A$2004,0)))) -> 1200 | J15: =IF($A15="","",N(INDEX(Workers!$M$5:$M$2004,MATCH($A15,Workers!$A$5:$A$2004,0)))) -> 300 | K15: =IF($A15="","",IF(D15="Monthly",ROUND(MAX(0,(I15+J15)-(I15+J15)/Settings!$B$10*H15),2),0)) -> 1450 | L15: =IF($A15="","",IF(D15="Hourly",ROUND(F15*N(INDEX(Workers!$N$5:$N$2004,MATCH($A15,Workers!$A$5:$A$2004,0))),2),0)) -> 0 | M15: =IF($A15="","",ROUND(G15*IF(D15="Hourly",N(INDEX(Workers!$N$5:$N$2004,MATCH($A15,Workers!$A$5:$A$2004,0))),I15/Settings!$B$10/Settings!$B$12)*Settings!$B$13,2)) -> 162.5 | N15: =IF($A15="","",K15+L15+M15) -> 1612.5 | O15: =IF($A15="","",SUMIFS(Deductions!$D$5:$D$2000,Deductions!$B$5:$B$2000,$A15,Deductions!$C$5:$C$2000,"Advance",Deductions!$E$5:$E$2000,">="&Settings!$B$8,Deductions!$E$5:$E$2000,"<="&Settings!$B$9)) -> 0 | P15: =IF($A15="","",SUMIFS(Deductions!$D$5:$D$2000,Deductions!$B$5:$B$2000,$A15,Deductions!$E$5:$E$2000,">="&Settings!$B$8,Deductions!$E$5:$E$2000,"<="&Settings!$B$9)-O15) -> 100 | Q15: =IF($A15="","",O15+P15) -> 100 | R15: =IF($A15="","",N15-Q15) -> 1512.5 | S15: =IF($A15="","",INDEX(Workers!$O$5:$O$2004,MATCH($A15,Workers!$A$5:$A$2004,0))&"") -> 402320106 | T15: =IF($A15="","",INDEX(Workers!$P$5:$P$2004,MATCH($A15,Workers!$A$5:$A$2004,0))&"") -> AE47 9392 2053 2848 4744 997 | U15: =IF($A15="","",INDEX(Workers!$H$5:$H$2004,MATCH($A15,Workers!$A$5:$A$2004,0))&"") -> 82822594276261
A16: =IFERROR(INDEX(Workers!$A$5:$A$2004,MATCH(ROW()-4,Workers!$U$5:$U$2004,0)),"") -> W0012 | B16: =IF($A16="","",INDEX(Workers!$B$5:$B$2004,MATCH($A16,Workers!$A$5:$A$2004,0))) -> Imran Ali | C16: =IF($A16="","",INDEX(Workers!$E$5:$E$2004,MATCH($A16,Workers!$A$5:$A$2004,0))) -> Helper | D16: =IF($A16="","",INDEX(Workers!$K$5:$K$2004,MATCH($A16,Workers!$A$5:$A$2004,0))) -> Monthly | E16: =IF($A16="","",SUMIFS(Timesheet!$E$5:$E$3004,Timesheet!$D$5:$D$3004,$A16,Timesheet!$A$5:$A$3004,">="&Settings!$B$8,Timesheet!$A$5:$A$3004,"<="&Settings!$B$9)) -> 22 | F16: =IF($A16="","",SUMIFS(Timesheet!$F$5:$F$3004,Timesheet!$D$5:$D$3004,$A16,Timesheet!$A$5:$A$3004,">="&Settings!$B$8,Timesheet!$A$5:$A$3004,"<="&Settings!$B$9)) -> 176 | G16: =IF($A16="","",SUMIFS(Timesheet!$G$5:$G$3004,Timesheet!$D$5:$D$3004,$A16,Timesheet!$A$5:$A$3004,">="&Settings!$B$8,Timesheet!$A$5:$A$3004,"<="&Settings!$B$9)) -> 16 | H16: =IF($A16="","",IF(D16="Monthly",MAX(0,Settings!$B$11-E16),0)) -> 4 | I16: =IF($A16="","",N(INDEX(Workers!$L$5:$L$2004,MATCH($A16,Workers!$A$5:$A$2004,0)))) -> 2000 | J16: =IF($A16="","",N(INDEX(Workers!$M$5:$M$2004,MATCH($A16,Workers!$A$5:$A$2004,0)))) -> 300 | K16: =IF($A16="","",IF(D16="Monthly",ROUND(MAX(0,(I16+J16)-(I16+J16)/Settings!$B$10*H16),2),0)) -> 1993.33 | L16: =IF($A16="","",IF(D16="Hourly",ROUND(F16*N(INDEX(Workers!$N$5:$N$2004,MATCH($A16,Workers!$A$5:$A$2004,0))),2),0)) -> 0 | M16: =IF($A16="","",ROUND(G16*IF(D16="Hourly",N(INDEX(Workers!$N$5:$N$2004,MATCH($A16,Workers!$A$5:$A$2004,0))),I16/Settings!$B$10/Settings!$B$12)*Settings!$B$13,2)) -> 166.67 | N16: =IF($A16="","",K16+L16+M16) -> 2160 | O16: =IF($A16="","",SUMIFS(Deductions!$D$5:$D$2000,Deductions!$B$5:$B$2000,$A16,Deductions!$C$5:$C$2000,"Advance",Deductions!$E$5:$E$2000,">="&Settings!$B$8,Deductions!$E$5:$E$2000,"<="&Settings!$B$9)) -> 0 | P16: =IF($A16="","",SUMIFS(Deductions!$D$5:$D$2000,Deductions!$B$5:$B$2000,$A16,Deductions!$E$5:$E$2000,">="&Settings!$B$8,Deductions!$E$5:$E$2000,"<="&Settings!$B$9)-O16) -> 0 | Q16: =IF($A16="","",O16+P16) -> 0 | R16: =IF($A16="","",N16-Q16) -> 2160 | S16: =IF($A16="","",INDEX(Workers!$O$5:$O$2004,MATCH($A16,Workers!$A$5:$A$2004,0))&"") -> 402320106 | T16: =IF($A16="","",INDEX(Workers!$P$5:$P$2004,MATCH($A16,Workers!$A$5:$A$2004,0))&"") -> AE33 7968 2186 5406 1275 749 | U16: =IF($A16="","",INDEX(Workers!$H$5:$H$2004,MATCH($A16,Workers!$A$5:$A$2004,0))&"") -> 18097211916423
... A1204: =IFERROR(INDEX(Workers!$A$5:$A$2004,MATCH(ROW()-4,Workers!$U$5:$U$2004,0)),"") | B1204: =IF($A1204="","",INDEX(Workers!$B$5:$B$2004,MATCH($A1204,Workers!$A$5:$A$2004,0))) | C1204: =IF($A1204="","",INDEX(Workers!$E$5:$E$2004,MATCH($A1204,Workers!$A$5:$A$2004,0))) | D1204: =IF($A1204="","",INDEX(Workers!$K$5:$K$2004,MATCH($A1204,Workers!$A$5:$A$2004,0))) | E1204: =IF($A1204="","",SUMIFS(Timesheet!$E$5:$E$3004,Timesheet!$D$5:$D$3004,$A1204,Timesheet!$A$5:$A$3004,">="&Settings!$B$8,Timesheet!$A$5:$A$3004,"<="&Settings!$B$9)) | F1204: =IF($A1204="","",SUMIFS(Timesheet!$F$5:$F$3004,Timesheet!$D$5:$D$3004,$A1204,Timesheet!$A$5:$A$3004,">="&Settings!$B$8,Timesheet!$A$5:$A$3004,"<="&Settings!$B$9)) | G1204: =IF($A1204="","",SUMIFS(Timesheet!$G$5:$G$3004,Timesheet!$D$5:$D$3004,$A1204,Timesheet!$A$5:$A$3004,">="&Settings!$B$8,Timesheet!$A$5:$A$3004,"<="&Settings!$B$9)) | H1204: =IF($A1204="","",IF(D1204="Monthly",MAX(0,Settings!$B$11-E1204),0)) | I1204: =IF($A1204="","",N(INDEX(Workers!$L$5:$L$2004,MATCH($A1204,Workers!$A$5:$A$2004,0)))) | J1204: =IF($A1204="","",N(INDEX(Workers!$M$5:$M$2004,MATCH($A1204,Workers!$A$5:$A$2004,0)))) | K1204: =IF($A1204="","",IF(D1204="Monthly",ROUND(MAX(0,(I1204+J1204)-(I1204+J1204)/Settings!$B$10*H1204),2),0)) | L1204: =IF($A1204="","",IF(D1204="Hourly",ROUND(F1204*N(INDEX(Workers!$N$5:$N$2004,MATCH($A1204,Workers!$A$5:$A$2004,0))),2),0)) | M1204: =IF($A1204="","",ROUND(G1204*IF(D1204="Hourly",N(INDEX(Workers!$N$5:$N$2004,MATCH($A1204,Workers!$A$5:$A$2004,0))),I1204/Settings!$B$10/Settings!$B$12)*Settings!$B$13,2)) | N1204: =IF($A1204="","",K1204+L1204+M1204) | O1204: =IF($A1204="","",SUMIFS(Deductions!$D$5:$D$2000,Deductions!$B$5:$B$2000,$A1204,Deductions!$C$5:$C$2000,"Advance",Deductions!$E$5:$E$2000,">="&Settings!$B$8,Deductions!$E$5:$E$2000,"<="&Settings!$B$9)) | P1204: =IF($A1204="","",SUMIFS(Deductions!$D$5:$D$2000,Deductions!$B$5:$B$2000,$A1204,Deductions!$E$5:$E$2000,">="&Settings!$B$8,Deductions!$E$5:$E$2000,"<="&Settings!$B$9)-O1204) | Q1204: =IF($A1204="","",O1204+P1204) | R1204: =IF($A1204="","",N1204-Q1204) | S1204: =IF($A1204="","",INDEX(Workers!$O$5:$O$2004,MATCH($A1204,Workers!$A$5:$A$2004,0))&"") | T1204: =IF($A1204="","",INDEX(Workers!$P$5:$P$2004,MATCH($A1204,Workers!$A$5:$A$2004,0))&"") | U1204: =IF($A1204="","",INDEX(Workers!$H$5:$H$2004,MATCH($A1204,Workers!$A$5:$A$2004,0))&"")

Sheet Payslip
B1: =Settings!$B$4 -> Gulf Star Manpower Services LLC | E1: « HOME
B2: ="PAYSLIP for "&TEXT(Settings!$B$8,"mmmm yyyy") -> PAYSLIP for October 2026
B4: Select Worker ID >> | C4: W0001
B6: Employee Name | C6: =IFERROR(INDEX(Payroll!$B$5:$B$1204,MATCH($C$4,Payroll!$A$5:$A$1204,0)),"") -> Marlon Khan | D6: EARNINGS (AED)
B7: Trade | C7: =IFERROR(INDEX(Payroll!$C$5:$C$1204,MATCH($C$4,Payroll!$A$5:$A$1204,0)),"") -> Steel Fixer | D7: Basic Salary | E7: =IFERROR(INDEX(Payroll!$I$5:$I$1204,MATCH($C$4,Payroll!$A$5:$A$1204,0)),"") -> 1400
B8: Pay Basis | C8: =IFERROR(INDEX(Payroll!$D$5:$D$1204,MATCH($C$4,Payroll!$A$5:$A$1204,0)),"") -> Monthly | D8: Allowances | E8: =IFERROR(INDEX(Payroll!$J$5:$J$1204,MATCH($C$4,Payroll!$A$5:$A$1204,0)),"") -> 400
B9: Labour Card / Person ID | C9: =IFERROR(INDEX(Payroll!$U$5:$U$1204,MATCH($C$4,Payroll!$A$5:$A$1204,0)),"") -> 96921334349946 | D9: Fixed Earned (after absence) | E9: =IFERROR(INDEX(Payroll!$K$5:$K$1204,MATCH($C$4,Payroll!$A$5:$A$1204,0)),"") -> 1800
B10: Bank IBAN | C10: =IFERROR(INDEX(Payroll!$T$5:$T$1204,MATCH($C$4,Payroll!$A$5:$A$1204,0)),"") -> AE96 1884 8481 7428 7521 508 | D10: Hourly Earnings | E10: =IFERROR(INDEX(Payroll!$L$5:$L$1204,MATCH($C$4,Payroll!$A$5:$A$1204,0)),"") -> 0
B11: Days Worked | C11: =IFERROR(INDEX(Payroll!$E$5:$E$1204,MATCH($C$4,Payroll!$A$5:$A$1204,0)),"") -> 26 | D11: Overtime Pay | E11: =IFERROR(INDEX(Payroll!$M$5:$M$1204,MATCH($C$4,Payroll!$A$5:$A$1204,0)),"") -> 189.58
B12: Absent Days | C12: =IFERROR(INDEX(Payroll!$H$5:$H$1204,MATCH($C$4,Payroll!$A$5:$A$1204,0)),"") -> 0 | D12: GROSS PAY | E12: =IFERROR(INDEX(Payroll!$N$5:$N$1204,MATCH($C$4,Payroll!$A$5:$A$1204,0)),"") -> 1989.58
B13: Normal Hours | C13: =IFERROR(INDEX(Payroll!$F$5:$F$1204,MATCH($C$4,Payroll!$A$5:$A$1204,0)),"") -> 208
B14: OT Hours | C14: =IFERROR(INDEX(Payroll!$G$5:$G$1204,MATCH($C$4,Payroll!$A$5:$A$1204,0)),"") -> 26 | D14: DEDUCTIONS (AED)
D15: Salary Advance | E15: =IFERROR(INDEX(Payroll!$O$5:$O$1204,MATCH($C$4,Payroll!$A$5:$A$1204,0)),"") -> 0
D16: Other Deductions | E16: =IFERROR(INDEX(Payroll!$P$5:$P$1204,MATCH($C$4,Payroll!$A$5:$A$1204,0)),"") -> 0
D17: TOTAL DEDUCTIONS | E17: =IFERROR(INDEX(Payroll!$Q$5:$Q$1204,MATCH($C$4,Payroll!$A$5:$A$1204,0)),"") -> 0
D19: NET PAY | E19: =IFERROR(INDEX(Payroll!$R$5:$R$1204,MATCH($C$4,Payroll!$A$5:$A$1204,0)),"") -> 1989.58
B22: Employee Signature: ____________________ | D22: Authorised Signatory: ____________________

Sheet ClientInvoice
B1: =Settings!$B$4 -> Gulf Star Manpower Services LLC | G1: TAX INVOICE | I1: « HOME
B2: ="TRN: "&Settings!$B$5 -> TRN: 100123456700003
B4: Select Client ID >> | C4: C001 | G4: Invoice No: | H4: ="INV-"&TEXT(Settings!$B$8,"yymm")&"-"&$C$4 -> INV-2610-C001
B5: Bill To: | C5: =IFERROR(INDEX(Clients!$B$5:$B$300,MATCH($C$4,Clients!$A$5:$A$300,0)),"") -> Al Waha Contracting LLC | G5: Invoice Date: | H5: =Settings!$B$9 -> 46326
B6: Client TRN: | C6: =IFERROR(INDEX(Clients!$C$5:$C$300,MATCH($C$4,Clients!$A$5:$A$300,0)),"") -> 100555111200003 | G6: Due Date: | H6: =IFERROR(Settings!$B$9+IFERROR(INDEX(Clients!$E$5:$E$300,MATCH($C$4,Clients!$A$5:$A$300,0)),""),"") -> 46356
G7: Period: | H7: =TEXT(Settings!$B$8,"mmm yyyy") -> Oct 2026
B9: Trade | C9: Workers | D9: Normal Hrs | E9: Rate / hr | F9: OT Hrs | G9: OT Rate | H9: Amount (AED)
B10: =Settings!$D$5 -> Helper | C10: =COUNTIFS(Timesheet!$B$5:$B$3004,$C$4,Timesheet!$L$5:$L$3004,$B10,Timesheet!$A$5:$A$3004,">="&Settings!$B$8,Timesheet!$A$5:$A$3004,"<="&Settings!$B$9) -> 2 | D10: =SUMIFS(Timesheet!$F$5:$F$3004,Timesheet!$B$5:$B$3004,$C$4,Timesheet!$L$5:$L$3004,$B10,Timesheet!$A$5:$A$3004,">="&Settings!$B$8,Timesheet!$A$5:$A$3004,"<="&Settings!$B$9) -> 408 | E10: =IFERROR(INDEX(ClientRates!$D$5:$D$500,MATCH($C$4&"|"&$B10,ClientRates!$A$5:$A$500,0)),0) -> 16 | F10: =SUMIFS(Timesheet!$G$5:$G$3004,Timesheet!$B$5:$B$3004,$C$4,Timesheet!$L$5:$L$3004,$B10,Timesheet!$A$5:$A$3004,">="&Settings!$B$8,Timesheet!$A$5:$A$3004,"<="&Settings!$B$9) -> 52 | G10: =IFERROR(INDEX(ClientRates!$E$5:$E$500,MATCH($C$4&"|"&$B10,ClientRates!$A$5:$A$500,0)),0) -> 20 | H10: =SUMIFS(Timesheet!$O$5:$O$3004,Timesheet!$B$5:$B$3004,$C$4,Timesheet!$L$5:$L$3004,$B10,Timesheet!$A$5:$A$3004,">="&Settings!$B$8,Timesheet!$A$5:$A$3004,"<="&Settings!$B$9) -> 7568
B11: =Settings!$D$6 -> Mason | C11: =COUNTIFS(Timesheet!$B$5:$B$3004,$C$4,Timesheet!$L$5:$L$3004,$B11,Timesheet!$A$5:$A$3004,">="&Settings!$B$8,Timesheet!$A$5:$A$3004,"<="&Settings!$B$9) -> 5 | D11: =SUMIFS(Timesheet!$F$5:$F$3004,Timesheet!$B$5:$B$3004,$C$4,Timesheet!$L$5:$L$3004,$B11,Timesheet!$A$5:$A$3004,">="&Settings!$B$8,Timesheet!$A$5:$A$3004,"<="&Settings!$B$9) -> 992 | E11: =IFERROR(INDEX(ClientRates!$D$5:$D$500,MATCH($C$4&"|"&$B11,ClientRates!$A$5:$A$500,0)),0) -> 22 | F11: =SUMIFS(Timesheet!$G$5:$G$3004,Timesheet!$B$5:$B$3004,$C$4,Timesheet!$L$5:$L$3004,$B11,Timesheet!$A$5:$A$3004,">="&Settings!$B$8,Timesheet!$A$5:$A$3004,"<="&Settings!$B$9) -> 98 | G11: =IFERROR(INDEX(ClientRates!$E$5:$E$500,MATCH($C$4&"|"&$B11,ClientRates!$A$5:$A$500,0)),0) -> 27.5 | H11: =SUMIFS(Timesheet!$O$5:$O$3004,Timesheet!$B$5:$B$3004,$C$4,Timesheet!$L$5:$L$3004,$B11,Timesheet!$A$5:$A$3004,">="&Settings!$B$8,Timesheet!$A$5:$A$3004,"<="&Settings!$B$9) -> 24519
B12: =Settings!$D$7 -> Carpenter | C12: =COUNTIFS(Timesheet!$B$5:$B$3004,$C$4,Timesheet!$L$5:$L$3004,$B12,Timesheet!$A$5:$A$3004,">="&Settings!$B$8,Timesheet!$A$5:$A$3004,"<="&Settings!$B$9) -> 2 | D12: =SUMIFS(Timesheet!$F$5:$F$3004,Timesheet!$B$5:$B$3004,$C$4,Timesheet!$L$5:$L$3004,$B12,Timesheet!$A$5:$A$3004,">="&Settings!$B$8,Timesheet!$A$5:$A$3004,"<="&Settings!$B$9) -> 384 | E12: =IFERROR(INDEX(ClientRates!$D$5:$D$500,MATCH($C$4&"|"&$B12,ClientRates!$A$5:$A$500,0)),0) -> 22 | F12: =SUMIFS(Timesheet!$G$5:$G$3004,Timesheet!$B$5:$B$3004,$C$4,Timesheet!$L$5:$L$3004,$B12,Timesheet!$A$5:$A$3004,">="&Settings!$B$8,Timesheet!$A$5:$A$3004,"<="&Settings!$B$9) -> 60 | G12: =IFERROR(INDEX(ClientRates!$E$5:$E$500,MATCH($C$4&"|"&$B12,ClientRates!$A$5:$A$500,0)),0) -> 27.5 | H12: =SUMIFS(Timesheet!$O$5:$O$3004,Timesheet!$B$5:$B$3004,$C$4,Timesheet!$L$5:$L$3004,$B12,Timesheet!$A$5:$A$3004,">="&Settings!$B$8,Timesheet!$A$5:$A$3004,"<="&Settings!$B$9) -> 10098
B13: =Settings!$D$8 -> Electrician | C13: =COUNTIFS(Timesheet!$B$5:$B$3004,$C$4,Timesheet!$L$5:$L$3004,$B13,Timesheet!$A$5:$A$3004,">="&Settings!$B$8,Timesheet!$A$5:$A$3004,"<="&Settings!$B$9) -> 3 | D13: =SUMIFS(Timesheet!$F$5:$F$3004,Timesheet!$B$5:$B$3004,$C$4,Timesheet!$L$5:$L$3004,$B13,Timesheet!$A$5:$A$3004,">="&Settings!$B$8,Timesheet!$A$5:$A$3004,"<="&Settings!$B$9) -> 536 | E13: =IFERROR(INDEX(ClientRates!$D$5:$D$500,MATCH($C$4&"|"&$B13,ClientRates!$A$5:$A$500,0)),0) -> 26 | F13: =SUMIFS(Timesheet!$G$5:$G$3004,Timesheet!$B$5:$B$3004,$C$4,Timesheet!$L$5:$L$3004,$B13,Timesheet!$A$5:$A$3004,">="&Settings!$B$8,Timesheet!$A$5:$A$3004,"<="&Settings!$B$9) -> 26 | G13: =IFERROR(INDEX(ClientRates!$E$5:$E$500,MATCH($C$4&"|"&$B13,ClientRates!$A$5:$A$500,0)),0) -> 32.5 | H13: =SUMIFS(Timesheet!$O$5:$O$3004,Timesheet!$B$5:$B$3004,$C$4,Timesheet!$L$5:$L$3004,$B13,Timesheet!$A$5:$A$3004,">="&Settings!$B$8,Timesheet!$A$5:$A$3004,"<="&Settings!$B$9) -> 14781
B14: =Settings!$D$9 -> Plumber | C14: =COUNTIFS(Timesheet!$B$5:$B$3004,$C$4,Timesheet!$L$5:$L$3004,$B14,Timesheet!$A$5:$A$3004,">="&Settings!$B$8,Timesheet!$A$5:$A$3004,"<="&Settings!$B$9) -> 3 | D14: =SUMIFS(Timesheet!$F$5:$F$3004,Timesheet!$B$5:$B$3004,$C$4,Timesheet!$L$5:$L$3004,$B14,Timesheet!$A$5:$A$3004,">="&Settings!$B$8,Timesheet!$A$5:$A$3004,"<="&Settings!$B$9) -> 464 | E14: =IFERROR(INDEX(ClientRates!$D$5:$D$500,MATCH($C$4&"|"&$B14,ClientRates!$A$5:$A$500,0)),0) -> 25 | F14: =SUMIFS(Timesheet!$G$5:$G$3004,Timesheet!$B$5:$B$3004,$C$4,Timesheet!$L$5:$L$3004,$B14,Timesheet!$A$5:$A$3004,">="&Settings!$B$8,Timesheet!$A$5:$A$3004,"<="&Settings!$B$9) -> 36 | G14: =IFERROR(INDEX(ClientRates!$E$5:$E$500,MATCH($C$4&"|"&$B14,ClientRates!$A$5:$A$500,0)),0) -> 31.25 | H14: =SUMIFS(Timesheet!$O$5:$O$3004,Timesheet!$B$5:$B$3004,$C$4,Timesheet!$L$5:$L$3004,$B14,Timesheet!$A$5:$A$3004,">="&Settings!$B$8,Timesheet!$A$5:$A$3004,"<="&Settings!$B$9) -> 12725
B15: =Settings!$D$10 -> Steel Fixer | C15: =COUNTIFS(Timesheet!$B$5:$B$3004,$C$4,Timesheet!$L$5:$L$3004,$B15,Timesheet!$A$5:$A$3004,">="&Settings!$B$8,Timesheet!$A$5:$A$3004,"<="&Settings!$B$9) -> 0 | D15: =SUMIFS(Timesheet!$F$5:$F$3004,Timesheet!$B$5:$B$3004,$C$4,Timesheet!$L$5:$L$3004,$B15,Timesheet!$A$5:$A$3004,">="&Settings!$B$8,Timesheet!$A$5:$A$3004,"<="&Settings!$B$9) -> 0 | E15: =IFERROR(INDEX(ClientRates!$D$5:$D$500,MATCH($C$4&"|"&$B15,ClientRates!$A$5:$A$500,0)),0) -> 23 | F15: =SUMIFS(Timesheet!$G$5:$G$3004,Timesheet!$B$5:$B$3004,$C$4,Timesheet!$L$5:$L$3004,$B15,Timesheet!$A$5:$A$3004,">="&Settings!$B$8,Timesheet!$A$5:$A$3004,"<="&Settings!$B$9) -> 0 | G15: =IFERROR(INDEX(ClientRates!$E$5:$E$500,MATCH($C$4&"|"&$B15,ClientRates!$A$5:$A$500,0)),0) -> 28.75 | H15: =SUMIFS(Timesheet!$O$5:$O$3004,Timesheet!$B$5:$B$3004,$C$4,Timesheet!$L$5:$L$3004,$B15,Timesheet!$A$5:$A$3004,">="&Settings!$B$8,Timesheet!$A$5:$A$3004,"<="&Settings!$B$9) -> 0
B16: =Settings!$D$11 -> Driver | C16: =COUNTIFS(Timesheet!$B$5:$B$3004,$C$4,Timesheet!$L$5:$L$3004,$B16,Timesheet!$A$5:$A$3004,">="&Settings!$B$8,Timesheet!$A$5:$A$3004,"<="&Settings!$B$9) -> 3 | D16: =SUMIFS(Timesheet!$F$5:$F$3004,Timesheet!$B$5:$B$3004,$C$4,Timesheet!$L$5:$L$3004,$B16,Timesheet!$A$5:$A$3004,">="&Settings!$B$8,Timesheet!$A$5:$A$3004,"<="&Settings!$B$9) -> 552 | E16: =IFERROR(INDEX(ClientRates!$D$5:$D$500,MATCH($C$4&"|"&$B16,ClientRates!$A$5:$A$500,0)),0) -> 24 | F16: =SUMIFS(Timesheet!$G$5:$G$3004,Timesheet!$B$5:$B$3004,$C$4,Timesheet!$L$5:$L$3004,$B16,Timesheet!$A$5:$A$3004,">="&Settings!$B$8,Timesheet!$A$5:$A$3004,"<="&Settings!$B$9) -> 16 | G16: =IFERROR(INDEX(ClientRates!$E$5:$E$500,MATCH($C$4&"|"&$B16,ClientRates!$A$5:$A$500,0)),0) -> 30 | H16: =SUMIFS(Timesheet!$O$5:$O$3004,Timesheet!$B$5:$B$3004,$C$4,Timesheet!$L$5:$L$3004,$B16,Timesheet!$A$5:$A$3004,">="&Settings!$B$8,Timesheet!$A$5:$A$3004,"<="&Settings!$B$9) -> 13728
B17: =Settings!$D$12 -> Cleaner | C17: =COUNTIFS(Timesheet!$B$5:$B$3004,$C$4,Timesheet!$L$5:$L$3004,$B17,Timesheet!$A$5:$A$3004,">="&Settings!$B$8,Timesheet!$A$5:$A$3004,"<="&Settings!$B$9) -> 4 | D17: =SUMIFS(Timesheet!$F$5:$F$3004,Timesheet!$B$5:$B$3004,$C$4,Timesheet!$L$5:$L$3004,$B17,Timesheet!$A$5:$A$3004,">="&Settings!$B$8,Timesheet!$A$5:$A$3004,"<="&Settings!$B$9) -> 624 | E17: =IFERROR(INDEX(ClientRates!$D$5:$D$500,MATCH($C$4&"|"&$B17,ClientRates!$A$5:$A$500,0)),0) -> 15 | F17: =SUMIFS(Timesheet!$G$5:$G$3004,Timesheet!$B$5:$B$3004,$C$4,Timesheet!$L$5:$L$3004,$B17,Timesheet!$A$5:$A$3004,">="&Settings!$B$8,Timesheet!$A$5:$A$3004,"<="&Settings!$B$9) -> 92 | G17: =IFERROR(INDEX(ClientRates!$E$5:$E$500,MATCH($C$4&"|"&$B17,ClientRates!$A$5:$A$500,0)),0) -> 18.75 | H17: =SUMIFS(Timesheet!$O$5:$O$3004,Timesheet!$B$5:$B$3004,$C$4,Timesheet!$L$5:$L$3004,$B17,Timesheet!$A$5:$A$3004,">="&Settings!$B$8,Timesheet!$A$5:$A$3004,"<="&Settings!$B$9) -> 11085
B18: =Settings!$D$13 -> Security Guard | C18: =COUNTIFS(Timesheet!$B$5:$B$3004,$C$4,Timesheet!$L$5:$L$3004,$B18,Timesheet!$A$5:$A$3004,">="&Settings!$B$8,Timesheet!$A$5:$A$3004,"<="&Settings!$B$9) -> 1 | D18: =SUMIFS(Timesheet!$F$5:$F$3004,Timesheet!$B$5:$B$3004,$C$4,Timesheet!$L$5:$L$3004,$B18,Timesheet!$A$5:$A$3004,">="&Settings!$B$8,Timesheet!$A$5:$A$3004,"<="&Settings!$B$9) -> 176 | E18: =IFERROR(INDEX(ClientRates!$D$5:$D$500,MATCH($C$4&"|"&$B18,ClientRates!$A$5:$A$500,0)),0) -> 17 | F18: =SUMIFS(Timesheet!$G$5:$G$3004,Timesheet!$B$5:$B$3004,$C$4,Timesheet!$L$5:$L$3004,$B18,Timesheet!$A$5:$A$3004,">="&Settings!$B$8,Timesheet!$A$5:$A$3004,"<="&Settings!$B$9) -> 20 | G18: =IFERROR(INDEX(ClientRates!$E$5:$E$500,MATCH($C$4&"|"&$B18,ClientRates!$A$5:$A$500,0)),0) -> 21.25 | H18: =SUMIFS(Timesheet!$O$5:$O$3004,Timesheet!$B$5:$B$3004,$C$4,Timesheet!$L$5:$L$3004,$B18,Timesheet!$A$5:$A$3004,">="&Settings!$B$8,Timesheet!$A$5:$A$3004,"<="&Settings!$B$9) -> 3417
B20: Total hours: | C20: =SUM(D10:D18)+SUM(F10:F18) -> 4536 | G20: Sub Total | H20: =SUM(H10:H18) -> 97921
G21: ="VAT "&TEXT(Settings!$B$14,"0%") -> VAT 5% | H21: =ROUND(H20*Settings!$B$14,2) -> 4896.05
G22: TOTAL (AED) | H22: =H20+H21 -> 102817.05
B24: Detailed worker-wise timesheet: filter the Timesheet sheet by this Client ID and attach.

Sheet SupplierStatement
A1: Supplier Payment Statement | D1: « HOME
A2: Amount payable to each supplier for the month in Settings!B8.
A3: TOTALS | C3: =SUM(C5:C54) -> 30 | D3: =SUM(D5:D54) -> 704 | E3: =SUM(E5:E54) -> 5632 | F3: =SUM(F5:F54) -> 488 | G3: =SUM(G5:G54) -> 99352.62 | H3: =SUM(H5:H54) -> 4967.63 | I3: =SUM(I5:I54) -> 104320.25
A4: Supplier ID | B4: Supplier Name | C4: Worker Lines | D4: Days | E4: Normal Hours | F4: OT Hours | G4: Amount (AED) | H4: VAT (AED) | I4: Total Payable (AED) | J4: Payment Terms | K4: Due Date
A5: =IF(Suppliers!A5="","",Suppliers!A5) -> S001 | B5: =IF($A5="","",Suppliers!B5) -> Desert Falcon Manpower Supply | C5: =IF($A5="","",COUNTIFS(Timesheet!$K$5:$K$3004,$A5,Timesheet!$A$5:$A$3004,">="&Settings!$B$8,Timesheet!$A$5:$A$3004,"<="&Settings!$B$9)) -> 10 | D5: =IF($A5="","",SUMIFS(Timesheet!$E$5:$E$3004,Timesheet!$K$5:$K$3004,$A5,Timesheet!$A$5:$A$3004,">="&Settings!$B$8,Timesheet!$A$5:$A$3004,"<="&Settings!$B$9)) -> 235 | E5: =IF($A5="","",SUMIFS(Timesheet!$F$5:$F$3004,Timesheet!$K$5:$K$3004,$A5,Timesheet!$A$5:$A$3004,">="&Settings!$B$8,Timesheet!$A$5:$A$3004,"<="&Settings!$B$9)) -> 1880 | F5: =IF($A5="","",SUMIFS(Timesheet!$G$5:$G$3004,Timesheet!$K$5:$K$3004,$A5,Timesheet!$A$5:$A$3004,">="&Settings!$B$8,Timesheet!$A$5:$A$3004,"<="&Settings!$B$9)) -> 144 | G5: =IF($A5="","",SUMIFS(Timesheet!$R$5:$R$3004,Timesheet!$K$5:$K$3004,$A5,Timesheet!$A$5:$A$3004,">="&Settings!$B$8,Timesheet!$A$5:$A$3004,"<="&Settings!$B$9)) -> 32654.16 | H5: =IF($A5="","",ROUND(G5*Settings!$B$14,2)) -> 1632.71 | I5: =IF($A5="","",G5+H5) -> 34286.87 | J5: =IF($A5="","",Suppliers!D5) -> 30 | K5: =IF($A5="","",Settings!$B$9+J5) -> 46356
A6: =IF(Suppliers!A6="","",Suppliers!A6) -> S002 | B6: =IF($A6="","",Suppliers!B6) -> Emirates Link Labour Services | C6: =IF($A6="","",COUNTIFS(Timesheet!$K$5:$K$3004,$A6,Timesheet!$A$5:$A$3004,">="&Settings!$B$8,Timesheet!$A$5:$A$3004,"<="&Settings!$B$9)) -> 10 | D6: =IF($A6="","",SUMIFS(Timesheet!$E$5:$E$3004,Timesheet!$K$5:$K$3004,$A6,Timesheet!$A$5:$A$3004,">="&Settings!$B$8,Timesheet!$A$5:$A$3004,"<="&Settings!$B$9)) -> 233 | E6: =IF($A6="","",SUMIFS(Timesheet!$F$5:$F$3004,Timesheet!$K$5:$K$3004,$A6,Timesheet!$A$5:$A$3004,">="&Settings!$B$8,Timesheet!$A$5:$A$3004,"<="&Settings!$B$9)) -> 1864 | F6: =IF($A6="","",SUMIFS(Timesheet!$G$5:$G$3004,Timesheet!$K$5:$K$3004,$A6,Timesheet!$A$5:$A$3004,">="&Settings!$B$8,Timesheet!$A$5:$A$3004,"<="&Settings!$B$9)) -> 152 | G6: =IF($A6="","",SUMIFS(Timesheet!$R$5:$R$3004,Timesheet!$K$5:$K$3004,$A6,Timesheet!$A$5:$A$3004,">="&Settings!$B$8,Timesheet!$A$5:$A$3004,"<="&Settings!$B$9)) -> 32642.88 | H6: =IF($A6="","",ROUND(G6*Settings!$B$14,2)) -> 1632.14 | I6: =IF($A6="","",G6+H6) -> 34275.02 | J6: =IF($A6="","",Suppliers!D6) -> 45 | K6: =IF($A6="","",Settings!$B$9+J6) -> 46371
A7: =IF(Suppliers!A7="","",Suppliers!A7) -> S003 | B7: =IF($A7="","",Suppliers!B7) -> Oasis Workforce Solutions | C7: =IF($A7="","",COUNTIFS(Timesheet!$K$5:$K$3004,$A7,Timesheet!$A$5:$A$3004,">="&Settings!$B$8,Timesheet!$A$5:$A$3004,"<="&Settings!$B$9)) -> 10 | D7: =IF($A7="","",SUMIFS(Timesheet!$E$5:$E$3004,Timesheet!$K$5:$K$3004,$A7,Timesheet!$A$5:$A$3004,">="&Settings!$B$8,Timesheet!$A$5:$A$3004,"<="&Settings!$B$9)) -> 236 | E7: =IF($A7="","",SUMIFS(Timesheet!$F$5:$F$3004,Timesheet!$K$5:$K$3004,$A7,Timesheet!$A$5:$A$3004,">="&Settings!$B$8,Timesheet!$A$5:$A$3004,"<="&Settings!$B$9)) -> 1888 | F7: =IF($A7="","",SUMIFS(Timesheet!$G$5:$G$3004,Timesheet!$K$5:$K$3004,$A7,Timesheet!$A$5:$A$3004,">="&Settings!$B$8,Timesheet!$A$5:$A$3004,"<="&Settings!$B$9)) -> 192 | G7: =IF($A7="","",SUMIFS(Timesheet!$R$5:$R$3004,Timesheet!$K$5:$K$3004,$A7,Timesheet!$A$5:$A$3004,">="&Settings!$B$8,Timesheet!$A$5:$A$3004,"<="&Settings!$B$9)) -> 34055.58 | H7: =IF($A7="","",ROUND(G7*Settings!$B$14,2)) -> 1702.78 | I7: =IF($A7="","",G7+H7) -> 35758.36 | J7: =IF($A7="","",Suppliers!D7) -> 30 | K7: =IF($A7="","",Settings!$B$9+J7) -> 46356
A8: =IF(Suppliers!A8="","",Suppliers!A8) | B8: =IF($A8="","",Suppliers!B8) | C8: =IF($A8="","",COUNTIFS(Timesheet!$K$5:$K$3004,$A8,Timesheet!$A$5:$A$3004,">="&Settings!$B$8,Timesheet!$A$5:$A$3004,"<="&Settings!$B$9)) | D8: =IF($A8="","",SUMIFS(Timesheet!$E$5:$E$3004,Timesheet!$K$5:$K$3004,$A8,Timesheet!$A$5:$A$3004,">="&Settings!$B$8,Timesheet!$A$5:$A$3004,"<="&Settings!$B$9)) | E8: =IF($A8="","",SUMIFS(Timesheet!$F$5:$F$3004,Timesheet!$K$5:$K$3004,$A8,Timesheet!$A$5:$A$3004,">="&Settings!$B$8,Timesheet!$A$5:$A$3004,"<="&Settings!$B$9)) | F8: =IF($A8="","",SUMIFS(Timesheet!$G$5:$G$3004,Timesheet!$K$5:$K$3004,$A8,Timesheet!$A$5:$A$3004,">="&Settings!$B$8,Timesheet!$A$5:$A$3004,"<="&Settings!$B$9)) | G8: =IF($A8="","",SUMIFS(Timesheet!$R$5:$R$3004,Timesheet!$K$5:$K$3004,$A8,Timesheet!$A$5:$A$3004,">="&Settings!$B$8,Timesheet!$A$5:$A$3004,"<="&Settings!$B$9)) | H8: =IF($A8="","",ROUND(G8*Settings!$B$14,2)) | I8: =IF($A8="","",G8+H8) | J8: =IF($A8="","",Suppliers!D8) | K8: =IF($A8="","",Settings!$B$9+J8)
A9: =IF(Suppliers!A9="","",Suppliers!A9) | B9: =IF($A9="","",Suppliers!B9) | C9: =IF($A9="","",COUNTIFS(Timesheet!$K$5:$K$3004,$A9,Timesheet!$A$5:$A$3004,">="&Settings!$B$8,Timesheet!$A$5:$A$3004,"<="&Settings!$B$9)) | D9: =IF($A9="","",SUMIFS(Timesheet!$E$5:$E$3004,Timesheet!$K$5:$K$3004,$A9,Timesheet!$A$5:$A$3004,">="&Settings!$B$8,Timesheet!$A$5:$A$3004,"<="&Settings!$B$9)) | E9: =IF($A9="","",SUMIFS(Timesheet!$F$5:$F$3004,Timesheet!$K$5:$K$3004,$A9,Timesheet!$A$5:$A$3004,">="&Settings!$B$8,Timesheet!$A$5:$A$3004,"<="&Settings!$B$9)) | F9: =IF($A9="","",SUMIFS(Timesheet!$G$5:$G$3004,Timesheet!$K$5:$K$3004,$A9,Timesheet!$A$5:$A$3004,">="&Settings!$B$8,Timesheet!$A$5:$A$3004,"<="&Settings!$B$9)) | G9: =IF($A9="","",SUMIFS(Timesheet!$R$5:$R$3004,Timesheet!$K$5:$K$3004,$A9,Timesheet!$A$5:$A$3004,">="&Settings!$B$8,Timesheet!$A$5:$A$3004,"<="&Settings!$B$9)) | H9: =IF($A9="","",ROUND(G9*Settings!$B$14,2)) | I9: =IF($A9="","",G9+H9) | J9: =IF($A9="","",Suppliers!D9) | K9: =IF($A9="","",Settings!$B$9+J9)
A10: =IF(Suppliers!A10="","",Suppliers!A10) | B10: =IF($A10="","",Suppliers!B10) | C10: =IF($A10="","",COUNTIFS(Timesheet!$K$5:$K$3004,$A10,Timesheet!$A$5:$A$3004,">="&Settings!$B$8,Timesheet!$A$5:$A$3004,"<="&Settings!$B$9)) | D10: =IF($A10="","",SUMIFS(Timesheet!$E$5:$E$3004,Timesheet!$K$5:$K$3004,$A10,Timesheet!$A$5:$A$3004,">="&Settings!$B$8,Timesheet!$A$5:$A$3004,"<="&Settings!$B$9)) | E10: =IF($A10="","",SUMIFS(Timesheet!$F$5:$F$3004,Timesheet!$K$5:$K$3004,$A10,Timesheet!$A$5:$A$3004,">="&Settings!$B$8,Timesheet!$A$5:$A$3004,"<="&Settings!$B$9)) | F10: =IF($A10="","",SUMIFS(Timesheet!$G$5:$G$3004,Timesheet!$K$5:$K$3004,$A10,Timesheet!$A$5:$A$3004,">="&Settings!$B$8,Timesheet!$A$5:$A$3004,"<="&Settings!$B$9)) | G10: =IF($A10="","",SUMIFS(Timesheet!$R$5:$R$3004,Timesheet!$K$5:$K$3004,$A10,Timesheet!$A$5:$A$3004,">="&Settings!$B$8,Timesheet!$A$5:$A$3004,"<="&Settings!$B$9)) | H10: =IF($A10="","",ROUND(G10*Settings!$B$14,2)) | I10: =IF($A10="","",G10+H10) | J10: =IF($A10="","",Suppliers!D10) | K10: =IF($A10="","",Settings!$B$9+J10)
A11: =IF(Suppliers!A11="","",Suppliers!A11) | B11: =IF($A11="","",Suppliers!B11) | C11: =IF($A11="","",COUNTIFS(Timesheet!$K$5:$K$3004,$A11,Timesheet!$A$5:$A$3004,">="&Settings!$B$8,Timesheet!$A$5:$A$3004,"<="&Settings!$B$9)) | D11: =IF($A11="","",SUMIFS(Timesheet!$E$5:$E$3004,Timesheet!$K$5:$K$3004,$A11,Timesheet!$A$5:$A$3004,">="&Settings!$B$8,Timesheet!$A$5:$A$3004,"<="&Settings!$B$9)) | E11: =IF($A11="","",SUMIFS(Timesheet!$F$5:$F$3004,Timesheet!$K$5:$K$3004,$A11,Timesheet!$A$5:$A$3004,">="&Settings!$B$8,Timesheet!$A$5:$A$3004,"<="&Settings!$B$9)) | F11: =IF($A11="","",SUMIFS(Timesheet!$G$5:$G$3004,Timesheet!$K$5:$K$3004,$A11,Timesheet!$A$5:$A$3004,">="&Settings!$B$8,Timesheet!$A$5:$A$3004,"<="&Settings!$B$9)) | G11: =IF($A11="","",SUMIFS(Timesheet!$R$5:$R$3004,Timesheet!$K$5:$K$3004,$A11,Timesheet!$A$5:$A$3004,">="&Settings!$B$8,Timesheet!$A$5:$A$3004,"<="&Settings!$B$9)) | H11: =IF($A11="","",ROUND(G11*Settings!$B$14,2)) | I11: =IF($A11="","",G11+H11) | J11: =IF($A11="","",Suppliers!D11) | K11: =IF($A11="","",Settings!$B$9+J11)
A12: =IF(Suppliers!A12="","",Suppliers!A12) | B12: =IF($A12="","",Suppliers!B12) | C12: =IF($A12="","",COUNTIFS(Timesheet!$K$5:$K$3004,$A12,Timesheet!$A$5:$A$3004,">="&Settings!$B$8,Timesheet!$A$5:$A$3004,"<="&Settings!$B$9)) | D12: =IF($A12="","",SUMIFS(Timesheet!$E$5:$E$3004,Timesheet!$K$5:$K$3004,$A12,Timesheet!$A$5:$A$3004,">="&Settings!$B$8,Timesheet!$A$5:$A$3004,"<="&Settings!$B$9)) | E12: =IF($A12="","",SUMIFS(Timesheet!$F$5:$F$3004,Timesheet!$K$5:$K$3004,$A12,Timesheet!$A$5:$A$3004,">="&Settings!$B$8,Timesheet!$A$5:$A$3004,"<="&Settings!$B$9)) | F12: =IF($A12="","",SUMIFS(Timesheet!$G$5:$G$3004,Timesheet!$K$5:$K$3004,$A12,Timesheet!$A$5:$A$3004,">="&Settings!$B$8,Timesheet!$A$5:$A$3004,"<="&Settings!$B$9)) | G12: =IF($A12="","",SUMIFS(Timesheet!$R$5:$R$3004,Timesheet!$K$5:$K$3004,$A12,Timesheet!$A$5:$A$3004,">="&Settings!$B$8,Timesheet!$A$5:$A$3004,"<="&Settings!$B$9)) | H12: =IF($A12="","",ROUND(G12*Settings!$B$14,2)) | I12: =IF($A12="","",G12+H12) | J12: =IF($A12="","",Suppliers!D12) | K12: =IF($A12="","",Settings!$B$9+J12)
A13: =IF(Suppliers!A13="","",Suppliers!A13) | B13: =IF($A13="","",Suppliers!B13) | C13: =IF($A13="","",COUNTIFS(Timesheet!$K$5:$K$3004,$A13,Timesheet!$A$5:$A$3004,">="&Settings!$B$8,Timesheet!$A$5:$A$3004,"<="&Settings!$B$9)) | D13: =IF($A13="","",SUMIFS(Timesheet!$E$5:$E$3004,Timesheet!$K$5:$K$3004,$A13,Timesheet!$A$5:$A$3004,">="&Settings!$B$8,Timesheet!$A$5:$A$3004,"<="&Settings!$B$9)) | E13: =IF($A13="","",SUMIFS(Timesheet!$F$5:$F$3004,Timesheet!$K$5:$K$3004,$A13,Timesheet!$A$5:$A$3004,">="&Settings!$B$8,Timesheet!$A$5:$A$3004,"<="&Settings!$B$9)) | F13: =IF($A13="","",SUMIFS(Timesheet!$G$5:$G$3004,Timesheet!$K$5:$K$3004,$A13,Timesheet!$A$5:$A$3004,">="&Settings!$B$8,Timesheet!$A$5:$A$3004,"<="&Settings!$B$9)) | G13: =IF($A13="","",SUMIFS(Timesheet!$R$5:$R$3004,Timesheet!$K$5:$K$3004,$A13,Timesheet!$A$5:$A$3004,">="&Settings!$B$8,Timesheet!$A$5:$A$3004,"<="&Settings!$B$9)) | H13: =IF($A13="","",ROUND(G13*Settings!$B$14,2)) | I13: =IF($A13="","",G13+H13) | J13: =IF($A13="","",Suppliers!D13) | K13: =IF($A13="","",Settings!$B$9+J13)
A14: =IF(Suppliers!A14="","",Suppliers!A14) | B14: =IF($A14="","",Suppliers!B14) | C14: =IF($A14="","",COUNTIFS(Timesheet!$K$5:$K$3004,$A14,Timesheet!$A$5:$A$3004,">="&Settings!$B$8,Timesheet!$A$5:$A$3004,"<="&Settings!$B$9)) | D14: =IF($A14="","",SUMIFS(Timesheet!$E$5:$E$3004,Timesheet!$K$5:$K$3004,$A14,Timesheet!$A$5:$A$3004,">="&Settings!$B$8,Timesheet!$A$5:$A$3004,"<="&Settings!$B$9)) | E14: =IF($A14="","",SUMIFS(Timesheet!$F$5:$F$3004,Timesheet!$K$5:$K$3004,$A14,Timesheet!$A$5:$A$3004,">="&Settings!$B$8,Timesheet!$A$5:$A$3004,"<="&Settings!$B$9)) | F14: =IF($A14="","",SUMIFS(Timesheet!$G$5:$G$3004,Timesheet!$K$5:$K$3004,$A14,Timesheet!$A$5:$A$3004,">="&Settings!$B$8,Timesheet!$A$5:$A$3004,"<="&Settings!$B$9)) | G14: =IF($A14="","",SUMIFS(Timesheet!$R$5:$R$3004,Timesheet!$K$5:$K$3004,$A14,Timesheet!$A$5:$A$3004,">="&Settings!$B$8,Timesheet!$A$5:$A$3004,"<="&Settings!$B$9)) | H14: =IF($A14="","",ROUND(G14*Settings!$B$14,2)) | I14: =IF($A14="","",G14+H14) | J14: =IF($A14="","",Suppliers!D14) | K14: =IF($A14="","",Settings!$B$9+J14)
A15: =IF(Suppliers!A15="","",Suppliers!A15) | B15: =IF($A15="","",Suppliers!B15) | C15: =IF($A15="","",COUNTIFS(Timesheet!$K$5:$K$3004,$A15,Timesheet!$A$5:$A$3004,">="&Settings!$B$8,Timesheet!$A$5:$A$3004,"<="&Settings!$B$9)) | D15: =IF($A15="","",SUMIFS(Timesheet!$E$5:$E$3004,Timesheet!$K$5:$K$3004,$A15,Timesheet!$A$5:$A$3004,">="&Settings!$B$8,Timesheet!$A$5:$A$3004,"<="&Settings!$B$9)) | E15: =IF($A15="","",SUMIFS(Timesheet!$F$5:$F$3004,Timesheet!$K$5:$K$3004,$A15,Timesheet!$A$5:$A$3004,">="&Settings!$B$8,Timesheet!$A$5:$A$3004,"<="&Settings!$B$9)) | F15: =IF($A15="","",SUMIFS(Timesheet!$G$5:$G$3004,Timesheet!$K$5:$K$3004,$A15,Timesheet!$A$5:$A$3004,">="&Settings!$B$8,Timesheet!$A$5:$A$3004,"<="&Settings!$B$9)) | G15: =IF($A15="","",SUMIFS(Timesheet!$R$5:$R$3004,Timesheet!$K$5:$K$3004,$A15,Timesheet!$A$5:$A$3004,">="&Settings!$B$8,Timesheet!$A$5:$A$3004,"<="&Settings!$B$9)) | H15: =IF($A15="","",ROUND(G15*Settings!$B$14,2)) | I15: =IF($A15="","",G15+H15) | J15: =IF($A15="","",Suppliers!D15) | K15: =IF($A15="","",Settings!$B$9+J15)
A16: =IF(Suppliers!A16="","",Suppliers!A16) | B16: =IF($A16="","",Suppliers!B16) | C16: =IF($A16="","",COUNTIFS(Timesheet!$K$5:$K$3004,$A16,Timesheet!$A$5:$A$3004,">="&Settings!$B$8,Timesheet!$A$5:$A$3004,"<="&Settings!$B$9)) | D16: =IF($A16="","",SUMIFS(Timesheet!$E$5:$E$3004,Timesheet!$K$5:$K$3004,$A16,Timesheet!$A$5:$A$3004,">="&Settings!$B$8,Timesheet!$A$5:$A$3004,"<="&Settings!$B$9)) | E16: =IF($A16="","",SUMIFS(Timesheet!$F$5:$F$3004,Timesheet!$K$5:$K$3004,$A16,Timesheet!$A$5:$A$3004,">="&Settings!$B$8,Timesheet!$A$5:$A$3004,"<="&Settings!$B$9)) | F16: =IF($A16="","",SUMIFS(Timesheet!$G$5:$G$3004,Timesheet!$K$5:$K$3004,$A16,Timesheet!$A$5:$A$3004,">="&Settings!$B$8,Timesheet!$A$5:$A$3004,"<="&Settings!$B$9)) | G16: =IF($A16="","",SUMIFS(Timesheet!$R$5:$R$3004,Timesheet!$K$5:$K$3004,$A16,Timesheet!$A$5:$A$3004,">="&Settings!$B$8,Timesheet!$A$5:$A$3004,"<="&Settings!$B$9)) | H16: =IF($A16="","",ROUND(G16*Settings!$B$14,2)) | I16: =IF($A16="","",G16+H16) | J16: =IF($A16="","",Suppliers!D16) | K16: =IF($A16="","",Settings!$B$9+J16)
... A54: =IF(Suppliers!A54="","",Suppliers!A54) | B54: =IF($A54="","",Suppliers!B54) | C54: =IF($A54="","",COUNTIFS(Timesheet!$K$5:$K$3004,$A54,Timesheet!$A$5:$A$3004,">="&Settings!$B$8,Timesheet!$A$5:$A$3004,"<="&Settings!$B$9)) | D54: =IF($A54="","",SUMIFS(Timesheet!$E$5:$E$3004,Timesheet!$K$5:$K$3004,$A54,Timesheet!$A$5:$A$3004,">="&Settings!$B$8,Timesheet!$A$5:$A$3004,"<="&Settings!$B$9)) | E54: =IF($A54="","",SUMIFS(Timesheet!$F$5:$F$3004,Timesheet!$K$5:$K$3004,$A54,Timesheet!$A$5:$A$3004,">="&Settings!$B$8,Timesheet!$A$5:$A$3004,"<="&Settings!$B$9)) | F54: =IF($A54="","",SUMIFS(Timesheet!$G$5:$G$3004,Timesheet!$K$5:$K$3004,$A54,Timesheet!$A$5:$A$3004,">="&Settings!$B$8,Timesheet!$A$5:$A$3004,"<="&Settings!$B$9)) | G54: =IF($A54="","",SUMIFS(Timesheet!$R$5:$R$3004,Timesheet!$K$5:$K$3004,$A54,Timesheet!$A$5:$A$3004,">="&Settings!$B$8,Timesheet!$A$5:$A$3004,"<="&Settings!$B$9)) | H54: =IF($A54="","",ROUND(G54*Settings!$B$14,2)) | I54: =IF($A54="","",G54+H54) | J54: =IF($A54="","",Suppliers!D54) | K54: =IF($A54="","",Settings!$B$9+J54)

Sheet WPS_SIF
A1: WPS Salary Information File (SIF) - layout sample | G1: « HOME
A2: EDR rows per employee + SCR control row. Save as CSV named per bank rules. Verify field formats with your bank/exchange house.
A3: SCR | B3: =Settings!$B$6 -> 0000001234567 | C3: =Settings!$B$7 -> 803320101 | D3: =TEXT(TODAY(),"yyyy-mm-dd") -> 2026-11-01 | E3: =TEXT(NOW(),"hhmm") -> 0511 | F3: =TEXT(Settings!$B$8,"mmyyyy") -> 102026 | G3: =COUNTIF(A5:A1204,"EDR") -> 40 | H3: =SUM(H5:H1204)+SUM(I5:I1204) -> 87430.82 | I3: AED | J3: =Settings!$B$4 -> Gulf Star Manpower Services LLC
A4: Record | B4: Person ID / Labour Card | C4: Agent Routing Code | D4: IBAN | E4: Pay Start | F4: Pay End | G4: Days | H4: Fixed Salary | I4: Variable Salary | J4: Leave Days
A5: =IF(AND(Payroll!$A5<>"",N(Payroll!$R5)>0),"EDR","") -> EDR | B5: =IF($A5="","",Payroll!U5) -> 96921334349946 | C5: =IF($A5="","",Payroll!S5) -> 402320106 | D5: =IF($A5="","",SUBSTITUTE(Payroll!T5," ","")) -> AE961884848174287521508 | E5: =IF($A5="","",TEXT(Settings!$B$8,"yyyy-mm-dd")) -> 2026-10-01 | F5: =IF($A5="","",TEXT(Settings!$B$9,"yyyy-mm-dd")) -> 2026-10-31 | G5: =IF($A5="","",DAY(Settings!$B$9)) -> 31 | H5: =IF($A5="","",ROUND(Payroll!R5-Payroll!L5-Payroll!M5,2)) -> 1800 | I5: =IF($A5="","",ROUND(Payroll!L5+Payroll!M5,2)) -> 189.58 | J5: =IF($A5="","",0) -> 0
A6: =IF(AND(Payroll!$A6<>"",N(Payroll!$R6)>0),"EDR","") -> EDR | B6: =IF($A6="","",Payroll!U6) -> 24278776051635 | C6: =IF($A6="","",Payroll!S6) -> 600310101 | D6: =IF($A6="","",SUBSTITUTE(Payroll!T6," ","")) -> AE881417215244077164252 | E6: =IF($A6="","",TEXT(Settings!$B$8,"yyyy-mm-dd")) -> 2026-10-01 | F6: =IF($A6="","",TEXT(Settings!$B$9,"yyyy-mm-dd")) -> 2026-10-31 | G6: =IF($A6="","",DAY(Settings!$B$9)) -> 31 | H6: =IF($A6="","",ROUND(Payroll!R6-Payroll!L6-Payroll!M6,2)) -> 1343.33 | I6: =IF($A6="","",ROUND(Payroll!L6+Payroll!M6,2)) -> 162.5 | J6: =IF($A6="","",0) -> 0
A7: =IF(AND(Payroll!$A7<>"",N(Payroll!$R7)>0),"EDR","") -> EDR | B7: =IF($A7="","",Payroll!U7) -> 32723349357046 | C7: =IF($A7="","",Payroll!S7) -> 402320106 | D7: =IF($A7="","",SUBSTITUTE(Payroll!T7," ","")) -> AE124362965469263401806 | E7: =IF($A7="","",TEXT(Settings!$B$8,"yyyy-mm-dd")) -> 2026-10-01 | F7: =IF($A7="","",TEXT(Settings!$B$9,"yyyy-mm-dd")) -> 2026-10-31 | G7: =IF($A7="","",DAY(Settings!$B$9)) -> 31 | H7: =IF($A7="","",ROUND(Payroll!R7-Payroll!L7-Payroll!M7,2)) -> 1933.33 | I7: =IF($A7="","",ROUND(Payroll!L7+Payroll!M7,2)) -> 203.13 | J7: =IF($A7="","",0) -> 0
A8: =IF(AND(Payroll!$A8<>"",N(Payroll!$R8)>0),"EDR","") -> EDR | B8: =IF($A8="","",Payroll!U8) -> 41910762301181 | C8: =IF($A8="","",Payroll!S8) -> 803320101 | D8: =IF($A8="","",SUBSTITUTE(Payroll!T8," ","")) -> AE769073682514741457909 | E8: =IF($A8="","",TEXT(Settings!$B$8,"yyyy-mm-dd")) -> 2026-10-01 | F8: =IF($A8="","",TEXT(Settings!$B$9,"yyyy-mm-dd")) -> 2026-10-31 | G8: =IF($A8="","",DAY(Settings!$B$9)) -> 31 | H8: =IF($A8="","",ROUND(Payroll!R8-Payroll!L8-Payroll!M8,2)) -> 2146.67 | I8: =IF($A8="","",ROUND(Payroll!L8+Payroll!M8,2)) -> 166.67 | J8: =IF($A8="","",0) -> 0
A9: =IF(AND(Payroll!$A9<>"",N(Payroll!$R9)>0),"EDR","") -> EDR | B9: =IF($A9="","",Payroll!U9) -> 95890327812981 | C9: =IF($A9="","",Payroll!S9) -> 803320101 | D9: =IF($A9="","",SUBSTITUTE(Payroll!T9," ","")) -> AE716636238929647365901 | E9: =IF($A9="","",TEXT(Settings!$B$8,"yyyy-mm-dd")) -> 2026-10-01 | F9: =IF($A9="","",TEXT(Settings!$B$9,"yyyy-mm-dd")) -> 2026-10-31 | G9: =IF($A9="","",DAY(Settings!$B$9)) -> 31 | H9: =IF($A9="","",ROUND(Payroll!R9-Payroll!L9-Payroll!M9,2)) -> 1100 | I9: =IF($A9="","",ROUND(Payroll!L9+Payroll!M9,2)) -> 162.5 | J9: =IF($A9="","",0) -> 0
A10: =IF(AND(Payroll!$A10<>"",N(Payroll!$R10)>0),"EDR","") -> EDR | B10: =IF($A10="","",Payroll!U10) -> 96071772425721 | C10: =IF($A10="","",Payroll!S10) -> 402320106 | D10: =IF($A10="","",SUBSTITUTE(Payroll!T10," ","")) -> AE706741355499899983234 | E10: =IF($A10="","",TEXT(Settings!$B$8,"yyyy-mm-dd")) -> 2026-10-01 | F10: =IF($A10="","",TEXT(Settings!$B$9,"yyyy-mm-dd")) -> 2026-10-31 | G10: =IF($A10="","",DAY(Settings!$B$9)) -> 31 | H10: =IF($A10="","",ROUND(Payroll!R10-Payroll!L10-Payroll!M10,2)) -> 1300 | I10: =IF($A10="","",ROUND(Payroll!L10+Payroll!M10,2)) -> 0 | J10: =IF($A10="","",0) -> 0
A11: =IF(AND(Payroll!$A11<>"",N(Payroll!$R11)>0),"EDR","") -> EDR | B11: =IF($A11="","",Payroll!U11) -> 68972238951406 | C11: =IF($A11="","",Payroll!S11) -> 803320101 | D11: =IF($A11="","",SUBSTITUTE(Payroll!T11," ","")) -> AE176796850694667891946 | E11: =IF($A11="","",TEXT(Settings!$B$8,"yyyy-mm-dd")) -> 2026-10-01 | F11: =IF($A11="","",TEXT(Settings!$B$9,"yyyy-mm-dd")) -> 2026-10-31 | G11: =IF($A11="","",DAY(Settings!$B$9)) -> 31 | H11: =IF($A11="","",ROUND(Payroll!R11-Payroll!L11-Payroll!M11,2)) -> 2240 | I11: =IF($A11="","",ROUND(Payroll!L11+Payroll!M11,2)) -> 270.83 | J11: =IF($A11="","",0) -> 0
A12: =IF(AND(Payroll!$A12<>"",N(Payroll!$R12)>0),"EDR","") -> EDR | B12: =IF($A12="","",Payroll!U12) -> 84691707568212 | C12: =IF($A12="","",Payroll!S12) -> 402320106 | D12: =IF($A12="","",SUBSTITUTE(Payroll!T12," ","")) -> AE712738193050714134383 | E12: =IF($A12="","",TEXT(Settings!$B$8,"yyyy-mm-dd")) -> 2026-10-01 | F12: =IF($A12="","",TEXT(Settings!$B$9,"yyyy-mm-dd")) -> 2026-10-31 | G12: =IF($A12="","",DAY(Settings!$B$9)) -> 31 | H12: =IF($A12="","",ROUND(Payroll!R12-Payroll!L12-Payroll!M12,2)) -> 0 | I12: =IF($A12="","",ROUND(Payroll!L12+Payroll!M12,2)) -> 2097 | J12: =IF($A12="","",0) -> 0
A13: =IF(AND(Payroll!$A13<>"",N(Payroll!$R13)>0),"EDR","") -> EDR | B13: =IF($A13="","",Payroll!U13) -> 85052441044367 | C13: =IF($A13="","",Payroll!S13) -> 600310101 | D13: =IF($A13="","",SUBSTITUTE(Payroll!T13," ","")) -> AE745057957252534319960 | E13: =IF($A13="","",TEXT(Settings!$B$8,"yyyy-mm-dd")) -> 2026-10-01 | F13: =IF($A13="","",TEXT(Settings!$B$9,"yyyy-mm-dd")) -> 2026-10-31 | G13: =IF($A13="","",DAY(Settings!$B$9)) -> 31 | H13: =IF($A13="","",ROUND(Payroll!R13-Payroll!L13-Payroll!M13,2)) -> 2900 | I13: =IF($A13="","",ROUND(Payroll!L13+Payroll!M13,2)) -> 260.42 | J13: =IF($A13="","",0) -> 0
A14: =IF(AND(Payroll!$A14<>"",N(Payroll!$R14)>0),"EDR","") -> EDR | B14: =IF($A14="","",Payroll!U14) -> 40904298604831 | C14: =IF($A14="","",Payroll!S14) -> 402320106 | D14: =IF($A14="","",SUBSTITUTE(Payroll!T14," ","")) -> AE227525898336674665265 | E14: =IF($A14="","",TEXT(Settings!$B$8,"yyyy-mm-dd")) -> 2026-10-01 | F14: =IF($A14="","",TEXT(Settings!$B$9,"yyyy-mm-dd")) -> 2026-10-31 | G14: =IF($A14="","",DAY(Settings!$B$9)) -> 31 | H14: =IF($A14="","",ROUND(Payroll!R14-Payroll!L14-Payroll!M14,2)) -> 2416.67 | I14: =IF($A14="","",ROUND(Payroll!L14+Payroll!M14,2)) -> 0 | J14: =IF($A14="","",0) -> 0
A15: =IF(AND(Payroll!$A15<>"",N(Payroll!$R15)>0),"EDR","") -> EDR | B15: =IF($A15="","",Payroll!U15) -> 82822594276261 | C15: =IF($A15="","",Payroll!S15) -> 402320106 | D15: =IF($A15="","",SUBSTITUTE(Payroll!T15," ","")) -> AE479392205328484744997 | E15: =IF($A15="","",TEXT(Settings!$B$8,"yyyy-mm-dd")) -> 2026-10-01 | F15: =IF($A15="","",TEXT(Settings!$B$9,"yyyy-mm-dd")) -> 2026-10-31 | G15: =IF($A15="","",DAY(Settings!$B$9)) -> 31 | H15: =IF($A15="","",ROUND(Payroll!R15-Payroll!L15-Payroll!M15,2)) -> 1350 | I15: =IF($A15="","",ROUND(Payroll!L15+Payroll!M15,2)) -> 162.5 | J15: =IF($A15="","",0) -> 0
A16: =IF(AND(Payroll!$A16<>"",N(Payroll!$R16)>0),"EDR","") -> EDR | B16: =IF($A16="","",Payroll!U16) -> 18097211916423 | C16: =IF($A16="","",Payroll!S16) -> 402320106 | D16: =IF($A16="","",SUBSTITUTE(Payroll!T16," ","")) -> AE337968218654061275749 | E16: =IF($A16="","",TEXT(Settings!$B$8,"yyyy-mm-dd")) -> 2026-10-01 | F16: =IF($A16="","",TEXT(Settings!$B$9,"yyyy-mm-dd")) -> 2026-10-31 | G16: =IF($A16="","",DAY(Settings!$B$9)) -> 31 | H16: =IF($A16="","",ROUND(Payroll!R16-Payroll!L16-Payroll!M16,2)) -> 1993.33 | I16: =IF($A16="","",ROUND(Payroll!L16+Payroll!M16,2)) -> 166.67 | J16: =IF($A16="","",0) -> 0
... A1204: =IF(AND(Payroll!$A1204<>"",N(Payroll!$R1204)>0),"EDR","") | B1204: =IF($A1204="","",Payroll!U1204) | C1204: =IF($A1204="","",Payroll!S1204) | D1204: =IF($A1204="","",SUBSTITUTE(Payroll!T1204," ","")) | E1204: =IF($A1204="","",TEXT(Settings!$B$8,"yyyy-mm-dd")) | F1204: =IF($A1204="","",TEXT(Settings!$B$9,"yyyy-mm-dd")) | G1204: =IF($A1204="","",DAY(Settings!$B$9)) | H1204: =IF($A1204="","",ROUND(Payroll!R1204-Payroll!L1204-Payroll!M1204,2)) | I1204: =IF($A1204="","",ROUND(Payroll!L1204+Payroll!M1204,2)) | J1204: =IF($A1204="","",0)
